Workbook

Sheet stata
A1: label | B1: idstudy | C1: pubyear | D1: reviewed | E1: dollaryear | F1: emissionyear | G1: tolweight | H1: scc | I1: sccmean | J1: sccbg | K1: sccmed | L1: stdev | M1: stdlow | N1: stdup | O1: iie | P1: mmi | Q1: dim | R1: sce | S1: fund | T1: dicerice | U1: page | V1: cdr | W1: prtp | X1: rra | Y1: growth | Z1: ies | AA1: eweight | AB1: climatesens | AC1: hope | AD1: nordhaus | AE1: tol | AF1: pigou | AG1: dataset | AH1: citations | AI1: sjr | AJ1: perstudy
A2: =+VLOOKUP(B2,studies!$A$2:$C$102,3) -> Nordhaus (1982) | B2: 1 | C2: 1982 | D2: 1 | E2: 1980 | F2: 1980 | G2: 0.5 | H2: 1984.9987 | I2: 0 | J2: 1 | K2: 0 | O2: 1 | P2: 0 | Q2: 0 | R2: 0 | S2: 0 | T2: 0 | U2: 0 | W2: 1 | Y2: 4 | AA2: 0 | AC2: 0 | AD2: 1 | AE2: 0 | AF2: 0 | AG2: 0 | AH2: 132 | AI2: 6.46 | AJ2: 2
A3: =+VLOOKUP(B3,studies!$A$2:$C$102,3) -> Nordhaus (1982) | B3: 1 | C3: 1982 | D3: 1 | E3: 1980 | F3: 1980 | G3: 0.5 | H3: 283.57124 | I3: 0 | J3: 1 | K3: 0 | O3: 1 | P3: 0 | Q3: 0 | R3: 0 | S3: 0 | T3: 0 | U3: 0 | W3: 1 | Y3: 1 | AA3: 0 | AC3: 0 | AD3: 1 | AE3: 0 | AF3: 0 | AG3: 0 | AH3: 132 | AI3: 6.46 | AJ3: 2
A4: =+VLOOKUP(B4,studies!$A$2:$C$102,3) -> Ayres & Walter (1991) | B4: 2 | C4: 1991 | D4: 1 | E4: 1989 | F4: 1990 | G4: 1 | H4: 450.7956 | I4: 0 | J4: 1 | K4: 0 | O4: 1 | P4: 0 | Q4: 0 | R4: 0 | S4: 0 | T4: 0 | U4: 0 | V4: 3 | W4: 1 | Y4: 0 | AA4: 0 | AC4: 0 | AD4: 0 | AE4: 0 | AF4: 0 | AG4: 0 | AH4: 220 | AI4: 1.65 | AJ4: 1
A5: =+VLOOKUP(B5,studies!$A$2:$C$102,3) -> Nordhaus (1991) | B5: 3 | C5: 1991 | D5: 1 | E5: 1989 | F5: 1990 | G5: 0.0625 | H5: 914.62959 | I5: 0 | J5: 1 | K5: 0 | O5: 1 | P5: 0 | Q5: 0 | R5: 0 | S5: 0 | T5: 1 | U5: 0 | V5: 1 | W5: 0 | X5: 1 | Y5: 1 | AA5: 0 | AC5: 0 | AD5: 1 | AE5: 0 | AF5: 0 | AG5: 0 | AH5: 1166 | AI5: 3.46 | AJ5: 9
A6: =+VLOOKUP(B6,studies!$A$2:$C$102,3) -> Nordhaus (1991) | B6: 3 | C6: 1991 | D6: 1 | E6: 1989 | F6: 1990 | G6: 0.125 | H6: 457.31479 | I6: 0 | J6: 1 | K6: 0 | O6: 1 | P6: 0 | Q6: 0 | R6: 0 | S6: 0 | T6: 1 | U6: 0 | V6: 1 | W6: 0 | X6: 1 | Y6: 1 | AA6: 0 | AC6: 0 | AD6: 1 | AE6: 0 | AF6: 0 | AG6: 0 | AH6: 1166 | AI6: 3.46 | AJ6: 9
A7: =+VLOOKUP(B7,studies!$A$2:$C$102,3) -> Nordhaus (1991) | B7: 3 | C7: 1991 | D7: 1 | E7: 1989 | F7: 1990 | G7: 0.0625 | H7: 114.29402 | I7: 0 | J7: 1 | K7: 0 | O7: 1 | P7: 0 | Q7: 0 | R7: 0 | S7: 0 | T7: 1 | U7: 0 | V7: 1 | W7: 0 | X7: 1 | Y7: 1 | AA7: 0 | AC7: 0 | AD7: 1 | AE7: 0 | AF7: 0 | AG7: 0 | AH7: 1166 | AI7: 3.46 | AJ7: 9
A8: =+VLOOKUP(B8,studies!$A$2:$C$102,3) -> Nordhaus (1991) | B8: 3 | C8: 1991 | D8: 1 | E8: 1989 | F8: 1990 | G8: 0.125 | H8: 203.20478 | I8: 0 | J8: 1 | K8: 0 | O8: 1 | P8: 0 | Q8: 0 | R8: 0 | S8: 0 | T8: 1 | U8: 0 | V8: 3 | W8: 1 | X8: 1 | Y8: 2 | AA8: 0 | AC8: 0 | AD8: 1 | AE8: 0 | AF8: 0 | AG8: 0 | AH8: 1166 | AI8: 3.46 | AJ8: 9
A9: =+VLOOKUP(B9,studies!$A$2:$C$102,3) -> Nordhaus (1991) | B9: 3 | C9: 1991 | D9: 1 | E9: 1989 | F9: 1990 | G9: 0.25 | H9: 101.67175 | I9: 0 | J9: 1 | K9: 0 | O9: 1 | P9: 0 | Q9: 0 | R9: 0 | S9: 0 | T9: 1 | U9: 0 | V9: 3 | W9: 1 | X9: 1 | Y9: 2 | AA9: 0 | AC9: 0 | AD9: 1 | AE9: 0 | AF9: 0 | AG9: 0 | AH9: 1166 | AI9: 3.46 | AJ9: 9
A10: =+VLOOKUP(B10,studies!$A$2:$C$102,3) -> Nordhaus (1991) | B10: 3 | C10: 1991 | D10: 1 | E10: 1989 | F10: 1990 | G10: 0.125 | H10: 25.38326 | I10: 0 | J10: 1 | K10: 0 | O10: 1 | P10: 0 | Q10: 0 | R10: 0 | S10: 0 | T10: 1 | U10: 0 | V10: 3 | W10: 1 | X10: 1 | Y10: 2 | AA10: 0 | AC10: 0 | AD10: 1 | AE10: 0 | AF10: 0 | AG10: 0 | AH10: 1166 | AI10: 3.46 | AJ10: 9
A11: =+VLOOKUP(B11,studies!$A$2:$C$102,3) -> Nordhaus (1991) | B11: 3 | C11: 1991 | D11: 1 | E11: 1989 | F11: 1990 | G11: 0.0625 | H11: 33.844346 | I11: 0 | J11: 1 | K11: 0 | O11: 1 | P11: 0 | Q11: 0 | R11: 0 | S11: 0 | T11: 1 | U11: 0 | V11: 7 | W11: 4 | X11: 1 | Y11: 3 | AA11: 0 | AC11: 0 | AD11: 1 | AE11: 0 | AF11: 0 | AG11: 0 | AH11: 1166 | AI11: 3.46 | AJ11: 9
A12: =+VLOOKUP(B12,studies!$A$2:$C$102,3) -> Nordhaus (1991) | B12: 3 | C12: 1991 | D12: 1 | E12: 1989 | F12: 1990 | G12: 0.125 | H12: 16.922173 | I12: 0 | J12: 1 | K12: 0 | O12: 1 | P12: 0 | Q12: 0 | R12: 0 | S12: 0 | T12: 1 | U12: 0 | V12: 7 | W12: 4 | X12: 1 | Y12: 3 | AA12: 0 | AC12: 0 | AD12: 1 | AE12: 0 | AF12: 0 | AG12: 0 | AH12: 1166 | AI12: 3.46 | AJ12: 9
A13: =+VLOOKUP(B13,studies!$A$2:$C$102,3) -> Nordhaus (1991) | B13: 3 | C13: 1991 | D13: 1 | E13: 1989 | F13: 1990 | G13: 0.0625 | H13: 4.2998965 | I13: 0 | J13: 1 | K13: 0 | O13: 1 | P13: 0 | Q13: 0 | R13: 0 | S13: 0 | T13: 1 | U13: 0 | V13: 7 | W13: 4 | X13: 1 | Y13: 3 | AA13: 0 | AC13: 0 | AD13: 1 | AE13: 0 | AF13: 0 | AG13: 0 | AH13: 1166 | AI13: 3.46 | AJ13: 9
A14: =+VLOOKUP(B14,studies!$A$2:$C$102,3) -> Cline (1992) | B14: 4 | C14: 1992 | D14: 0 | E14: 1989 | F14: 1990 | G14: 1 | H14: 245.51022 | I14: 0 | J14: 1 | K14: 0 | L14: 111.7847 | M14: 114.06602 | N14: 114.06602 | O14: 1 | P14: 1 | Q14: 0 | R14: 1 | S14: 0 | T14: 0 | U14: 0 | V14: 1.5 | W14: 0 | X14: 1.5 | Y14: 1 | AA14: 0 | AC14: 0 | AD14: 0 | AE14: 0 | AF14: 0 | AG14: 0 | AH14: 39 | AI14: 0 | AJ14: 1
A15: =+VLOOKUP(B15,studies!$A$2:$C$102,3) -> Haraden (1992) | B15: 5 | C15: 1992 | D15: 1 | E15: 1984 | F15: 1987 | G15: 1 | H15: 72.59118 | I15: 0 | J15: 1 | K15: 0 | O15: 1 | P15: 0 | Q15: 0 | R15: 0 | S15: 0 | T15: 0 | U15: 0 | V15: 4 | W15: 2 | X15: 1 | Y15: 2 | AA15: 0 | AC15: 0 | AD15: 0 | AE15: 0 | AF15: 0 | AG15: 0 | AH15: 12 | AI15: 1.85 | AJ15: 1
A16: =+VLOOKUP(B16,studies!$A$2:$C$102,3) -> Hohmeyer & Gaertner (1992) | B16: 6 | C16: 1992 | D16: 0 | E16: 1990 | F16: 1990 | G16: 1 | H16: 6383.0401 | I16: 0 | J16: 1 | K16: 0 | O16: 1 | P16: 0 | Q16: 0 | R16: 1 | S16: 0 | T16: 0 | U16: 0 | V16: 0 | W16: 2 | AA16: 0 | AC16: 0 | AD16: 0 | AE16: 0 | AF16: 0 | AG16: 0 | AH16: 37 | AI16: 0 | AJ16: 1
A17: =+VLOOKUP(B17,studies!$A$2:$C$102,3) -> Penner et al. (1992) | B17: 7 | C17: 1992 | D17: 1 | E17: 1989 | F17: 1989 | G17: 0.25 | H17: 65.023092 | I17: 0 | J17: 1 | K17: 0 | O17: 0 | P17: 0 | Q17: 0 | R17: 0 | S17: 0 | T17: 1 | U17: 0 | V17: 4 | W17: 2 | AA17: 0 | AC17: 0 | AD17: 0 | AE17: 0 | AF17: 0 | AG17: 0 | AH17: 7 | AI17: 1.85 | AJ17: 1
A18: =+VLOOKUP(B18,studies!$A$2:$C$102,3) -> Haraden (1993) | B18: 8 | C18: 1993 | D18: 1 | E18: 1989 | F18: 1989 | G18: 0.25 | H18: 7.2161199 | I18: 0 | J18: 1 | K18: 0 | O18: 0 | P18: 0 | Q18: 0 | R18: 0 | S18: 0 | T18: 0 | U18: 0 | V18: 4 | W18: 2 | X18: 1.25 | Y18: 1.6 | AA18: 0 | AC18: 0 | AD18: 0 | AE18: 0 | AF18: 0 | AG18: 0 | AH18: 9 | AI18: 1.85 | AJ18: 3
A19: =+VLOOKUP(B19,studies!$A$2:$C$102,3) -> Haraden (1993) | B19: 8 | C19: 1993 | D19: 1 | E19: 1989 | F19: 1989 | G19: 0.5 | H19: 11.623804 | I19: 0 | J19: 1 | K19: 0 | O19: 0 | P19: 0 | Q19: 0 | R19: 0 | S19: 0 | T19: 0 | U19: 0 | V19: 4 | W19: 2 | X19: 0.86956522 | Y19: 2.3 | AA19: 0 | AC19: 0 | AD19: 0 | AE19: 0 | AF19: 0 | AG19: 0 | AH19: 9 | AI19: 1.85 | AJ19: 3
A20: =+VLOOKUP(B20,studies!$A$2:$C$102,3) -> Haraden (1993) | B20: 8 | C20: 1993 | D20: 1 | E20: 1989 | F20: 1989 | G20: 0.25 | H20: 34.247315 | I20: 0 | J20: 1 | K20: 0 | O20: 0 | P20: 0 | Q20: 0 | R20: 0 | S20: 0 | T20: 0 | U20: 0 | V20: 4 | W20: 2 | X20: 0.5 | Y20: 4 | AA20: 0 | AC20: 0 | AD20: 0 | AE20: 0 | AF20: 0 | AG20: 0 | AH20: 9 | AI20: 1.85 | AJ20: 3
A21: =+VLOOKUP(B21,studies!$A$2:$C$102,3) -> Nordhaus (1993) | B21: 9 | C21: 1993 | D21: 1 | E21: 1989 | F21: 1990 | G21: 1 | H21: 18.914501 | I21: 0 | J21: 1 | K21: 0 | O21: 0 | P21: 1 | Q21: 0 | R21: 1 | S21: 0 | T21: 1 | U21: 0 | V21: 5 | W21: 3 | AA21: 0 | AC21: 0 | AD21: 1 | AE21: 0 | AF21: 1 | AG21: 0 | AH21: 386 | AI21: 1.13 | AJ21: 1
A22: =+VLOOKUP(B22,studies!$A$2:$C$102,3) -> Parry (1993) | B22: 10 | C22: 1993 | D22: 1 | E22: 1991 | F22: 1990 | G22: 0.0089285714 | H22: 0.025256367 | I22: 0 | J22: 1 | K22: 0 | O22: 0 | P22: 1 | Q22: 0 | R22: 0 | S22: 0 | T22: 1 | U22: 0 | W22: 0 | AA22: 0 | AC22: 0 | AD22: 0 | AE22: 0 | AF22: 0 | AG22: 0 | AH22: 23 | AI22: 1.13 | AJ22: 60
A23: =+VLOOKUP(B23,studies!$A$2:$C$102,3) -> Parry (1993) | B23: 10 | C23: 1993 | D23: 1 | E23: 1991 | F23: 1990 | G23: 0.0089285714 | H23: 0.1515382 | I23: 0 | J23: 1 | K23: 0 | O23: 0 | P23: 1 | Q23: 0 | R23: 0 | S23: 0 | T23: 1 | U23: 0 | W23: 0 | AA23: 0 | AC23: 0 | AD23: 0 | AE23: 0 | AF23: 0 | AG23: 0 | AH23: 23 | AI23: 1.13 | AJ23: 60
A24: =+VLOOKUP(B24,studies!$A$2:$C$102,3) -> Parry (1993) | B24: 10 | C24: 1993 | D24: 1 | E24: 1991 | F24: 1990 | G24: 0.017857143 | H24: 0.03788455 | I24: 0 | J24: 1 | K24: 0 | O24: 0 | P24: 1 | Q24: 0 | R24: 0 | S24: 0 | T24: 1 | U24: 0 | W24: 0 | AA24: 0 | AC24: 0 | AD24: 0 | AE24: 0 | AF24: 0 | AG24: 0 | AH24: 23 | AI24: 1.13 | AJ24: 60
A25: =+VLOOKUP(B25,studies!$A$2:$C$102,3) -> Parry (1993) | B25: 10 | C25: 1993 | D25: 1 | E25: 1991 | F25: 1990 | G25: 0.017857143 | H25: 0.2273073 | I25: 0 | J25: 1 | K25: 0 | O25: 0 | P25: 1 | Q25: 0 | R25: 0 | S25: 0 | T25: 1 | U25: 0 | W25: 0 | AA25: 0 | AC25: 0 | AD25: 0 | AE25: 0 | AF25: 0 | AG25: 0 | AH25: 23 | AI25: 1.13 | AJ25: 60
A26: =+VLOOKUP(B26,studies!$A$2:$C$102,3) -> Parry (1993) | B26: 10 | C26: 1993 | D26: 1 | E26: 1991 | F26: 1990 | G26: 0.017857143 | H26: 0.075769101 | I26: 0 | J26: 1 | K26: 0 | O26: 0 | P26: 1 | Q26: 0 | R26: 0 | S26: 0 | T26: 1 | U26: 0 | W26: 0 | AA26: 0 | AC26: 0 | AD26: 0 | AE26: 0 | AF26: 0 | AG26: 0 | AH26: 23 | AI26: 1.13 | AJ26: 60
A27: =+VLOOKUP(B27,studies!$A$2:$C$102,3) -> Parry (1993) | B27: 10 | C27: 1993 | D27: 1 | E27: 1991 | F27: 1990 | G27: 0.017857143 | H27: 0.4546146 | I27: 0 | J27: 1 | K27: 0 | O27: 0 | P27: 1 | Q27: 0 | R27: 0 | S27: 0 | T27: 1 | U27: 0 | W27: 0 | AA27: 0 | AC27: 0 | AD27: 0 | AE27: 0 | AF27: 0 | AG27: 0 | AH27: 23 | AI27: 1.13 | AJ27: 60
A28: =+VLOOKUP(B28,studies!$A$2:$C$102,3) -> Parry (1993) | B28: 10 | C28: 1993 | D28: 1 | E28: 1991 | F28: 1990 | G28: 0.0089285714 | H28: 0.13891002 | I28: 0 | J28: 1 | K28: 0 | O28: 0 | P28: 1 | Q28: 0 | R28: 0 | S28: 0 | T28: 1 | U28: 0 | W28: 0 | AA28: 0 | AC28: 0 | AD28: 0 | AE28: 0 | AF28: 0 | AG28: 0 | AH28: 23 | AI28: 1.13 | AJ28: 60
A29: =+VLOOKUP(B29,studies!$A$2:$C$102,3) -> Parry (1993) | B29: 10 | C29: 1993 | D29: 1 | E29: 1991 | F29: 1990 | G29: 0.0089285714 | H29: 0.83346011 | I29: 0 | J29: 1 | K29: 0 | O29: 0 | P29: 1 | Q29: 0 | R29: 0 | S29: 0 | T29: 1 | U29: 0 | W29: 0 | AA29: 0 | AC29: 0 | AD29: 0 | AE29: 0 | AF29: 0 | AG29: 0 | AH29: 23 | AI29: 1.13 | AJ29: 60
A30: =+VLOOKUP(B30,studies!$A$2:$C$102,3) -> Parry (1993) | B30: 10 | C30: 1993 | D30: 1 | E30: 1991 | F30: 1990 | G30: 0.0089285714 | H30: 0.34096095 | I30: 0 | J30: 1 | K30: 0 | O30: 0 | P30: 1 | Q30: 0 | R30: 0 | S30: 0 | T30: 1 | U30: 0 | W30: 0 | AA30: 0 | AC30: 0 | AD30: 0 | AE30: 0 | AF30: 0 | AG30: 0 | AH30: 23 | AI30: 1.13 | AJ30: 60
A31: =+VLOOKUP(B31,studies!$A$2:$C$102,3) -> Parry (1993) | B31: 10 | C31: 1993 | D31: 1 | E31: 1991 | F31: 1990 | G31: 0.0089285714 | H31: 2.0457657 | I31: 0 | J31: 1 | K31: 0 | O31: 0 | P31: 1 | Q31: 0 | R31: 0 | S31: 0 | T31: 1 | U31: 0 | W31: 0 | AA31: 0 | AC31: 0 | AD31: 0 | AE31: 0 | AF31: 0 | AG31: 0 | AH31: 23 | AI31: 1.13 | AJ31: 60
A32: =+VLOOKUP(B32,studies!$A$2:$C$102,3) -> Parry (1993) | B32: 10 | C32: 1993 | D32: 1 | E32: 1991 | F32: 1990 | G32: 0.0089285714 | H32: 0.050512734 | I32: 0 | J32: 1 | K32: 0 | O32: 0 | P32: 1 | Q32: 0 | R32: 0 | S32: 0 | T32: 1 | U32: 0 | W32: 0 | AA32: 0 | AC32: 0 | AD32: 0 | AE32: 0 | AF32: 0 | AG32: 0 | AH32: 23 | AI32: 1.13 | AJ32: 60
A33: =+VLOOKUP(B33,studies!$A$2:$C$102,3) -> Parry (1993) | B33: 10 | C33: 1993 | D33: 1 | E33: 1991 | F33: 1990 | G33: 0.0089285714 | H33: 0.3030764 | I33: 0 | J33: 1 | K33: 0 | O33: 0 | P33: 1 | Q33: 0 | R33: 0 | S33: 0 | T33: 1 | U33: 0 | W33: 0 | AA33: 0 | AC33: 0 | AD33: 0 | AE33: 0 | AF33: 0 | AG33: 0 | AH33: 23 | AI33: 1.13 | AJ33: 60
... A81: =+VLOOKUP(B81,studies!$A$2:$C$102,3) -> Parry (1993) | B81: 10 | C81: 1993 | D81: 1 | E81: 1991 | F81: 1990 | G81: 0.0089285714 | H81: 10396.657 | I81: 0 | J81: 1 | K81: 0 | O81: 0 | P81: 1 | Q81: 0 | R81: 0 | S81: 0 | T81: 1 | U81: 0 | W81: 0 | AA81: 0 | AC81: 0 | AD81: 0 | AE81: 0 | AF81: 0 | AG81: 0 | AH81: 23 | AI81: 1.13 | AJ81: 60
A82: =+VLOOKUP(B82,studies!$A$2:$C$102,3) -> Peck & Teisberg (1993) | B82: 11 | C82: 1993 | D82: 1 | E82: 1989 | F82: 2030 | G82: 0.5 | H82: 11.105529 | I82: 0 | J82: 1 | K82: 0 | O82: 0 | P82: 1 | Q82: 0 | R82: 1 | S82: 0 | T82: 0 | U82: 0 | V82: 5 | W82: 3 | AA82: 0 | AC82: 0 | AD82: 0 | AE82: 0 | AF82: 1 | AG82: 0 | AH82: 198 | AI82: 1.13 | AJ82: 27
A83: =+VLOOKUP(B83,studies!$A$2:$C$102,3) -> Peck & Teisberg (1993) | B83: 11 | C83: 1993 | D83: 1 | E83: 1989 | F83: 2030 | G83: 0.019230769 | H83: 24.210053 | I83: 0 | J83: 1 | K83: 0 | O83: 0 | P83: 1 | Q83: 0 | R83: 1 | S83: 0 | T83: 0 | U83: 0 | V83: 5 | W83: 3 | AA83: 0 | AC83: 0 | AD83: 0 | AE83: 0 | AF83: 1 | AG83: 0 | AH83: 198 | AI83: 1.13 | AJ83: 27
A84: =+VLOOKUP(B84,studies!$A$2:$C$102,3) -> Peck & Teisberg (1993) | B84: 11 | C84: 1993 | D84: 1 | E84: 1989 | F84: 2030 | G84: 0.019230769 | H84: 24.543219 | I84: 0 | J84: 1 | K84: 0 | O84: 0 | P84: 1 | Q84: 0 | R84: 1 | S84: 0 | T84: 0 | U84: 0 | V84: 5 | W84: 3 | AA84: 0 | AC84: 0 | AD84: 0 | AE84: 0 | AF84: 1 | AG84: 0 | AH84: 198 | AI84: 1.13 | AJ84: 27
A85: =+VLOOKUP(B85,studies!$A$2:$C$102,3) -> Peck & Teisberg (1993) | B85: 11 | C85: 1993 | D85: 1 | E85: 1989 | F85: 2030 | G85: 0.019230769 | H85: 25.431661 | I85: 0 | J85: 1 | K85: 0 | O85: 0 | P85: 1 | Q85: 0 | R85: 1 | S85: 0 | T85: 0 | U85: 0 | V85: 5 | W85: 3 | AA85: 0 | AC85: 0 | AD85: 0 | AE85: 0 | AF85: 1 | AG85: 0 | AH85: 198 | AI85: 1.13 | AJ85: 27
A86: =+VLOOKUP(B86,studies!$A$2:$C$102,3) -> Peck & Teisberg (1993) | B86: 11 | C86: 1993 | D86: 1 | E86: 1989 | F86: 2030 | G86: 0.019230769 | H86: 24.210053 | I86: 0 | J86: 1 | K86: 0 | O86: 0 | P86: 1 | Q86: 0 | R86: 1 | S86: 0 | T86: 0 | U86: 0 | V86: 5 | W86: 3 | AA86: 0 | AC86: 0 | AD86: 0 | AE86: 0 | AF86: 1 | AG86: 0 | AH86: 198 | AI86: 1.13 | AJ86: 27
A87: =+VLOOKUP(B87,studies!$A$2:$C$102,3) -> Peck & Teisberg (1993) | B87: 11 | C87: 1993 | D87: 1 | E87: 1989 | F87: 2030 | G87: 0.019230769 | H87: 24.543219 | I87: 0 | J87: 1 | K87: 0 | O87: 0 | P87: 1 | Q87: 0 | R87: 1 | S87: 0 | T87: 0 | U87: 0 | V87: 5 | W87: 3 | AA87: 0 | AC87: 0 | AD87: 0 | AE87: 0 | AF87: 1 | AG87: 0 | AH87: 198 | AI87: 1.13 | AJ87: 27
A88: =+VLOOKUP(B88,studies!$A$2:$C$102,3) -> Peck & Teisberg (1993) | B88: 11 | C88: 1993 | D88: 1 | E88: 1989 | F88: 2030 | G88: 0.019230769 | H88: 3.7758798 | I88: 0 | J88: 1 | K88: 0 | O88: 0 | P88: 1 | Q88: 0 | R88: 1 | S88: 0 | T88: 0 | U88: 0 | V88: 5 | W88: 3 | AA88: 0 | AC88: 0 | AD88: 0 | AE88: 0 | AF88: 1 | AG88: 0 | AH88: 198 | AI88: 1.13 | AJ88: 27
A89: =+VLOOKUP(B89,studies!$A$2:$C$102,3) -> Peck & Teisberg (1993) | B89: 11 | C89: 1993 | D89: 1 | E89: 1989 | F89: 2030 | G89: 0.019230769 | H89: 6.1080409 | I89: 0 | J89: 1 | K89: 0 | O89: 0 | P89: 1 | Q89: 0 | R89: 1 | S89: 0 | T89: 0 | U89: 0 | V89: 5 | W89: 3 | AA89: 0 | AC89: 0 | AD89: 0 | AE89: 0 | AF89: 1 | AG89: 0 | AH89: 198 | AI89: 1.13 | AJ89: 27
A90: =+VLOOKUP(B90,studies!$A$2:$C$102,3) -> Peck & Teisberg (1993) | B90: 11 | C90: 1993 | D90: 1 | E90: 1989 | F90: 2030 | G90: 0.019230769 | H90: 13.326635 | I90: 0 | J90: 1 | K90: 0 | O90: 0 | P90: 1 | Q90: 0 | R90: 1 | S90: 0 | T90: 0 | U90: 0 | V90: 5 | W90: 3 | AA90: 0 | AC90: 0 | AD90: 0 | AE90: 0 | AF90: 1 | AG90: 0 | AH90: 198 | AI90: 1.13 | AJ90: 27
A91: =+VLOOKUP(B91,studies!$A$2:$C$102,3) -> Peck & Teisberg (1993) | B91: 11 | C91: 1993 | D91: 1 | E91: 1989 | F91: 2030 | G91: 0.019230769 | H91: 11.882916 | I91: 0 | J91: 1 | K91: 0 | O91: 0 | P91: 1 | Q91: 0 | R91: 1 | S91: 0 | T91: 0 | U91: 0 | V91: 5 | W91: 3 | AA91: 0 | AC91: 0 | AD91: 0 | AE91: 0 | AF91: 1 | AG91: 0 | AH91: 198 | AI91: 1.13 | AJ91: 27
A92: =+VLOOKUP(B92,studies!$A$2:$C$102,3) -> Peck & Teisberg (1993) | B92: 11 | C92: 1993 | D92: 1 | E92: 1989 | F92: 2030 | G92: 0.019230769 | H92: 21.21156 | I92: 0 | J92: 1 | K92: 0 | O92: 0 | P92: 1 | Q92: 0 | R92: 1 | S92: 0 | T92: 0 | U92: 0 | V92: 5 | W92: 3 | AA92: 0 | AC92: 0 | AD92: 0 | AE92: 0 | AF92: 1 | AG92: 0 | AH92: 198 | AI92: 1.13 | AJ92: 27
A93: =+VLOOKUP(B93,studies!$A$2:$C$102,3) -> Peck & Teisberg (1993) | B93: 11 | C93: 1993 | D93: 1 | E93: 1989 | F93: 2030 | G93: 0.019230769 | H93: 21.322615 | I93: 0 | J93: 1 | K93: 0 | O93: 0 | P93: 1 | Q93: 0 | R93: 1 | S93: 0 | T93: 0 | U93: 0 | V93: 5 | W93: 3 | AA93: 0 | AC93: 0 | AD93: 0 | AE93: 0 | AF93: 1 | AG93: 0 | AH93: 198 | AI93: 1.13 | AJ93: 27
... A106: =+VLOOKUP(B106,studies!$A$2:$C$102,3) -> Peck & Teisberg (1993) | B106: 11 | C106: 1993 | D106: 1 | E106: 1989 | F106: 2030 | G106: 0.019230769 | H106: 31.428647 | I106: 0 | J106: 1 | K106: 0 | O106: 0 | P106: 1 | Q106: 0 | R106: 1 | S106: 0 | T106: 0 | U106: 0 | V106: 5 | W106: 3 | AA106: 0 | AC106: 0 | AD106: 0 | AE106: 0 | AF106: 1 | AG106: 0 | AH106: 198 | AI106: 1.13 | AJ106: 27
A107: =+VLOOKUP(B107,studies!$A$2:$C$102,3) -> Peck & Teisberg (1993) | B107: 11 | C107: 1993 | D107: 1 | E107: 1989 | F107: 2030 | G107: 0.019230769 | H107: 13.992966 | I107: 0 | J107: 1 | K107: 0 | O107: 0 | P107: 1 | Q107: 0 | R107: 1 | S107: 0 | T107: 0 | U107: 0 | AA107: 0 | AC107: 0 | AD107: 0 | AE107: 0 | AF107: 1 | AG107: 0 | AH107: 198 | AI107: 1.13 | AJ107: 27
A108: =+VLOOKUP(B108,studies!$A$2:$C$102,3) -> Peck & Teisberg (1993) | B108: 11 | C108: 1993 | D108: 1 | E108: 1989 | F108: 2030 | G108: 0.019230769 | H108: 49.863825 | I108: 0 | J108: 1 | K108: 0 | O108: 0 | P108: 1 | Q108: 0 | R108: 1 | S108: 0 | T108: 0 | U108: 0 | AA108: 0 | AC108: 0 | AD108: 0 | AE108: 0 | AF108: 1 | AG108: 0 | AH108: 198 | AI108: 1.13 | AJ108: 27
A109: =+VLOOKUP(B109,studies!$A$2:$C$102,3) -> Reilly & Richards (1993) | B109: 12 | C109: 1993 | D109: 1 | E109: 1990 | F109: 1990 | G109: 0.2 | H109: 51.322406 | I109: 0 | J109: 1 | K109: 0 | O109: 0 | P109: 1 | Q109: 0 | R109: 0 | S109: 0 | T109: 0 | U109: 0 | V109: 5 | W109: 3 | AA109: 0 | AC109: 0 | AD109: 0 | AE109: 0 | AF109: 0 | AG109: 0 | AH109: 115 | AI109: 1.65 | AJ109: 8
A110: =+VLOOKUP(B110,studies!$A$2:$C$102,3) -> Reilly & Richards (1993) | B110: 12 | C110: 1993 | D110: 1 | E110: 1990 | F110: 1990 | G110: 0.2 | H110: 76.32563 | I110: 0 | J110: 1 | K110: 0 | O110: 0 | P110: 1 | Q110: 0 | R110: 0 | S110: 0 | T110: 0 | U110: 0 | V110: 5 | W110: 3 | AA110: 0 | AC110: 0 | AD110: 0 | AE110: 0 | AF110: 0 | AG110: 0 | AH110: 115 | AI110: 1.65 | AJ110: 8
A111: =+VLOOKUP(B111,studies!$A$2:$C$102,3) -> Reilly & Richards (1993) | B111: 12 | C111: 1993 | D111: 1 | E111: 1990 | F111: 1990 | G111: 0.1 | H111: 184.23428 | I111: 0 | J111: 1 | K111: 0 | O111: 0 | P111: 1 | Q111: 0 | R111: 0 | S111: 0 | T111: 0 | U111: 0 | V111: 2 | W111: 0 | AA111: 0 | AC111: 0 | AD111: 0 | AE111: 0 | AF111: 0 | AG111: 0 | AH111: 115 | AI111: 1.65 | AJ111: 8
A112: =+VLOOKUP(B112,studies!$A$2:$C$102,3) -> Reilly & Richards (1993) | B112: 12 | C112: 1993 | D112: 1 | E112: 1990 | F112: 1990 | G112: 0.1 | H112: 157.9151 | I112: 0 | J112: 1 | K112: 0 | O112: 0 | P112: 1 | Q112: 0 | R112: 0 | S112: 0 | T112: 0 | U112: 0 | V112: 2 | W112: 0 | AA112: 0 | AC112: 0 | AD112: 0 | AE112: 0 | AF112: 0 | AG112: 0 | AH112: 115 | AI112: 1.65 | AJ112: 8
A113: =+VLOOKUP(B113,studies!$A$2:$C$102,3) -> Reilly & Richards (1993) | B113: 12 | C113: 1993 | D113: 1 | E113: 1990 | F113: 1990 | G113: 0.1 | H113: 28.951101 | I113: 0 | J113: 1 | K113: 0 | O113: 0 | P113: 1 | Q113: 0 | R113: 0 | S113: 0 | T113: 0 | U113: 0 | V113: 8 | W113: 6 | AA113: 0 | AC113: 0 | AD113: 0 | AE113: 0 | AF113: 0 | AG113: 0 | AH113: 115 | AI113: 1.65 | AJ113: 8
A114: =+VLOOKUP(B114,studies!$A$2:$C$102,3) -> Reilly & Richards (1993) | B114: 12 | C114: 1993 | D114: 1 | E114: 1990 | F114: 1990 | G114: 0.1 | H114: 50.006447 | I114: 0 | J114: 1 | K114: 0 | O114: 0 | P114: 1 | Q114: 0 | R114: 0 | S114: 0 | T114: 0 | U114: 0 | V114: 8 | W114: 6 | AA114: 0 | AC114: 0 | AD114: 0 | AE114: 0 | AF114: 0 | AG114: 0 | AH114: 115 | AI114: 1.65 | AJ114: 8
A115: =+VLOOKUP(B115,studies!$A$2:$C$102,3) -> Reilly & Richards (1993) | B115: 12 | C115: 1993 | D115: 1 | E115: 1990 | F115: 1990 | G115: 0.1 | H115: 67.113916 | I115: 0 | J115: 1 | K115: 0 | O115: 0 | P115: 1 | Q115: 0 | R115: 0 | S115: 0 | T115: 0 | U115: 0 | V115: 5 | W115: 3 | AA115: 0 | AC115: 0 | AD115: 0 | AE115: 0 | AF115: 0 | AG115: 0 | AH115: 115 | AI115: 1.65 | AJ115: 8
A116: =+VLOOKUP(B116,studies!$A$2:$C$102,3) -> Reilly & Richards (1993) | B116: 12 | C116: 1993 | D116: 1 | E116: 1990 | F116: 1990 | G116: 0.1 | H116: 80.273507 | I116: 0 | J116: 1 | K116: 0 | O116: 0 | P116: 1 | Q116: 0 | R116: 0 | S116: 0 | T116: 0 | U116: 0 | V116: 5 | W116: 3 | AA116: 0 | AC116: 0 | AD116: 0 | AE116: 0 | AF116: 0 | AG116: 0 | AH116: 115 | AI116: 1.65 | AJ116: 8
A117: =+VLOOKUP(B117,studies!$A$2:$C$102,3) -> Azar (1994) | B117: 13 | C117: 1994 | D117: 1 | E117: 1990 | F117: 1990 | G117: 0.25 | H117: 179.44897 | I117: 0 | J117: 1 | K117: 0 | O117: 0 | P117: 0 | Q117: 0 | R117: 0 | S117: 0 | T117: 0 | U117: 0 | W117: 0 | AA117: 0 | AC117: 0 | AD117: 0 | AE117: 0 | AF117: 0 | AG117: 0 | AH117: 14 | AI117: 1.85 | AJ117: 3
A118: =+VLOOKUP(B118,studies!$A$2:$C$102,3) -> Azar (1994) | B118: 13 | C118: 1994 | D118: 1 | E118: 1990 | F118: 1990 | G118: 0.5 | H118: 717.79589 | I118: 0 | J118: 1 | K118: 0 | O118: 0 | P118: 0 | Q118: 0 | R118: 0 | S118: 0 | T118: 0 | U118: 0 | W118: 0 | AA118: 0 | AC118: 0 | AD118: 0 | AE118: 0 | AF118: 0 | AG118: 0 | AH118: 14 | AI118: 1.85 | AJ118: 3
A119: =+VLOOKUP(B119,studies!$A$2:$C$102,3) -> Azar (1994) | B119: 13 | C119: 1994 | D119: 1 | E119: 1990 | F119: 1990 | G119: 0.25 | H119: 1794.4897 | I119: 0 | J119: 1 | K119: 0 | O119: 0 | P119: 0 | Q119: 0 | R119: 0 | S119: 0 | T119: 0 | U119: 0 | W119: 0 | AA119: 0 | AC119: 0 | AD119: 0 | AE119: 0 | AF119: 0 | AG119: 0 | AH119: 14 | AI119: 1.85 | AJ119: 3
A120: =+VLOOKUP(B120,studies!$A$2:$C$102,3) -> Fankhauser (1994) | B120: 14 | C120: 1994 | D120: 1 | E120: 1988 | F120: 2015 | G120: 1 | H120: 46.634123 | I120: 1 | J120: 0 | K120: 0 | L120: 32.256805 | M120: 15.987338 | N120: 29.247424 | O120: 1 | P120: 1 | Q120: 0 | R120: 1 | S120: 0 | T120: 0 | U120: 0 | X120: 1 | AA120: 0 | AB120: 6 | AC120: 0 | AD120: 0 | AE120: 0 | AF120: 0 | AG120: 0 | AH120: 296 | AI120: 1.85 | AJ120: 1
A121: =+VLOOKUP(B121,studies!$A$2:$C$102,3) -> Nordhaus (1994) | B121: 15 | C121: 1994 | D121: 0 | E121: 1989 | F121: 2005 | G121: 1 | H121: 17.200864 | I121: 0 | J121: 1 | K121: 0 | O121: 1 | P121: 1 | Q121: 0 | R121: 1 | S121: 0 | T121: 1 | U121: 0 | V121: 5 | W121: 3 | AA121: 0 | AC121: 0 | AD121: 1 | AE121: 0 | AF121: 1 | AG121: 0 | AH121: 1733 | AI121: 0 | AJ121: 1
A122: =+VLOOKUP(B122,studies!$A$2:$C$102,3) -> Maddison (1995) | B122: 16 | C122: 1995 | D122: 1 | E122: 1990 | F122: 2010 | G122: 1 | H122: 43.033788 | I122: 0 | J122: 1 | K122: 0 | O122: 0 | P122: 1 | Q122: 0 | R122: 1 | S122: 0 | T122: 0 | U122: 0 | V122: 5 | W122: 3 | Y122: 2.8414595 | AA122: 0 | AB122: 1.2 | AC122: 0 | AD122: 0 | AE122: 0 | AF122: 1 | AG122: 0 | AH122: 97 | AI122: 1.6 | AJ122: 1
A123: =+VLOOKUP(B123,studies!$A$2:$C$102,3) -> Schauer (1995) | B123: 17 | C123: 1995 | D123: 1 | E123: 1990 | F123: 1990 | G123: 0.5 | H123: 6.3273708 | I123: 0 | J123: 0 | K123: 1 | L123: 75.942805 | M123: 75.942805 | N123: 75.942805 | O123: 1 | P123: 1 | Q123: 0 | R123: 1 | S123: 0 | T123: 0 | U123: 0 | V123: 4.91 | W123: 2.3 | AA123: 0 | AC123: 0 | AD123: 0 | AE123: 0 | AF123: 0 | AG123: 0 | AH123: 15 | AI123: 1.65 | AJ123: 2
A124: =+VLOOKUP(B124,studies!$A$2:$C$102,3) -> Schauer (1995) | B124: 17 | C124: 1995 | D124: 1 | E124: 1990 | F124: 1990 | G124: 0.5 | H124: 192.08218 | I124: 0 | J124: 0 | K124: 1 | L124: 537.62912 | M124: 537.62912 | N124: 537.62912 | O124: 1 | P124: 1 | Q124: 0 | R124: 1 | S124: 0 | T124: 0 | U124: 0 | V124: 4.91 | W124: 2.3 | AA124: 0 | AC124: 0 | AD124: 0 | AE124: 0 | AF124: 0 | AG124: 0 | AH124: 15 | AI124: 1.65 | AJ124: 2
A125: =+VLOOKUP(B125,studies!$A$2:$C$102,3) -> Azar & Sterner (1996) | B125: 18 | C125: 1996 | D125: 1 | E125: 1990 | F125: 1990 | G125: 0.044444444 | H125: 305.06325 | I125: 0 | J125: 1 | K125: 0 | O125: 0 | P125: 1 | Q125: 0 | R125: 1 | S125: 0 | T125: 0 | U125: 0 | V125: 2 | W125: 0 | AA125: 0 | AC125: 0 | AD125: 0 | AE125: 0 | AF125: 0 | AG125: 0 | AH125: 297 | AI125: 1.93 | AJ125: 16
A126: =+VLOOKUP(B126,studies!$A$2:$C$102,3) -> Azar & Sterner (1996) | B126: 18 | C126: 1996 | D126: 1 | E126: 1990 | F126: 1990 | G126: 0.088888889 | H126: 717.79589 | I126: 0 | J126: 1 | K126: 0 | O126: 0 | P126: 1 | Q126: 0 | R126: 1 | S126: 0 | T126: 0 | U126: 0 | V126: 2 | W126: 0 | AA126: 0 | AC126: 0 | AD126: 0 | AE126: 0 | AF126: 0 | AG126: 0 | AH126: 297 | AI126: 1.93 | AJ126: 16
A127: =+VLOOKUP(B127,studies!$A$2:$C$102,3) -> Azar & Sterner (1996) | B127: 18 | C127: 1996 | D127: 1 | E127: 1990 | F127: 1990 | G127: 0.033333333 | H127: 269.17346 | I127: 0 | J127: 1 | K127: 0 | O127: 0 | P127: 1 | Q127: 0 | R127: 1 | S127: 0 | T127: 0 | U127: 0 | V127: 2.1 | W127: 0.1 | AA127: 0 | AC127: 0 | AD127: 0 | AE127: 0 | AF127: 0 | AG127: 0 | AH127: 297 | AI127: 1.93 | AJ127: 16
A128: =+VLOOKUP(B128,studies!$A$2:$C$102,3) -> Azar & Sterner (1996) | B128: 18 | C128: 1996 | D128: 1 | E128: 1990 | F128: 1990 | G128: 0.066666667 | H128: 502.45712 | I128: 0 | J128: 1 | K128: 0 | O128: 0 | P128: 1 | Q128: 0 | R128: 1 | S128: 0 | T128: 0 | U128: 0 | V128: 2.1 | W128: 0.1 | AA128: 0 | AC128: 0 | AD128: 0 | AE128: 0 | AF128: 0 | AG128: 0 | AH128: 297 | AI128: 1.93 | AJ128: 16
A129: =+VLOOKUP(B129,studies!$A$2:$C$102,3) -> Azar & Sterner (1996) | B129: 18 | C129: 1996 | D129: 1 | E129: 1990 | F129: 1990 | G129: 0.022222222 | H129: 114.84734 | I129: 0 | J129: 1 | K129: 0 | O129: 0 | P129: 1 | Q129: 0 | R129: 1 | S129: 0 | T129: 0 | U129: 0 | V129: 3 | W129: 1 | AA129: 0 | AC129: 0 | AD129: 0 | AE129: 0 | AF129: 0 | AG129: 0 | AH129: 297 | AI129: 1.93 | AJ129: 16
A130: =+VLOOKUP(B130,studies!$A$2:$C$102,3) -> Azar & Sterner (1996) | B130: 18 | C130: 1996 | D130: 1 | E130: 1990 | F130: 1990 | G130: 0.044444444 | H130: 118.43632 | I130: 0 | J130: 1 | K130: 0 | O130: 0 | P130: 1 | Q130: 0 | R130: 1 | S130: 0 | T130: 0 | U130: 0 | V130: 3 | W130: 1 | AA130: 0 | AC130: 0 | AD130: 0 | AE130: 0 | AF130: 0 | AG130: 0 | AH130: 297 | AI130: 1.93 | AJ130: 16
A131: =+VLOOKUP(B131,studies!$A$2:$C$102,3) -> Azar & Sterner (1996) | B131: 18 | C131: 1996 | D131: 1 | E131: 1990 | F131: 1990 | G131: 0.011111111 | H131: 46.656733 | I131: 0 | J131: 1 | K131: 0 | O131: 0 | P131: 1 | Q131: 0 | R131: 1 | S131: 0 | T131: 0 | U131: 0 | V131: 5 | W131: 3 | AA131: 0 | AC131: 0 | AD131: 0 | AE131: 0 | AF131: 0 | AG131: 0 | AH131: 297 | AI131: 1.93 | AJ131: 16
A132: =+VLOOKUP(B132,studies!$A$2:$C$102,3) -> Azar & Sterner (1996) | B132: 18 | C132: 1996 | D132: 1 | E132: 1990 | F132: 1990 | G132: 0.022222222 | H132: 46.656733 | I132: 0 | J132: 1 | K132: 0 | O132: 0 | P132: 1 | Q132: 0 | R132: 1 | S132: 0 | T132: 0 | U132: 0 | V132: 5 | W132: 3 | AA132: 0 | AC132: 0 | AD132: 0 | AE132: 0 | AF132: 0 | AG132: 0 | AH132: 297 | AI132: 1.93 | AJ132: 16
A133: =+VLOOKUP(B133,studies!$A$2:$C$102,3) -> Azar & Sterner (1996) | B133: 18 | C133: 1996 | D133: 1 | E133: 1990 | F133: 1990 | G133: 0.088888889 | H133: 933.13466 | I133: 0 | J133: 1 | K133: 0 | O133: 0 | P133: 1 | Q133: 0 | R133: 1 | S133: 0 | T133: 0 | U133: 0 | V133: 2 | W133: 0 | AA133: 1 | AC133: 0 | AD133: 0 | AE133: 0 | AF133: 0 | AG133: 0 | AH133: 297 | AI133: 1.93 | AJ133: 16
A134: =+VLOOKUP(B134,studies!$A$2:$C$102,3) -> Azar & Sterner (1996) | B134: 18 | C134: 1996 | D134: 1 | E134: 1990 | F134: 1990 | G134: 0.17777778 | H134: 2117.4979 | I134: 0 | J134: 1 | K134: 0 | O134: 0 | P134: 1 | Q134: 0 | R134: 1 | S134: 0 | T134: 0 | U134: 0 | V134: 2 | W134: 0 | AA134: 1 | AC134: 0 | AD134: 0 | AE134: 0 | AF134: 0 | AG134: 0 | AH134: 297 | AI134: 1.93 | AJ134: 16
A135: =+VLOOKUP(B135,studies!$A$2:$C$102,3) -> Azar & Sterner (1996) | B135: 18 | C135: 1996 | D135: 1 | E135: 1990 | F135: 1990 | G135: 0.066666667 | H135: 825.46527 | I135: 0 | J135: 1 | K135: 0 | O135: 0 | P135: 1 | Q135: 0 | R135: 1 | S135: 0 | T135: 0 | U135: 0 | V135: 2.1 | W135: 0.1 | AA135: 1 | AC135: 0 | AD135: 0 | AE135: 0 | AF135: 0 | AG135: 0 | AH135: 297 | AI135: 1.93 | AJ135: 16
A136: =+VLOOKUP(B136,studies!$A$2:$C$102,3) -> Azar & Sterner (1996) | B136: 18 | C136: 1996 | D136: 1 | E136: 1990 | F136: 1990 | G136: 0.13333333 | H136: 1471.4816 | I136: 0 | J136: 1 | K136: 0 | O136: 0 | P136: 1 | Q136: 0 | R136: 1 | S136: 0 | T136: 0 | U136: 0 | V136: 2.1 | W136: 0.1 | AA136: 1 | AC136: 0 | AD136: 0 | AE136: 0 | AF136: 0 | AG136: 0 | AH136: 297 | AI136: 1.93 | AJ136: 16
... A143: =+VLOOKUP(B143,studies!$A$2:$C$102,3) -> Hohmeyer (1996) | B143: 20 | C143: 1996 | D143: 0 | E143: 1990 | F143: 1995 | G143: 1 | H143: 2463.3451 | I143: 0 | J143: 1 | K143: 0 | O143: 0 | P143: 0 | Q143: 0 | R143: 1 | S143: 0 | T143: 0 | U143: 0 | V143: 0 | W143: -2 | AA143: 0 | AC143: 0 | AD143: 0 | AE143: 0 | AF143: 0 | AG143: 0 | AH143: 38 | AI143: 0 | AJ143: 1
A144: =+VLOOKUP(B144,studies!$A$2:$C$102,3) -> Hope & Maul (1996) | B144: 21 | C144: 1996 | D144: 1 | E144: 1990 | F144: 1990 | G144: 0.1 | H144: 25.122856 | I144: 1 | J144: 0 | K144: 0 | M144: 7.3244479 | N144: 7.3244479 | O144: 1 | P144: 1 | Q144: 0 | R144: 0 | S144: 0 | T144: 0 | U144: 1 | V144: 4 | W144: 2 | AA144: 0 | AC144: 1 | AD144: 0 | AE144: 0 | AF144: 0 | AG144: 0 | AH144: 38 | AI144: 1.6 | AJ144: 6
A145: =+VLOOKUP(B145,studies!$A$2:$C$102,3) -> Hope & Maul (1996) | B145: 21 | C145: 1996 | D145: 1 | E145: 1990 | F145: 1990 | G145: 1 | H145: 86.135507 | I145: 1 | J145: 0 | K145: 0 | M145: 43.946687 | N145: 450.45354 | O145: 1 | P145: 1 | Q145: 0 | R145: 0 | S145: 0 | T145: 0 | U145: 1 | V145: 4 | W145: 2 | AA145: 0 | AC145: 1 | AD145: 0 | AE145: 0 | AF145: 0 | AG145: 0 | AH145: 38 | AI145: 1.6 | AJ145: 6
A146: =+VLOOKUP(B146,studies!$A$2:$C$102,3) -> Hope & Maul (1996) | B146: 21 | C146: 1996 | D146: 1 | E146: 1990 | F146: 1990 | G146: 0.1 | H146: 32.300815 | I146: 1 | J146: 0 | K146: 0 | M146: 9.1555598 | N146: 9.1555598 | O146: 1 | P146: 1 | Q146: 0 | R146: 0 | S146: 0 | T146: 0 | U146: 1 | V146: 4 | W146: 2 | AA146: 0 | AC146: 1 | AD146: 0 | AE146: 0 | AF146: 0 | AG146: 0 | AH146: 38 | AI146: 1.6 | AJ146: 6
A147: =+VLOOKUP(B147,studies!$A$2:$C$102,3) -> Hope & Maul (1996) | B147: 21 | C147: 1996 | D147: 1 | E147: 1990 | F147: 1990 | G147: 0.1 | H147: 68.19061 | I147: 1 | J147: 0 | K147: 0 | M147: 20.142232 | N147: 23.804456 | O147: 1 | P147: 1 | Q147: 0 | R147: 0 | S147: 0 | T147: 0 | U147: 1 | V147: 4 | W147: 2 | AA147: 0 | AC147: 1 | AD147: 0 | AE147: 0 | AF147: 0 | AG147: 0 | AH147: 38 | AI147: 1.6 | AJ147: 6
A148: =+VLOOKUP(B148,studies!$A$2:$C$102,3) -> Hope & Maul (1996) | B148: 21 | C148: 1996 | D148: 1 | E148: 1990 | F148: 1990 | G148: 0.6 | H148: 17.944897 | I148: 1 | J148: 0 | K148: 0 | M148: 5.4933359 | N148: 3.6622239 | O148: 1 | P148: 1 | Q148: 0 | R148: 1 | S148: 0 | T148: 0 | U148: 1 | V148: 4 | W148: 2 | AA148: 0 | AC148: 1 | AD148: 0 | AE148: 0 | AF148: 0 | AG148: 0 | AH148: 38 | AI148: 1.6 | AJ148: 6
A149: =+VLOOKUP(B149,studies!$A$2:$C$102,3) -> Hope & Maul (1996) | B149: 21 | C149: 1996 | D149: 1 | E149: 1990 | F149: 1990 | G149: 0.1 | H149: 104.0804 | I149: 1 | J149: 0 | K149: 0 | M149: 31.128903 | N149: 29.297791 | O149: 1 | P149: 1 | Q149: 0 | R149: 0 | S149: 0 | T149: 0 | U149: 1 | V149: 4 | W149: 2 | AA149: 0 | AC149: 1 | AD149: 0 | AE149: 0 | AF149: 0 | AG149: 0 | AH149: 38 | AI149: 1.6 | AJ149: 6
A150: =+VLOOKUP(B150,studies!$A$2:$C$102,3) -> Nordhaus & Yang (1996) | B150: 22 | C150: 1996 | D150: 1 | E150: 1990 | F150: 2010 | G150: 1 | H150: 14.973347 | I150: 0 | J150: 1 | K150: 0 | O150: 1 | P150: 1 | Q150: 0 | R150: 1 | S150: 0 | T150: 1 | U150: 0 | V150: 5 | W150: 3 | AA150: 0 | AC150: 0 | AD150: 1 | AE150: 0 | AF150: 1 | AG150: 0 | AH150: 871 | AI150: 6.46 | AJ150: 1
A151: =+VLOOKUP(B151,studies!$A$2:$C$102,3) -> Plambeck & Hope (1996) | B151: 23 | C151: 1996 | D151: 1 | E151: 1990 | F151: 1990 | G151: 0.125 | H151: 10.766938 | I151: 1 | J151: 0 | K151: 0 | M151: 3.6622239 | N151: 5.4933359 | O151: 1 | P151: 1 | Q151: 0 | R151: 1 | S151: 0 | T151: 0 | U151: 1 | V151: 5 | W151: 3 | AA151: 0 | AC151: 1 | AD151: 0 | AE151: 0 | AF151: 0 | AG151: 0 | AH151: 102 | AI151: 1.6 | AJ151: 8
A152: =+VLOOKUP(B152,studies!$A$2:$C$102,3) -> Plambeck & Hope (1996) | B152: 23 | C152: 1996 | D152: 1 | E152: 1990 | F152: 1990 | G152: 0.0625 | H152: 17.944897 | I152: 1 | J152: 0 | K152: 0 | M152: 5.4933359 | N152: 12.817784 | O152: 1 | P152: 1 | Q152: 0 | R152: 1 | S152: 0 | T152: 0 | U152: 1 | V152: 5 | W152: 3 | AA152: 0 | AC152: 1 | AD152: 0 | AE152: 0 | AF152: 0 | AG152: 0 | AH152: 102 | AI152: 1.6 | AJ152: 8
A153: =+VLOOKUP(B153,studies!$A$2:$C$102,3) -> Plambeck & Hope (1996) | B153: 23 | C153: 1996 | D153: 1 | E153: 1990 | F153: 1990 | G153: 0.125 | H153: 28.711836 | I153: 1 | J153: 0 | K153: 0 | M153: 9.1555598 | N153: 7.3244479 | O153: 1 | P153: 1 | Q153: 0 | R153: 1 | S153: 0 | T153: 0 | U153: 1 | V153: 5 | W153: 3 | AA153: 0 | AC153: 1 | AD153: 0 | AE153: 0 | AF153: 0 | AG153: 0 | AH153: 102 | AI153: 1.6 | AJ153: 8
A154: =+VLOOKUP(B154,studies!$A$2:$C$102,3) -> Plambeck & Hope (1996) | B154: 23 | C154: 1996 | D154: 1 | E154: 1990 | F154: 1990 | G154: 0.125 | H154: 28.711836 | I154: 1 | J154: 0 | K154: 0 | M154: 3.6622239 | N154: 18.31112 | O154: 1 | P154: 1 | Q154: 0 | R154: 1 | S154: 0 | T154: 0 | U154: 1 | V154: 5 | W154: 3 | AA154: 0 | AC154: 1 | AD154: 0 | AE154: 0 | AF154: 0 | AG154: 0 | AH154: 102 | AI154: 1.6 | AJ154: 8
A155: =+VLOOKUP(B155,studies!$A$2:$C$102,3) -> Plambeck & Hope (1996) | B155: 23 | C155: 1996 | D155: 1 | E155: 1990 | F155: 1990 | G155: 0.25 | H155: 75.368568 | I155: 1 | J155: 0 | K155: 0 | M155: 20.142232 | N155: 49.440023 | O155: 1 | P155: 1 | Q155: 0 | R155: 1 | S155: 0 | T155: 0 | U155: 1 | V155: 5 | W155: 3 | AA155: 0 | AC155: 1 | AD155: 0 | AE155: 0 | AF155: 0 | AG155: 0 | AH155: 102 | AI155: 1.6 | AJ155: 8
A156: =+VLOOKUP(B156,studies!$A$2:$C$102,3) -> Plambeck & Hope (1996) | B156: 23 | C156: 1996 | D156: 1 | E156: 1990 | F156: 1990 | G156: 0.125 | H156: 165.09305 | I156: 1 | J156: 0 | K156: 0 | M156: 47.608911 | N156: 87.893374 | O156: 1 | P156: 1 | Q156: 0 | R156: 1 | S156: 0 | T156: 0 | U156: 1 | V156: 4 | W156: 2 | AA156: 0 | AC156: 1 | AD156: 0 | AE156: 0 | AF156: 0 | AG156: 0 | AH156: 102 | AI156: 1.6 | AJ156: 8
A157: =+VLOOKUP(B157,studies!$A$2:$C$102,3) -> Plambeck & Hope (1996) | B157: 23 | C157: 1996 | D157: 1 | E157: 1990 | F157: 1990 | G157: 0.125 | H157: 1579.151 | I157: 1 | J157: 0 | K157: 0 | M157: 91.555598 | N157: 73.244479 | O157: 1 | P157: 1 | Q157: 0 | R157: 1 | S157: 0 | T157: 0 | U157: 1 | V157: 2 | W157: 0 | AA157: 0 | AC157: 1 | AD157: 0 | AE157: 0 | AF157: 0 | AG157: 0 | AH157: 102 | AI157: 1.6 | AJ157: 8
A158: =+VLOOKUP(B158,studies!$A$2:$C$102,3) -> Plambeck & Hope (1996) | B158: 23 | C158: 1996 | D158: 1 | E158: 1990 | F158: 1990 | G158: 0.0625 | H158: 114.84734 | I158: 1 | J158: 0 | K158: 0 | M158: 18.31112 | N158: 43.946687 | O158: 1 | P158: 1 | Q158: 0 | R158: 1 | S158: 0 | T158: 0 | U158: 1 | V158: 5 | W158: 3 | AA158: 0 | AC158: 1 | AD158: 0 | AE158: 0 | AF158: 0 | AG158: 0 | AH158: 102 | AI158: 1.6 | AJ158: 8
A159: =+VLOOKUP(B159,studies!$A$2:$C$102,3) -> Cline (1997) | B159: 24 | C159: 1997 | D159: 0 | E159: 1995 | F159: 1995 | G159: 1 | H159: 231.72507 | I159: 0 | J159: 1 | K159: 0 | L159: 105.29957 | M159: 107.44854 | N159: 107.44854 | O159: 1 | P159: 1 | Q159: 0 | R159: 1 | S159: 0 | T159: 1 | U159: 0 | AA159: 0 | AC159: 0 | AD159: 0 | AE159: 0 | AF159: 1 | AG159: 0 | AH159: 23 | AI159: 0 | AJ159: 1
A160: =+VLOOKUP(B160,studies!$A$2:$C$102,3) -> Nordhaus & Popp (1997) | B160: 25 | C160: 1997 | D160: 1 | E160: 1990 | F160: 2000 | G160: 0.9 | H160: 30.750526 | I160: 1 | J160: 0 | K160: 0 | L160: 2.063244 | M160: 18.62909 | N160: 35.668284 | O160: 0 | P160: 1 | Q160: 0 | R160: 1 | S160: 0 | T160: 1 | U160: 0 | V160: 5 | W160: 3 | X160: 1 | Y160: 2 | AA160: 0 | AC160: 0 | AD160: 1 | AE160: 0 | AF160: 1 | AG160: 0 | AH160: 204 | AI160: 1.85 | AJ160: 2
A161: =+VLOOKUP(B161,studies!$A$2:$C$102,3) -> Nordhaus & Popp (1997) | B161: 25 | C161: 1997 | D161: 1 | E161: 1990 | F161: 2010 | G161: 0.1 | H161: 13.00931 | I161: 1 | J161: 0 | K161: 0 | O161: 0 | P161: 1 | Q161: 0 | R161: 1 | S161: 0 | T161: 1 | U161: 0 | V161: 5 | Y161: 2 | AA161: 0 | AC161: 0 | AD161: 1 | AE161: 0 | AF161: 1 | AG161: 0 | AH161: 204 | AI161: 1.85 | AJ161: 2
A162: =+VLOOKUP(B162,studies!$A$2:$C$102,3) -> Eyre et al. (1999) | B162: 26 | C162: 1999 | D162: 0 | E162: 1995 | F162: 1995 | G162: 0.5 | H162: 448.92605 | I162: 0 | J162: 1 | K162: 0 | O162: 0 | P162: 1 | Q162: 1 | R162: 1 | S162: 1 | T162: 0 | U162: 0 | V162: 1 | W162: -1 | AA162: 1 | AC162: 0 | AD162: 0 | AE162: 0 | AF162: 0 | AG162: 0 | AH162: 67 | AI162: 0 | AJ162: 4
A163: =+VLOOKUP(B163,studies!$A$2:$C$102,3) -> Eyre et al. (1999) | B163: 26 | C163: 1999 | D163: 0 | E163: 1995 | F163: 1995 | G163: 0.5 | H163: 184.8519 | I163: 0 | J163: 1 | K163: 0 | O163: 0 | P163: 1 | Q163: 1 | R163: 1 | S163: 1 | T163: 0 | U163: 0 | V163: 3 | W163: 1 | AA163: 1 | AC163: 0 | AD163: 0 | AE163: 0 | AF163: 0 | AG163: 0 | AH163: 67 | AI163: 0 | AJ163: 4
A164: =+VLOOKUP(B164,studies!$A$2:$C$102,3) -> Eyre et al. (1999) | B164: 26 | C164: 1999 | D164: 0 | E164: 1995 | F164: 1995 | G164: 0.5 | H164: 422.51864 | I164: 0 | J164: 1 | K164: 0 | O164: 0 | P164: 1 | Q164: 1 | R164: 1 | S164: 0 | T164: 0 | U164: 0 | V164: 1 | W164: -1 | AA164: 1 | AC164: 0 | AD164: 0 | AE164: 0 | AF164: 0 | AG164: 0 | AH164: 67 | AI164: 0 | AJ164: 4
A165: =+VLOOKUP(B165,studies!$A$2:$C$102,3) -> Eyre et al. (1999) | B165: 26 | C165: 1999 | D165: 0 | E165: 1995 | F165: 1995 | G165: 0.5 | H165: 195.41487 | I165: 0 | J165: 1 | K165: 0 | O165: 0 | P165: 1 | Q165: 1 | R165: 1 | S165: 0 | T165: 0 | U165: 0 | V165: 3 | W165: 1 | AA165: 1 | AC165: 0 | AD165: 0 | AE165: 0 | AF165: 0 | AG165: 0 | AH165: 67 | AI165: 0 | AJ165: 4
...

Sheet notes
A1: Dataset 0
A2: base dataset used from Richard Tols web: https://sites.google.com/site/climateconomics/data/06-economic-impacts, file marginaldamagecosts.xlsx as of March 5, 2013
A3: more studies picked using this query from Google scholar, additionally papers references checked for more papers, search finished on August 1, 2014 | O3: query
A4: keyword: integrated assessment, social cost of carbon, climate damages, marginal damage costs, climate change, emissions, greenhouse, carbon dioxide, marginal impacts
A5: dataset 0 is a whole dataset without curvature (future emissions not included), future SCC are on sheet SCC (with average growth rate of SCC estimation)
A6: SCC recalculated to 2010 USD/tC using consumer price index (CPI) from here (http://research.stlouisfed.org/fred2/series/CPIAUCNS/downloaddata)
A7: SCC recalculated for the 2015 year of emission using SCC growth rate of 3.11% per year (calculated from the literature, see sheet SCC: yearly growth rate between the closest two time points reported in the article)
A8: our preference for SCC reporting: median>best guess>mean; mean and median usually reported when Monte Carlo simulations
A9: standard deviations and confidence intervals also recalculated to 2010/2015 USD/emission
A10: confidence intervals recalculated to upper and lower standard deviation (preferentially for 5% and 95% CI)
A13: Dataset 1
A14: only studies reporting standard deviation or confidence intervals
A15: if study includes both estimates with stdev or CI and without stdev or CI, we delete estimates that do not have stdev or CI
A16: sometimes only upper interval present (then we assume upper = lower), sometimes only stdev reported (then we assume stdev = upper = lower)
A19: Dataset 2
... A31: Variables
A32: idstudy | B32: = identification number of a study
A33: reviewed | B33: = 1 if study was published in a peer-reviewed outlet.
A34: pubyear | B34: The year of publication of the study.
A35: dollaryear | B35: SCC are reported in US dollar of a particular year per ton of CO2 (or C)
A36: emissionyear | B36: SCC are associated with a one-ton increase in CO2 emissions in a particular year
A37: tolweight | B37: Tol put weights across different estimates within each study
A38: scc | B38: estimate of the social cost of carbon in USD per ton of carbon
A39: sccmean | B39: = 1 if SCC estimate is a mean value
A40: sccbg | B40: = 1 if SCC estimate is a best guess value
A41: sccmed | B41: = 1 if SCC estimate is a median value
A42: stdev | B42: standard deviation of a SCC estimate
A43: stdlow | B43: standard deviation from confidence interval, lower limit of 5%
... A64: sjr | B64: = SciMago journal rank based on impact factor from Scopus

Sheet studies
A1: idstudy | B1: label bib | C1: label | D1: citation | E1: pubyear | F1: citations | G1: sjr
A2: 1 | B2: Nordhaus1982 | C2: Nordhaus (1982) | D2: Nordhaus, W. (1982): "How Fast Should We Graze the Global Commons?," American Economic Review, American Economic Association 72(2), 242-46. | E2: 1982 | F2: 132 | G2: 6.46
A3: 2 | B3: Ayres1991 | C3: Ayres & Walter (1991) | D3: Ayres, R.U. and J. Walter (1991): "The Greenhouse Effect: Damages, Costs and Abatement," Environmental and Resource Economics 1(3), 237-270. | E3: 1991 | F3: 220 | G3: 1.65
A4: 3 | B4: Nordhaus1991 | C4: Nordhaus (1991) | D4: Nordhaus, W.D. (1991): "To Slow or Not to Slow: The Economics of the Greenhouse Effect," Economic Journal 101(407), 920-937. | E4: 1991 | F4: 1166 | G4: 3.46
A5: 4 | B5: Cline1992 | C5: Cline (1992) | D5: Cline, W.R. (1992): The Economics of Global Warming, Institute for International Economics, Washington, D.C. | E5: 1992 | F5: 39 | G5: 0
A6: 5 | B6: Haraden1992 | C6: Haraden (1992) | D6: Haraden, J. (1992): "An improved shadow price for CO2," Energy 17(5), 419-426. | E6: 1992 | F6: 12 | G6: 1.85
A7: 6 | B7: Hohmeyer1992 | C7: Hohmeyer & Gaertner (1992) | D7: Hohmeyer, O. and M.Gaertner (1992), The Costs of Climate Change - A Rough Estimate of Orders of Magnitude, Fraunhofer-Institut fur Systemtechnik und Innovationsforschung, Karlsruhe. | E7: 1992 | F7: 37 | G7: 0
A8: 7 | B8: Penner1992 | C8: Penner et al. (1992) | D8: Penner, S.S., J.Haraden, and S.Mates (1992), 'Long-term global energy supplies with acceptable environmental impacts', Energy, 17, (10), pp. 883-899. | E8: 1992 | F8: 7 | G8: 1.85
A9: 8 | B9: Haraden1993 | C9: Haraden (1993) | D9: Haraden, J. 1993. ʻAn updated shadow price for CO2ʼ. Energy 18(3): 303–307 | E9: 1993 | F9: 9 | G9: 1.85
A10: 9 | B10: Nordhaus1993 | C10: Nordhaus (1993) | D10: Nordhaus, W.D. (1993), 'Rolling the 'DICE': An Optimal Transition Path for Controlling Greenhouse Gases', Resource and Energy Economics, 15, 27-50. | E10: 1993 | F10: 386 | G10: 1.13
A11: 10 | B11: Parry1993 | C11: Parry (1993) | D11: Parry, I.W.H. (1993), 'Some Estimates of the Insurance Value against Climate Change from Reducing Greenhouse Gas Emissions', Resource and Energy Economics, 15, 99-115. | E11: 1993 | F11: 23 | G11: 1.13
A12: 11 | B12: Peck1993 | C12: Peck & Teisberg (1993) | D12: Peck, S.C. and T.J.Teisberg (1993), 'Global Warming Uncertainties and the Value of Information: An Analysis using CETA', Resource and Energy Economics, 15, 71-97. | E12: 1993 | F12: 198 | G12: 1.13
A13: 12 | B13: Reilly1993 | C13: Reilly & Richards (1993) | D13: Reilly, J.M. and K.R.Richards (1993), 'Climate Change Damage and the Trace Gas Index Issue', Environmental and Resource Economics, 3, 41-61. | E13: 1993 | F13: 115 | G13: 1.65
... A102: 102 | B102: Rezai2014 | C102: Rezai & van der Ploeg (2014) | D102: Rezai Armon & Frederick van der Ploeg, 2014. "Abandoning Fossil Fuel; How fast and how much?," OxCarre Working Papers 123, Oxford Centre for the Analysis of Resource Rich Economies, University of Oxford. | E102: 2014 | F102: 3 | G102: 0

Sheet Dataset0
A1: label | B1: idstudy | C1: pubyear | D1: reviewed | E1: dollaryear | F1: emissionyear | G1: tolweight | H1: scc | I1: sccmean | J1: sccbg | K1: sccmed | L1: stdev | M1: stdlow | N1: stdup | O1: iie | P1: mmi | Q1: dim | R1: sce | S1: fund | T1: dicerice | U1: page | V1: cdr | W1: prtp | X1: rra | Y1: growth | Z1: ies | AA1: eweight | AB1: climatesens | AC1: hope | AD1: nordhaus | AE1: tol | AF1: pigou
A2: =+VLOOKUP(B2,studies!$A$2:$C$102,3) -> Nordhaus (1982) | B2: 1 | C2: 1982 | D2: 1 | E2: 1980 | F2: 1980 | G2: 0.5 | H2: 1984.9987 | I2: 0 | J2: 1 | K2: 0 | O2: 1 | P2: 0 | Q2: 0 | R2: 0 | S2: 0 | T2: 0 | U2: 0 | W2: 1 | Y2: 4 | AA2: 0 | AC2: 0 | AD2: 1 | AE2: 0 | AF2: 0
A3: =+VLOOKUP(B3,studies!$A$2:$C$102,3) -> Nordhaus (1982) | B3: 1 | C3: 1982 | D3: 1 | E3: 1980 | F3: 1980 | G3: 0.5 | H3: 283.57124 | I3: 0 | J3: 1 | K3: 0 | O3: 1 | P3: 0 | Q3: 0 | R3: 0 | S3: 0 | T3: 0 | U3: 0 | W3: 1 | Y3: 1 | AA3: 0 | AC3: 0 | AD3: 1 | AE3: 0 | AF3: 0
A4: =+VLOOKUP(B4,studies!$A$2:$C$102,3) -> Ayres & Walter (1991) | B4: 2 | C4: 1991 | D4: 1 | E4: 1989 | F4: 1990 | G4: 1 | H4: 450.7956 | I4: 0 | J4: 1 | K4: 0 | O4: 1 | P4: 0 | Q4: 0 | R4: 0 | S4: 0 | T4: 0 | U4: 0 | V4: 3 | W4: 1 | Y4: 0 | AA4: 0 | AC4: 0 | AD4: 0 | AE4: 0 | AF4: 0
A5: =+VLOOKUP(B5,studies!$A$2:$C$102,3) -> Nordhaus (1991) | B5: 3 | C5: 1991 | D5: 1 | E5: 1989 | F5: 1990 | G5: 0.0625 | H5: 914.62959 | I5: 0 | J5: 1 | K5: 0 | O5: 1 | P5: 0 | Q5: 0 | R5: 0 | S5: 0 | T5: 1 | U5: 0 | V5: 1 | W5: 0 | X5: 1 | Y5: 1 | AA5: 0 | AC5: 0 | AD5: 1 | AE5: 0 | AF5: 0
A6: =+VLOOKUP(B6,studies!$A$2:$C$102,3) -> Nordhaus (1991) | B6: 3 | C6: 1991 | D6: 1 | E6: 1989 | F6: 1990 | G6: 0.125 | H6: 457.31479 | I6: 0 | J6: 1 | K6: 0 | O6: 1 | P6: 0 | Q6: 0 | R6: 0 | S6: 0 | T6: 1 | U6: 0 | V6: 1 | W6: 0 | X6: 1 | Y6: 1 | AA6: 0 | AC6: 0 | AD6: 1 | AE6: 0 | AF6: 0
A7: =+VLOOKUP(B7,studies!$A$2:$C$102,3) -> Nordhaus (1991) | B7: 3 | C7: 1991 | D7: 1 | E7: 1989 | F7: 1990 | G7: 0.0625 | H7: 114.29402 | I7: 0 | J7: 1 | K7: 0 | O7: 1 | P7: 0 | Q7: 0 | R7: 0 | S7: 0 | T7: 1 | U7: 0 | V7: 1 | W7: 0 | X7: 1 | Y7: 1 | AA7: 0 | AC7: 0 | AD7: 1 | AE7: 0 | AF7: 0
A8: =+VLOOKUP(B8,studies!$A$2:$C$102,3) -> Nordhaus (1991) | B8: 3 | C8: 1991 | D8: 1 | E8: 1989 | F8: 1990 | G8: 0.125 | H8: 203.20478 | I8: 0 | J8: 1 | K8: 0 | O8: 1 | P8: 0 | Q8: 0 | R8: 0 | S8: 0 | T8: 1 | U8: 0 | V8: 3 | W8: 1 | X8: 1 | Y8: 2 | AA8: 0 | AC8: 0 | AD8: 1 | AE8: 0 | AF8: 0
A9: =+VLOOKUP(B9,studies!$A$2:$C$102,3) -> Nordhaus (1991) | B9: 3 | C9: 1991 | D9: 1 | E9: 1989 | F9: 1990 | G9: 0.25 | H9: 101.67175 | I9: 0 | J9: 1 | K9: 0 | O9: 1 | P9: 0 | Q9: 0 | R9: 0 | S9: 0 | T9: 1 | U9: 0 | V9: 3 | W9: 1 | X9: 1 | Y9: 2 | AA9: 0 | AC9: 0 | AD9: 1 | AE9: 0 | AF9: 0
A10: =+VLOOKUP(B10,studies!$A$2:$C$102,3) -> Nordhaus (1991) | B10: 3 | C10: 1991 | D10: 1 | E10: 1989 | F10: 1990 | G10: 0.125 | H10: 25.38326 | I10: 0 | J10: 1 | K10: 0 | O10: 1 | P10: 0 | Q10: 0 | R10: 0 | S10: 0 | T10: 1 | U10: 0 | V10: 3 | W10: 1 | X10: 1 | Y10: 2 | AA10: 0 | AC10: 0 | AD10: 1 | AE10: 0 | AF10: 0
A11: =+VLOOKUP(B11,studies!$A$2:$C$102,3) -> Nordhaus (1991) | B11: 3 | C11: 1991 | D11: 1 | E11: 1989 | F11: 1990 | G11: 0.0625 | H11: 33.844346 | I11: 0 | J11: 1 | K11: 0 | O11: 1 | P11: 0 | Q11: 0 | R11: 0 | S11: 0 | T11: 1 | U11: 0 | V11: 7 | W11: 4 | X11: 1 | Y11: 3 | AA11: 0 | AC11: 0 | AD11: 1 | AE11: 0 | AF11: 0
A12: =+VLOOKUP(B12,studies!$A$2:$C$102,3) -> Nordhaus (1991) | B12: 3 | C12: 1991 | D12: 1 | E12: 1989 | F12: 1990 | G12: 0.125 | H12: 16.922173 | I12: 0 | J12: 1 | K12: 0 | O12: 1 | P12: 0 | Q12: 0 | R12: 0 | S12: 0 | T12: 1 | U12: 0 | V12: 7 | W12: 4 | X12: 1 | Y12: 3 | AA12: 0 | AC12: 0 | AD12: 1 | AE12: 0 | AF12: 0
A13: =+VLOOKUP(B13,studies!$A$2:$C$102,3) -> Nordhaus (1991) | B13: 3 | C13: 1991 | D13: 1 | E13: 1989 | F13: 1990 | G13: 0.0625 | H13: 4.2998965 | I13: 0 | J13: 1 | K13: 0 | O13: 1 | P13: 0 | Q13: 0 | R13: 0 | S13: 0 | T13: 1 | U13: 0 | V13: 7 | W13: 4 | X13: 1 | Y13: 3 | AA13: 0 | AC13: 0 | AD13: 1 | AE13: 0 | AF13: 0
A14: =+VLOOKUP(B14,studies!$A$2:$C$102,3) -> Cline (1992) | B14: 4 | C14: 1992 | D14: 0 | E14: 1989 | F14: 1990 | G14: 1 | H14: 245.51022 | I14: 0 | J14: 1 | K14: 0 | L14: 111.7847 | M14: 114.06602 | N14: 114.06602 | O14: 1 | P14: 1 | Q14: 0 | R14: 1 | S14: 0 | T14: 0 | U14: 0 | V14: 1.5 | W14: 0 | X14: 1.5 | Y14: 1 | AA14: 0 | AC14: 0 | AD14: 0 | AE14: 0 | AF14: 0
A15: =+VLOOKUP(B15,studies!$A$2:$C$102,3) -> Haraden (1992) | B15: 5 | C15: 1992 | D15: 1 | E15: 1984 | F15: 1987 | G15: 1 | H15: 72.59118 | I15: 0 | J15: 1 | K15: 0 | O15: 1 | P15: 0 | Q15: 0 | R15: 0 | S15: 0 | T15: 0 | U15: 0 | V15: 4 | W15: 2 | X15: 1 | Y15: 2 | AA15: 0 | AC15: 0 | AD15: 0 | AE15: 0 | AF15: 0
A16: =+VLOOKUP(B16,studies!$A$2:$C$102,3) -> Hohmeyer & Gaertner (1992) | B16: 6 | C16: 1992 | D16: 0 | E16: 1990 | F16: 1990 | G16: 1 | H16: 6383.0401 | I16: 0 | J16: 1 | K16: 0 | O16: 1 | P16: 0 | Q16: 0 | R16: 1 | S16: 0 | T16: 0 | U16: 0 | V16: 0 | W16: 2 | AA16: 0 | AC16: 0 | AD16: 0 | AE16: 0 | AF16: 0
A17: =+VLOOKUP(B17,studies!$A$2:$C$102,3) -> Penner et al. (1992) | B17: 7 | C17: 1992 | D17: 1 | E17: 1989 | F17: 1989 | G17: 0.25 | H17: 65.023092 | I17: 0 | J17: 1 | K17: 0 | O17: 0 | P17: 0 | Q17: 0 | R17: 0 | S17: 0 | T17: 1 | U17: 0 | V17: 4 | W17: 2 | AA17: 0 | AC17: 0 | AD17: 0 | AE17: 0 | AF17: 0
A18: =+VLOOKUP(B18,studies!$A$2:$C$102,3) -> Haraden (1993) | B18: 8 | C18: 1993 | D18: 1 | E18: 1989 | F18: 1989 | G18: 0.25 | H18: 7.2161199 | I18: 0 | J18: 1 | K18: 0 | O18: 0 | P18: 0 | Q18: 0 | R18: 0 | S18: 0 | T18: 0 | U18: 0 | V18: 4 | W18: 2 | X18: 1.25 | Y18: 1.6 | AA18: 0 | AC18: 0 | AD18: 0 | AE18: 0 | AF18: 0
A19: =+VLOOKUP(B19,studies!$A$2:$C$102,3) -> Haraden (1993) | B19: 8 | C19: 1993 | D19: 1 | E19: 1989 | F19: 1989 | G19: 0.5 | H19: 11.623804 | I19: 0 | J19: 1 | K19: 0 | O19: 0 | P19: 0 | Q19: 0 | R19: 0 | S19: 0 | T19: 0 | U19: 0 | V19: 4 | W19: 2 | X19: 0.86956522 | Y19: 2.3 | AA19: 0 | AC19: 0 | AD19: 0 | AE19: 0 | AF19: 0
A20: =+VLOOKUP(B20,studies!$A$2:$C$102,3) -> Haraden (1993) | B20: 8 | C20: 1993 | D20: 1 | E20: 1989 | F20: 1989 | G20: 0.25 | H20: 34.247315 | I20: 0 | J20: 1 | K20: 0 | O20: 0 | P20: 0 | Q20: 0 | R20: 0 | S20: 0 | T20: 0 | U20: 0 | V20: 4 | W20: 2 | X20: 0.5 | Y20: 4 | AA20: 0 | AC20: 0 | AD20: 0 | AE20: 0 | AF20: 0
A21: =+VLOOKUP(B21,studies!$A$2:$C$102,3) -> Nordhaus (1993) | B21: 9 | C21: 1993 | D21: 1 | E21: 1989 | F21: 1990 | G21: 1 | H21: 18.914501 | I21: 0 | J21: 1 | K21: 0 | O21: 0 | P21: 1 | Q21: 0 | R21: 1 | S21: 0 | T21: 1 | U21: 0 | V21: 5 | W21: 3 | AA21: 0 | AC21: 0 | AD21: 1 | AE21: 0 | AF21: 1
A22: =+VLOOKUP(B22,studies!$A$2:$C$102,3) -> Parry (1993) | B22: 10 | C22: 1993 | D22: 1 | E22: 1991 | F22: 1990 | G22: 0.0089285714 | H22: 0.025256367 | I22: 0 | J22: 1 | K22: 0 | O22: 0 | P22: 1 | Q22: 0 | R22: 0 | S22: 0 | T22: 1 | U22: 0 | W22: 0 | AA22: 0 | AC22: 0 | AD22: 0 | AE22: 0 | AF22: 0
A23: =+VLOOKUP(B23,studies!$A$2:$C$102,3) -> Parry (1993) | B23: 10 | C23: 1993 | D23: 1 | E23: 1991 | F23: 1990 | G23: 0.0089285714 | H23: 0.1515382 | I23: 0 | J23: 1 | K23: 0 | O23: 0 | P23: 1 | Q23: 0 | R23: 0 | S23: 0 | T23: 1 | U23: 0 | W23: 0 | AA23: 0 | AC23: 0 | AD23: 0 | AE23: 0 | AF23: 0
A24: =+VLOOKUP(B24,studies!$A$2:$C$102,3) -> Parry (1993) | B24: 10 | C24: 1993 | D24: 1 | E24: 1991 | F24: 1990 | G24: 0.017857143 | H24: 0.03788455 | I24: 0 | J24: 1 | K24: 0 | O24: 0 | P24: 1 | Q24: 0 | R24: 0 | S24: 0 | T24: 1 | U24: 0 | W24: 0 | AA24: 0 | AC24: 0 | AD24: 0 | AE24: 0 | AF24: 0
A25: =+VLOOKUP(B25,studies!$A$2:$C$102,3) -> Parry (1993) | B25: 10 | C25: 1993 | D25: 1 | E25: 1991 | F25: 1990 | G25: 0.017857143 | H25: 0.2273073 | I25: 0 | J25: 1 | K25: 0 | O25: 0 | P25: 1 | Q25: 0 | R25: 0 | S25: 0 | T25: 1 | U25: 0 | W25: 0 | AA25: 0 | AC25: 0 | AD25: 0 | AE25: 0 | AF25: 0
A26: =+VLOOKUP(B26,studies!$A$2:$C$102,3) -> Parry (1993) | B26: 10 | C26: 1993 | D26: 1 | E26: 1991 | F26: 1990 | G26: 0.017857143 | H26: 0.075769101 | I26: 0 | J26: 1 | K26: 0 | O26: 0 | P26: 1 | Q26: 0 | R26: 0 | S26: 0 | T26: 1 | U26: 0 | W26: 0 | AA26: 0 | AC26: 0 | AD26: 0 | AE26: 0 | AF26: 0
A27: =+VLOOKUP(B27,studies!$A$2:$C$102,3) -> Parry (1993) | B27: 10 | C27: 1993 | D27: 1 | E27: 1991 | F27: 1990 | G27: 0.017857143 | H27: 0.4546146 | I27: 0 | J27: 1 | K27: 0 | O27: 0 | P27: 1 | Q27: 0 | R27: 0 | S27: 0 | T27: 1 | U27: 0 | W27: 0 | AA27: 0 | AC27: 0 | AD27: 0 | AE27: 0 | AF27: 0
A28: =+VLOOKUP(B28,studies!$A$2:$C$102,3) -> Parry (1993) | B28: 10 | C28: 1993 | D28: 1 | E28: 1991 | F28: 1990 | G28: 0.0089285714 | H28: 0.13891002 | I28: 0 | J28: 1 | K28: 0 | O28: 0 | P28: 1 | Q28: 0 | R28: 0 | S28: 0 | T28: 1 | U28: 0 | W28: 0 | AA28: 0 | AC28: 0 | AD28: 0 | AE28: 0 | AF28: 0
A29: =+VLOOKUP(B29,studies!$A$2:$C$102,3) -> Parry (1993) | B29: 10 | C29: 1993 | D29: 1 | E29: 1991 | F29: 1990 | G29: 0.0089285714 | H29: 0.83346011 | I29: 0 | J29: 1 | K29: 0 | O29: 0 | P29: 1 | Q29: 0 | R29: 0 | S29: 0 | T29: 1 | U29: 0 | W29: 0 | AA29: 0 | AC29: 0 | AD29: 0 | AE29: 0 | AF29: 0
A30: =+VLOOKUP(B30,studies!$A$2:$C$102,3) -> Parry (1993) | B30: 10 | C30: 1993 | D30: 1 | E30: 1991 | F30: 1990 | G30: 0.0089285714 | H30: 0.34096095 | I30: 0 | J30: 1 | K30: 0 | O30: 0 | P30: 1 | Q30: 0 | R30: 0 | S30: 0 | T30: 1 | U30: 0 | W30: 0 | AA30: 0 | AC30: 0 | AD30: 0 | AE30: 0 | AF30: 0
A31: =+VLOOKUP(B31,studies!$A$2:$C$102,3) -> Parry (1993) | B31: 10 | C31: 1993 | D31: 1 | E31: 1991 | F31: 1990 | G31: 0.0089285714 | H31: 2.0457657 | I31: 0 | J31: 1 | K31: 0 | O31: 0 | P31: 1 | Q31: 0 | R31: 0 | S31: 0 | T31: 1 | U31: 0 | W31: 0 | AA31: 0 | AC31: 0 | AD31: 0 | AE31: 0 | AF31: 0
A32: =+VLOOKUP(B32,studies!$A$2:$C$102,3) -> Parry (1993) | B32: 10 | C32: 1993 | D32: 1 | E32: 1991 | F32: 1990 | G32: 0.0089285714 | H32: 0.050512734 | I32: 0 | J32: 1 | K32: 0 | O32: 0 | P32: 1 | Q32: 0 | R32: 0 | S32: 0 | T32: 1 | U32: 0 | W32: 0 | AA32: 0 | AC32: 0 | AD32: 0 | AE32: 0 | AF32: 0
A33: =+VLOOKUP(B33,studies!$A$2:$C$102,3) -> Parry (1993) | B33: 10 | C33: 1993 | D33: 1 | E33: 1991 | F33: 1990 | G33: 0.0089285714 | H33: 0.3030764 | I33: 0 | J33: 1 | K33: 0 | O33: 0 | P33: 1 | Q33: 0 | R33: 0 | S33: 0 | T33: 1 | U33: 0 | W33: 0 | AA33: 0 | AC33: 0 | AD33: 0 | AE33: 0 | AF33: 0
... A81: =+VLOOKUP(B81,studies!$A$2:$C$102,3) -> Parry (1993) | B81: 10 | C81: 1993 | D81: 1 | E81: 1991 | F81: 1990 | G81: 0.0089285714 | H81: 10396.657 | I81: 0 | J81: 1 | K81: 0 | O81: 0 | P81: 1 | Q81: 0 | R81: 0 | S81: 0 | T81: 1 | U81: 0 | W81: 0 | AA81: 0 | AC81: 0 | AD81: 0 | AE81: 0 | AF81: 0
A82: =+VLOOKUP(B82,studies!$A$2:$C$102,3) -> Peck & Teisberg (1993) | B82: 11 | C82: 1993 | D82: 1 | E82: 1989 | F82: 2030 | G82: 0.5 | H82: 11.105529 | I82: 0 | J82: 1 | K82: 0 | O82: 0 | P82: 1 | Q82: 0 | R82: 1 | S82: 0 | T82: 0 | U82: 0 | V82: 5 | W82: 3 | AA82: 0 | AC82: 0 | AD82: 0 | AE82: 0 | AF82: 1
A83: =+VLOOKUP(B83,studies!$A$2:$C$102,3) -> Peck & Teisberg (1993) | B83: 11 | C83: 1993 | D83: 1 | E83: 1989 | F83: 2030 | G83: 0.019230769 | H83: 24.210053 | I83: 0 | J83: 1 | K83: 0 | O83: 0 | P83: 1 | Q83: 0 | R83: 1 | S83: 0 | T83: 0 | U83: 0 | V83: 5 | W83: 3 | AA83: 0 | AC83: 0 | AD83: 0 | AE83: 0 | AF83: 1
A84: =+VLOOKUP(B84,studies!$A$2:$C$102,3) -> Peck & Teisberg (1993) | B84: 11 | C84: 1993 | D84: 1 | E84: 1989 | F84: 2030 | G84: 0.019230769 | H84: 24.543219 | I84: 0 | J84: 1 | K84: 0 | O84: 0 | P84: 1 | Q84: 0 | R84: 1 | S84: 0 | T84: 0 | U84: 0 | V84: 5 | W84: 3 | AA84: 0 | AC84: 0 | AD84: 0 | AE84: 0 | AF84: 1
A85: =+VLOOKUP(B85,studies!$A$2:$C$102,3) -> Peck & Teisberg (1993) | B85: 11 | C85: 1993 | D85: 1 | E85: 1989 | F85: 2030 | G85: 0.019230769 | H85: 25.431661 | I85: 0 | J85: 1 | K85: 0 | O85: 0 | P85: 1 | Q85: 0 | R85: 1 | S85: 0 | T85: 0 | U85: 0 | V85: 5 | W85: 3 | AA85: 0 | AC85: 0 | AD85: 0 | AE85: 0 | AF85: 1
A86: =+VLOOKUP(B86,studies!$A$2:$C$102,3) -> Peck & Teisberg (1993) | B86: 11 | C86: 1993 | D86: 1 | E86: 1989 | F86: 2030 | G86: 0.019230769 | H86: 24.210053 | I86: 0 | J86: 1 | K86: 0 | O86: 0 | P86: 1 | Q86: 0 | R86: 1 | S86: 0 | T86: 0 | U86: 0 | V86: 5 | W86: 3 | AA86: 0 | AC86: 0 | AD86: 0 | AE86: 0 | AF86: 1
A87: =+VLOOKUP(B87,studies!$A$2:$C$102,3) -> Peck & Teisberg (1993) | B87: 11 | C87: 1993 | D87: 1 | E87: 1989 | F87: 2030 | G87: 0.019230769 | H87: 24.543219 | I87: 0 | J87: 1 | K87: 0 | O87: 0 | P87: 1 | Q87: 0 | R87: 1 | S87: 0 | T87: 0 | U87: 0 | V87: 5 | W87: 3 | AA87: 0 | AC87: 0 | AD87: 0 | AE87: 0 | AF87: 1
A88: =+VLOOKUP(B88,studies!$A$2:$C$102,3) -> Peck & Teisberg (1993) | B88: 11 | C88: 1993 | D88: 1 | E88: 1989 | F88: 2030 | G88: 0.019230769 | H88: 3.7758798 | I88: 0 | J88: 1 | K88: 0 | O88: 0 | P88: 1 | Q88: 0 | R88: 1 | S88: 0 | T88: 0 | U88: 0 | V88: 5 | W88: 3 | AA88: 0 | AC88: 0 | AD88: 0 | AE88: 0 | AF88: 1
A89: =+VLOOKUP(B89,studies!$A$2:$C$102,3) -> Peck & Teisberg (1993) | B89: 11 | C89: 1993 | D89: 1 | E89: 1989 | F89: 2030 | G89: 0.019230769 | H89: 6.1080409 | I89: 0 | J89: 1 | K89: 0 | O89: 0 | P89: 1 | Q89: 0 | R89: 1 | S89: 0 | T89: 0 | U89: 0 | V89: 5 | W89: 3 | AA89: 0 | AC89: 0 | AD89: 0 | AE89: 0 | AF89: 1
A90: =+VLOOKUP(B90,studies!$A$2:$C$102,3) -> Peck & Teisberg (1993) | B90: 11 | C90: 1993 | D90: 1 | E90: 1989 | F90: 2030 | G90: 0.019230769 | H90: 13.326635 | I90: 0 | J90: 1 | K90: 0 | O90: 0 | P90: 1 | Q90: 0 | R90: 1 | S90: 0 | T90: 0 | U90: 0 | V90: 5 | W90: 3 | AA90: 0 | AC90: 0 | AD90: 0 | AE90: 0 | AF90: 1
A91: =+VLOOKUP(B91,studies!$A$2:$C$102,3) -> Peck & Teisberg (1993) | B91: 11 | C91: 1993 | D91: 1 | E91: 1989 | F91: 2030 | G91: 0.019230769 | H91: 11.882916 | I91: 0 | J91: 1 | K91: 0 | O91: 0 | P91: 1 | Q91: 0 | R91: 1 | S91: 0 | T91: 0 | U91: 0 | V91: 5 | W91: 3 | AA91: 0 | AC91: 0 | AD91: 0 | AE91: 0 | AF91: 1
A92: =+VLOOKUP(B92,studies!$A$2:$C$102,3) -> Peck & Teisberg (1993) | B92: 11 | C92: 1993 | D92: 1 | E92: 1989 | F92: 2030 | G92: 0.019230769 | H92: 21.21156 | I92: 0 | J92: 1 | K92: 0 | O92: 0 | P92: 1 | Q92: 0 | R92: 1 | S92: 0 | T92: 0 | U92: 0 | V92: 5 | W92: 3 | AA92: 0 | AC92: 0 | AD92: 0 | AE92: 0 | AF92: 1
A93: =+VLOOKUP(B93,studies!$A$2:$C$102,3) -> Peck & Teisberg (1993) | B93: 11 | C93: 1993 | D93: 1 | E93: 1989 | F93: 2030 | G93: 0.019230769 | H93: 21.322615 | I93: 0 | J93: 1 | K93: 0 | O93: 0 | P93: 1 | Q93: 0 | R93: 1 | S93: 0 | T93: 0 | U93: 0 | V93: 5 | W93: 3 | AA93: 0 | AC93: 0 | AD93: 0 | AE93: 0 | AF93: 1
... A106: =+VLOOKUP(B106,studies!$A$2:$C$102,3) -> Peck & Teisberg (1993) | B106: 11 | C106: 1993 | D106: 1 | E106: 1989 | F106: 2030 | G106: 0.019230769 | H106: 31.428647 | I106: 0 | J106: 1 | K106: 0 | O106: 0 | P106: 1 | Q106: 0 | R106: 1 | S106: 0 | T106: 0 | U106: 0 | V106: 5 | W106: 3 | AA106: 0 | AC106: 0 | AD106: 0 | AE106: 0 | AF106: 1
A107: =+VLOOKUP(B107,studies!$A$2:$C$102,3) -> Peck & Teisberg (1993) | B107: 11 | C107: 1993 | D107: 1 | E107: 1989 | F107: 2030 | G107: 0.019230769 | H107: 13.992966 | I107: 0 | J107: 1 | K107: 0 | O107: 0 | P107: 1 | Q107: 0 | R107: 1 | S107: 0 | T107: 0 | U107: 0 | W107: NA | AA107: 0 | AC107: 0 | AD107: 0 | AE107: 0 | AF107: 1
A108: =+VLOOKUP(B108,studies!$A$2:$C$102,3) -> Peck & Teisberg (1993) | B108: 11 | C108: 1993 | D108: 1 | E108: 1989 | F108: 2030 | G108: 0.019230769 | H108: 49.863825 | I108: 0 | J108: 1 | K108: 0 | O108: 0 | P108: 1 | Q108: 0 | R108: 1 | S108: 0 | T108: 0 | U108: 0 | W108: NA | AA108: 0 | AC108: 0 | AD108: 0 | AE108: 0 | AF108: 1
A109: =+VLOOKUP(B109,studies!$A$2:$C$102,3) -> Reilly & Richards (1993) | B109: 12 | C109: 1993 | D109: 1 | E109: 1990 | F109: 1990 | G109: 0.2 | H109: 51.322406 | I109: 0 | J109: 1 | K109: 0 | O109: 0 | P109: 1 | Q109: 0 | R109: 0 | S109: 0 | T109: 0 | U109: 0 | V109: 5 | W109: 3 | AA109: 0 | AC109: 0 | AD109: 0 | AE109: 0 | AF109: 0
A110: =+VLOOKUP(B110,studies!$A$2:$C$102,3) -> Reilly & Richards (1993) | B110: 12 | C110: 1993 | D110: 1 | E110: 1990 | F110: 1990 | G110: 0.2 | H110: 76.32563 | I110: 0 | J110: 1 | K110: 0 | O110: 0 | P110: 1 | Q110: 0 | R110: 0 | S110: 0 | T110: 0 | U110: 0 | V110: 5 | W110: 3 | AA110: 0 | AC110: 0 | AD110: 0 | AE110: 0 | AF110: 0
A111: =+VLOOKUP(B111,studies!$A$2:$C$102,3) -> Reilly & Richards (1993) | B111: 12 | C111: 1993 | D111: 1 | E111: 1990 | F111: 1990 | G111: 0.1 | H111: 184.23428 | I111: 0 | J111: 1 | K111: 0 | O111: 0 | P111: 1 | Q111: 0 | R111: 0 | S111: 0 | T111: 0 | U111: 0 | V111: 2 | W111: 0 | AA111: 0 | AC111: 0 | AD111: 0 | AE111: 0 | AF111: 0
A112: =+VLOOKUP(B112,studies!$A$2:$C$102,3) -> Reilly & Richards (1993) | B112: 12 | C112: 1993 | D112: 1 | E112: 1990 | F112: 1990 | G112: 0.1 | H112: 157.9151 | I112: 0 | J112: 1 | K112: 0 | O112: 0 | P112: 1 | Q112: 0 | R112: 0 | S112: 0 | T112: 0 | U112: 0 | V112: 2 | W112: 0 | AA112: 0 | AC112: 0 | AD112: 0 | AE112: 0 | AF112: 0
A113: =+VLOOKUP(B113,studies!$A$2:$C$102,3) -> Reilly & Richards (1993) | B113: 12 | C113: 1993 | D113: 1 | E113: 1990 | F113: 1990 | G113: 0.1 | H113: 28.951101 | I113: 0 | J113: 1 | K113: 0 | O113: 0 | P113: 1 | Q113: 0 | R113: 0 | S113: 0 | T113: 0 | U113: 0 | V113: 8 | W113: 6 | AA113: 0 | AC113: 0 | AD113: 0 | AE113: 0 | AF113: 0
A114: =+VLOOKUP(B114,studies!$A$2:$C$102,3) -> Reilly & Richards (1993) | B114: 12 | C114: 1993 | D114: 1 | E114: 1990 | F114: 1990 | G114: 0.1 | H114: 50.006447 | I114: 0 | J114: 1 | K114: 0 | O114: 0 | P114: 1 | Q114: 0 | R114: 0 | S114: 0 | T114: 0 | U114: 0 | V114: 8 | W114: 6 | AA114: 0 | AC114: 0 | AD114: 0 | AE114: 0 | AF114: 0
A115: =+VLOOKUP(B115,studies!$A$2:$C$102,3) -> Reilly & Richards (1993) | B115: 12 | C115: 1993 | D115: 1 | E115: 1990 | F115: 1990 | G115: 0.1 | H115: 67.113916 | I115: 0 | J115: 1 | K115: 0 | O115: 0 | P115: 1 | Q115: 0 | R115: 0 | S115: 0 | T115: 0 | U115: 0 | V115: 5 | W115: 3 | AA115: 0 | AC115: 0 | AD115: 0 | AE115: 0 | AF115: 0
A116: =+VLOOKUP(B116,studies!$A$2:$C$102,3) -> Reilly & Richards (1993) | B116: 12 | C116: 1993 | D116: 1 | E116: 1990 | F116: 1990 | G116: 0.1 | H116: 80.273507 | I116: 0 | J116: 1 | K116: 0 | O116: 0 | P116: 1 | Q116: 0 | R116: 0 | S116: 0 | T116: 0 | U116: 0 | V116: 5 | W116: 3 | AA116: 0 | AC116: 0 | AD116: 0 | AE116: 0 | AF116: 0
A117: =+VLOOKUP(B117,studies!$A$2:$C$102,3) -> Azar (1994) | B117: 13 | C117: 1994 | D117: 1 | E117: 1990 | F117: 1990 | G117: 0.25 | H117: 179.44897 | I117: 0 | J117: 1 | K117: 0 | O117: 0 | P117: 0 | Q117: 0 | R117: 0 | S117: 0 | T117: 0 | U117: 0 | W117: 0 | AA117: 0 | AC117: 0 | AD117: 0 | AE117: 0 | AF117: 0
A118: =+VLOOKUP(B118,studies!$A$2:$C$102,3) -> Azar (1994) | B118: 13 | C118: 1994 | D118: 1 | E118: 1990 | F118: 1990 | G118: 0.5 | H118: 717.79589 | I118: 0 | J118: 1 | K118: 0 | O118: 0 | P118: 0 | Q118: 0 | R118: 0 | S118: 0 | T118: 0 | U118: 0 | W118: 0 | AA118: 0 | AC118: 0 | AD118: 0 | AE118: 0 | AF118: 0
A119: =+VLOOKUP(B119,studies!$A$2:$C$102,3) -> Azar (1994) | B119: 13 | C119: 1994 | D119: 1 | E119: 1990 | F119: 1990 | G119: 0.25 | H119: 1794.4897 | I119: 0 | J119: 1 | K119: 0 | O119: 0 | P119: 0 | Q119: 0 | R119: 0 | S119: 0 | T119: 0 | U119: 0 | W119: 0 | AA119: 0 | AC119: 0 | AD119: 0 | AE119: 0 | AF119: 0
A120: =+VLOOKUP(B120,studies!$A$2:$C$102,3) -> Fankhauser (1994) | B120: 14 | C120: 1994 | D120: 1 | E120: 1988 | F120: 2015 | G120: 1 | H120: 46.634123 | I120: 1 | J120: 0 | K120: 0 | L120: 32.256805 | M120: 15.987338 | N120: 29.247424 | O120: 1 | P120: 1 | Q120: 0 | R120: 1 | S120: 0 | T120: 0 | U120: 0 | V120: NA | W120: NA | X120: 1 | AA120: 0 | AB120: 6 | AC120: 0 | AD120: 0 | AE120: 0 | AF120: 0
A121: =+VLOOKUP(B121,studies!$A$2:$C$102,3) -> Nordhaus (1994) | B121: 15 | C121: 1994 | D121: 0 | E121: 1989 | F121: 2005 | G121: 1 | H121: 17.200864 | I121: 0 | J121: 1 | K121: 0 | O121: 1 | P121: 1 | Q121: 0 | R121: 1 | S121: 0 | T121: 1 | U121: 0 | V121: 5 | W121: 3 | AA121: 0 | AC121: 0 | AD121: 1 | AE121: 0 | AF121: 1
A122: =+VLOOKUP(B122,studies!$A$2:$C$102,3) -> Maddison (1995) | B122: 16 | C122: 1995 | D122: 1 | E122: 1990 | F122: 2010 | G122: 1 | H122: 43.033788 | I122: 0 | J122: 1 | K122: 0 | O122: 0 | P122: 1 | Q122: 0 | R122: 1 | S122: 0 | T122: 0 | U122: 0 | V122: 5 | W122: 3 | Y122: 2.8414595 | AA122: 0 | AB122: 1.2 | AC122: 0 | AD122: 0 | AE122: 0 | AF122: 1
A123: =+VLOOKUP(B123,studies!$A$2:$C$102,3) -> Schauer (1995) | B123: 17 | C123: 1995 | D123: 1 | E123: 1990 | F123: 1990 | G123: 0.5 | H123: 6.3273708 | I123: 0 | J123: 0 | K123: 1 | L123: 75.942805 | M123: 75.942805 | N123: 75.942805 | O123: 1 | P123: 1 | Q123: 0 | R123: 1 | S123: 0 | T123: 0 | U123: 0 | V123: 4.91 | W123: 2.3 | AA123: 0 | AC123: 0 | AD123: 0 | AE123: 0 | AF123: 0
A124: =+VLOOKUP(B124,studies!$A$2:$C$102,3) -> Schauer (1995) | B124: 17 | C124: 1995 | D124: 1 | E124: 1990 | F124: 1990 | G124: 0.5 | H124: 192.08218 | I124: 0 | J124: 0 | K124: 1 | L124: 537.62912 | M124: 537.62912 | N124: 537.62912 | O124: 1 | P124: 1 | Q124: 0 | R124: 1 | S124: 0 | T124: 0 | U124: 0 | V124: 4.91 | W124: 2.3 | AA124: 0 | AC124: 0 | AD124: 0 | AE124: 0 | AF124: 0
A125: =+VLOOKUP(B125,studies!$A$2:$C$102,3) -> Azar & Sterner (1996) | B125: 18 | C125: 1996 | D125: 1 | E125: 1990 | F125: 1990 | G125: 0.044444444 | H125: 305.06325 | I125: 0 | J125: 1 | K125: 0 | O125: 0 | P125: 1 | Q125: 0 | R125: 1 | S125: 0 | T125: 0 | U125: 0 | V125: 2 | W125: 0 | AA125: 0 | AC125: 0 | AD125: 0 | AE125: 0 | AF125: 0
A126: =+VLOOKUP(B126,studies!$A$2:$C$102,3) -> Azar & Sterner (1996) | B126: 18 | C126: 1996 | D126: 1 | E126: 1990 | F126: 1990 | G126: 0.088888889 | H126: 717.79589 | I126: 0 | J126: 1 | K126: 0 | O126: 0 | P126: 1 | Q126: 0 | R126: 1 | S126: 0 | T126: 0 | U126: 0 | V126: 2 | W126: 0 | AA126: 0 | AC126: 0 | AD126: 0 | AE126: 0 | AF126: 0
A127: =+VLOOKUP(B127,studies!$A$2:$C$102,3) -> Azar & Sterner (1996) | B127: 18 | C127: 1996 | D127: 1 | E127: 1990 | F127: 1990 | G127: 0.033333333 | H127: 269.17346 | I127: 0 | J127: 1 | K127: 0 | O127: 0 | P127: 1 | Q127: 0 | R127: 1 | S127: 0 | T127: 0 | U127: 0 | V127: 2.1 | W127: 0.1 | AA127: 0 | AC127: 0 | AD127: 0 | AE127: 0 | AF127: 0
A128: =+VLOOKUP(B128,studies!$A$2:$C$102,3) -> Azar & Sterner (1996) | B128: 18 | C128: 1996 | D128: 1 | E128: 1990 | F128: 1990 | G128: 0.066666667 | H128: 502.45712 | I128: 0 | J128: 1 | K128: 0 | O128: 0 | P128: 1 | Q128: 0 | R128: 1 | S128: 0 | T128: 0 | U128: 0 | V128: 2.1 | W128: 0.1 | AA128: 0 | AC128: 0 | AD128: 0 | AE128: 0 | AF128: 0
A129: =+VLOOKUP(B129,studies!$A$2:$C$102,3) -> Azar & Sterner (1996) | B129: 18 | C129: 1996 | D129: 1 | E129: 1990 | F129: 1990 | G129: 0.022222222 | H129: 114.84734 | I129: 0 | J129: 1 | K129: 0 | O129: 0 | P129: 1 | Q129: 0 | R129: 1 | S129: 0 | T129: 0 | U129: 0 | V129: 3 | W129: 1 | AA129: 0 | AC129: 0 | AD129: 0 | AE129: 0 | AF129: 0
A130: =+VLOOKUP(B130,studies!$A$2:$C$102,3) -> Azar & Sterner (1996) | B130: 18 | C130: 1996 | D130: 1 | E130: 1990 | F130: 1990 | G130: 0.044444444 | H130: 118.43632 | I130: 0 | J130: 1 | K130: 0 | O130: 0 | P130: 1 | Q130: 0 | R130: 1 | S130: 0 | T130: 0 | U130: 0 | V130: 3 | W130: 1 | AA130: 0 | AC130: 0 | AD130: 0 | AE130: 0 | AF130: 0
A131: =+VLOOKUP(B131,studies!$A$2:$C$102,3) -> Azar & Sterner (1996) | B131: 18 | C131: 1996 | D131: 1 | E131: 1990 | F131: 1990 | G131: 0.011111111 | H131: 46.656733 | I131: 0 | J131: 1 | K131: 0 | O131: 0 | P131: 1 | Q131: 0 | R131: 1 | S131: 0 | T131: 0 | U131: 0 | V131: 5 | W131: 3 | AA131: 0 | AC131: 0 | AD131: 0 | AE131: 0 | AF131: 0
A132: =+VLOOKUP(B132,studies!$A$2:$C$102,3) -> Azar & Sterner (1996) | B132: 18 | C132: 1996 | D132: 1 | E132: 1990 | F132: 1990 | G132: 0.022222222 | H132: 46.656733 | I132: 0 | J132: 1 | K132: 0 | O132: 0 | P132: 1 | Q132: 0 | R132: 1 | S132: 0 | T132: 0 | U132: 0 | V132: 5 | W132: 3 | AA132: 0 | AC132: 0 | AD132: 0 | AE132: 0 | AF132: 0
A133: =+VLOOKUP(B133,studies!$A$2:$C$102,3) -> Azar & Sterner (1996) | B133: 18 | C133: 1996 | D133: 1 | E133: 1990 | F133: 1990 | G133: 0.088888889 | H133: 933.13466 | I133: 0 | J133: 1 | K133: 0 | O133: 0 | P133: 1 | Q133: 0 | R133: 1 | S133: 0 | T133: 0 | U133: 0 | V133: 2 | W133: 0 | AA133: 1 | AC133: 0 | AD133: 0 | AE133: 0 | AF133: 0
A134: =+VLOOKUP(B134,studies!$A$2:$C$102,3) -> Azar & Sterner (1996) | B134: 18 | C134: 1996 | D134: 1 | E134: 1990 | F134: 1990 | G134: 0.17777778 | H134: 2117.4979 | I134: 0 | J134: 1 | K134: 0 | O134: 0 | P134: 1 | Q134: 0 | R134: 1 | S134: 0 | T134: 0 | U134: 0 | V134: 2 | W134: 0 | AA134: 1 | AC134: 0 | AD134: 0 | AE134: 0 | AF134: 0
A135: =+VLOOKUP(B135,studies!$A$2:$C$102,3) -> Azar & Sterner (1996) | B135: 18 | C135: 1996 | D135: 1 | E135: 1990 | F135: 1990 | G135: 0.066666667 | H135: 825.46527 | I135: 0 | J135: 1 | K135: 0 | O135: 0 | P135: 1 | Q135: 0 | R135: 1 | S135: 0 | T135: 0 | U135: 0 | V135: 2.1 | W135: 0.1 | AA135: 1 | AC135: 0 | AD135: 0 | AE135: 0 | AF135: 0
A136: =+VLOOKUP(B136,studies!$A$2:$C$102,3) -> Azar & Sterner (1996) | B136: 18 | C136: 1996 | D136: 1 | E136: 1990 | F136: 1990 | G136: 0.13333333 | H136: 1471.4816 | I136: 0 | J136: 1 | K136: 0 | O136: 0 | P136: 1 | Q136: 0 | R136: 1 | S136: 0 | T136: 0 | U136: 0 | V136: 2.1 | W136: 0.1 | AA136: 1 | AC136: 0 | AD136: 0 | AE136: 0 | AF136: 0
... A143: =+VLOOKUP(B143,studies!$A$2:$C$102,3) -> Hohmeyer (1996) | B143: 20 | C143: 1996 | D143: 0 | E143: 1990 | F143: 1995 | G143: 1 | H143: 2463.3451 | I143: 0 | J143: 1 | K143: 0 | O143: 0 | P143: 0 | Q143: 0 | R143: 1 | S143: 0 | T143: 0 | U143: 0 | V143: 0 | W143: -2 | AA143: 0 | AC143: 0 | AD143: 0 | AE143: 0 | AF143: 0
A144: =+VLOOKUP(B144,studies!$A$2:$C$102,3) -> Hope & Maul (1996) | B144: 21 | C144: 1996 | D144: 1 | E144: 1990 | F144: 1990 | G144: 0.1 | H144: 25.122856 | I144: 1 | J144: 0 | K144: 0 | M144: 7.3244479 | N144: 7.3244479 | O144: 1 | P144: 1 | Q144: 0 | R144: 0 | S144: 0 | T144: 0 | U144: 1 | V144: 4 | W144: 2 | AA144: 0 | AC144: 1 | AD144: 0 | AE144: 0 | AF144: 0
A145: =+VLOOKUP(B145,studies!$A$2:$C$102,3) -> Hope & Maul (1996) | B145: 21 | C145: 1996 | D145: 1 | E145: 1990 | F145: 1990 | G145: 1 | H145: 86.135507 | I145: 1 | J145: 0 | K145: 0 | M145: 43.946687 | N145: 450.45354 | O145: 1 | P145: 1 | Q145: 0 | R145: 0 | S145: 0 | T145: 0 | U145: 1 | V145: 4 | W145: 2 | AA145: 0 | AC145: 1 | AD145: 0 | AE145: 0 | AF145: 0
A146: =+VLOOKUP(B146,studies!$A$2:$C$102,3) -> Hope & Maul (1996) | B146: 21 | C146: 1996 | D146: 1 | E146: 1990 | F146: 1990 | G146: 0.1 | H146: 32.300815 | I146: 1 | J146: 0 | K146: 0 | M146: 9.1555598 | N146: 9.1555598 | O146: 1 | P146: 1 | Q146: 0 | R146: 0 | S146: 0 | T146: 0 | U146: 1 | V146: 4 | W146: 2 | AA146: 0 | AC146: 1 | AD146: 0 | AE146: 0 | AF146: 0
A147: =+VLOOKUP(B147,studies!$A$2:$C$102,3) -> Hope & Maul (1996) | B147: 21 | C147: 1996 | D147: 1 | E147: 1990 | F147: 1990 | G147: 0.1 | H147: 68.19061 | I147: 1 | J147: 0 | K147: 0 | M147: 20.142232 | N147: 23.804456 | O147: 1 | P147: 1 | Q147: 0 | R147: 0 | S147: 0 | T147: 0 | U147: 1 | V147: 4 | W147: 2 | AA147: 0 | AC147: 1 | AD147: 0 | AE147: 0 | AF147: 0
A148: =+VLOOKUP(B148,studies!$A$2:$C$102,3) -> Hope & Maul (1996) | B148: 21 | C148: 1996 | D148: 1 | E148: 1990 | F148: 1990 | G148: 0.6 | H148: 17.944897 | I148: 1 | J148: 0 | K148: 0 | M148: 5.4933359 | N148: 3.6622239 | O148: 1 | P148: 1 | Q148: 0 | R148: 1 | S148: 0 | T148: 0 | U148: 1 | V148: 4 | W148: 2 | AA148: 0 | AC148: 1 | AD148: 0 | AE148: 0 | AF148: 0
A149: =+VLOOKUP(B149,studies!$A$2:$C$102,3) -> Hope & Maul (1996) | B149: 21 | C149: 1996 | D149: 1 | E149: 1990 | F149: 1990 | G149: 0.1 | H149: 104.0804 | I149: 1 | J149: 0 | K149: 0 | M149: 31.128903 | N149: 29.297791 | O149: 1 | P149: 1 | Q149: 0 | R149: 0 | S149: 0 | T149: 0 | U149: 1 | V149: 4 | W149: 2 | AA149: 0 | AC149: 1 | AD149: 0 | AE149: 0 | AF149: 0
A150: =+VLOOKUP(B150,studies!$A$2:$C$102,3) -> Nordhaus & Yang (1996) | B150: 22 | C150: 1996 | D150: 1 | E150: 1990 | F150: 2010 | G150: 1 | H150: 14.973347 | I150: 0 | J150: 1 | K150: 0 | O150: 1 | P150: 1 | Q150: 0 | R150: 1 | S150: 0 | T150: 1 | U150: 0 | V150: 5 | W150: 3 | AA150: 0 | AC150: 0 | AD150: 1 | AE150: 0 | AF150: 1
A151: =+VLOOKUP(B151,studies!$A$2:$C$102,3) -> Plambeck & Hope (1996) | B151: 23 | C151: 1996 | D151: 1 | E151: 1990 | F151: 1990 | G151: 0.125 | H151: 10.766938 | I151: 1 | J151: 0 | K151: 0 | M151: 3.6622239 | N151: 5.4933359 | O151: 1 | P151: 1 | Q151: 0 | R151: 1 | S151: 0 | T151: 0 | U151: 1 | V151: 5 | W151: 3 | AA151: 0 | AC151: 1 | AD151: 0 | AE151: 0 | AF151: 0
A152: =+VLOOKUP(B152,studies!$A$2:$C$102,3) -> Plambeck & Hope (1996) | B152: 23 | C152: 1996 | D152: 1 | E152: 1990 | F152: 1990 | G152: 0.0625 | H152: 17.944897 | I152: 1 | J152: 0 | K152: 0 | M152: 5.4933359 | N152: 12.817784 | O152: 1 | P152: 1 | Q152: 0 | R152: 1 | S152: 0 | T152: 0 | U152: 1 | V152: 5 | W152: 3 | AA152: 0 | AC152: 1 | AD152: 0 | AE152: 0 | AF152: 0
A153: =+VLOOKUP(B153,studies!$A$2:$C$102,3) -> Plambeck & Hope (1996) | B153: 23 | C153: 1996 | D153: 1 | E153: 1990 | F153: 1990 | G153: 0.125 | H153: 28.711836 | I153: 1 | J153: 0 | K153: 0 | M153: 9.1555598 | N153: 7.3244479 | O153: 1 | P153: 1 | Q153: 0 | R153: 1 | S153: 0 | T153: 0 | U153: 1 | V153: 5 | W153: 3 | AA153: 0 | AC153: 1 | AD153: 0 | AE153: 0 | AF153: 0
A154: =+VLOOKUP(B154,studies!$A$2:$C$102,3) -> Plambeck & Hope (1996) | B154: 23 | C154: 1996 | D154: 1 | E154: 1990 | F154: 1990 | G154: 0.125 | H154: 28.711836 | I154: 1 | J154: 0 | K154: 0 | M154: 3.6622239 | N154: 18.31112 | O154: 1 | P154: 1 | Q154: 0 | R154: 1 | S154: 0 | T154: 0 | U154: 1 | V154: 5 | W154: 3 | AA154: 0 | AC154: 1 | AD154: 0 | AE154: 0 | AF154: 0
A155: =+VLOOKUP(B155,studies!$A$2:$C$102,3) -> Plambeck & Hope (1996) | B155: 23 | C155: 1996 | D155: 1 | E155: 1990 | F155: 1990 | G155: 0.25 | H155: 75.368568 | I155: 1 | J155: 0 | K155: 0 | M155: 20.142232 | N155: 49.440023 | O155: 1 | P155: 1 | Q155: 0 | R155: 1 | S155: 0 | T155: 0 | U155: 1 | V155: 5 | W155: 3 | AA155: 0 | AC155: 1 | AD155: 0 | AE155: 0 | AF155: 0
A156: =+VLOOKUP(B156,studies!$A$2:$C$102,3) -> Plambeck & Hope (1996) | B156: 23 | C156: 1996 | D156: 1 | E156: 1990 | F156: 1990 | G156: 0.125 | H156: 165.09305 | I156: 1 | J156: 0 | K156: 0 | M156: 47.608911 | N156: 87.893374 | O156: 1 | P156: 1 | Q156: 0 | R156: 1 | S156: 0 | T156: 0 | U156: 1 | V156: 4 | W156: 2 | AA156: 0 | AC156: 1 | AD156: 0 | AE156: 0 | AF156: 0
A157: =+VLOOKUP(B157,studies!$A$2:$C$102,3) -> Plambeck & Hope (1996) | B157: 23 | C157: 1996 | D157: 1 | E157: 1990 | F157: 1990 | G157: 0.125 | H157: 1579.151 | I157: 1 | J157: 0 | K157: 0 | M157: 91.555598 | N157: 73.244479 | O157: 1 | P157: 1 | Q157: 0 | R157: 1 | S157: 0 | T157: 0 | U157: 1 | V157: 2 | W157: 0 | AA157: 0 | AC157: 1 | AD157: 0 | AE157: 0 | AF157: 0
A158: =+VLOOKUP(B158,studies!$A$2:$C$102,3) -> Plambeck & Hope (1996) | B158: 23 | C158: 1996 | D158: 1 | E158: 1990 | F158: 1990 | G158: 0.0625 | H158: 114.84734 | I158: 1 | J158: 0 | K158: 0 | M158: 18.31112 | N158: 43.946687 | O158: 1 | P158: 1 | Q158: 0 | R158: 1 | S158: 0 | T158: 0 | U158: 1 | V158: 5 | W158: 3 | AA158: 0 | AC158: 1 | AD158: 0 | AE158: 0 | AF158: 0
A159: =+VLOOKUP(B159,studies!$A$2:$C$102,3) -> Cline (1997) | B159: 24 | C159: 1997 | D159: 0 | E159: 1995 | F159: 1995 | G159: 1 | H159: 231.72507 | I159: 0 | J159: 1 | K159: 0 | L159: 105.29957 | M159: 107.44854 | N159: 107.44854 | O159: 1 | P159: 1 | Q159: 0 | R159: 1 | S159: 0 | T159: 1 | U159: 0 | V159: NA | W159: NA | AA159: 0 | AC159: 0 | AD159: 0 | AE159: 0 | AF159: 1
A160: =+VLOOKUP(B160,studies!$A$2:$C$102,3) -> Nordhaus & Popp (1997) | B160: 25 | C160: 1997 | D160: 1 | E160: 1990 | F160: 2000 | G160: 0.9 | H160: 30.750526 | I160: 1 | J160: 0 | K160: 0 | L160: 2.063244 | M160: 18.62909 | N160: 35.668284 | O160: 0 | P160: 1 | Q160: 0 | R160: 1 | S160: 0 | T160: 1 | U160: 0 | V160: 5 | W160: 3 | X160: 1 | Y160: 2 | AA160: 0 | AC160: 0 | AD160: 1 | AE160: 0 | AF160: 1
A161: =+VLOOKUP(B161,studies!$A$2:$C$102,3) -> Nordhaus & Popp (1997) | B161: 25 | C161: 1997 | D161: 1 | E161: 1990 | F161: 2010 | G161: 0.1 | H161: 13.00931 | I161: 1 | J161: 0 | K161: 0 | O161: 0 | P161: 1 | Q161: 0 | R161: 1 | S161: 0 | T161: 1 | U161: 0 | V161: 5 | W161: NA | Y161: 2 | AA161: 0 | AC161: 0 | AD161: 1 | AE161: 0 | AF161: 1
A162: =+VLOOKUP(B162,studies!$A$2:$C$102,3) -> Eyre et al. (1999) | B162: 26 | C162: 1999 | D162: 0 | E162: 1995 | F162: 1995 | G162: 0.5 | H162: 448.92605 | I162: 0 | J162: 1 | K162: 0 | O162: 0 | P162: 1 | Q162: 1 | R162: 1 | S162: 1 | T162: 0 | U162: 0 | V162: 1 | W162: -1 | AA162: 1 | AC162: 0 | AD162: 0 | AE162: 0 | AF162: 0
A163: =+VLOOKUP(B163,studies!$A$2:$C$102,3) -> Eyre et al. (1999) | B163: 26 | C163: 1999 | D163: 0 | E163: 1995 | F163: 1995 | G163: 0.5 | H163: 184.8519 | I163: 0 | J163: 1 | K163: 0 | O163: 0 | P163: 1 | Q163: 1 | R163: 1 | S163: 1 | T163: 0 | U163: 0 | V163: 3 | W163: 1 | AA163: 1 | AC163: 0 | AD163: 0 | AE163: 0 | AF163: 0
A164: =+VLOOKUP(B164,studies!$A$2:$C$102,3) -> Eyre et al. (1999) | B164: 26 | C164: 1999 | D164: 0 | E164: 1995 | F164: 1995 | G164: 0.5 | H164: 422.51864 | I164: 0 | J164: 1 | K164: 0 | O164: 0 | P164: 1 | Q164: 1 | R164: 1 | S164: 0 | T164: 0 | U164: 0 | V164: 1 | W164: -1 | AA164: 1 | AC164: 0 | AD164: 0 | AE164: 0 | AF164: 0
A165: =+VLOOKUP(B165,studies!$A$2:$C$102,3) -> Eyre et al. (1999) | B165: 26 | C165: 1999 | D165: 0 | E165: 1995 | F165: 1995 | G165: 0.5 | H165: 195.41487 | I165: 0 | J165: 1 | K165: 0 | O165: 0 | P165: 1 | Q165: 1 | R165: 1 | S165: 0 | T165: 0 | U165: 0 | V165: 3 | W165: 1 | AA165: 1 | AC165: 0 | AD165: 0 | AE165: 0 | AF165: 0
...

Sheet Dataset1
A1: label | B1: idstudy | C1: pubyear | D1: reviewed | E1: dollaryear | F1: emissionyear | G1: tolweight | H1: scc | I1: sccmean | J1: sccbg | K1: sccmed | L1: stdev | M1: stdlow | N1: stdup | O1: iie | P1: mmi | Q1: dim | R1: sce | S1: fund | T1: dicerice | U1: page | V1: cdr | W1: prtp | X1: rra | Y1: growth | Z1: ies | AA1: eweight | AB1: climatesens | AC1: hope | AD1: nordhaus | AE1: tol | AF1: pigou
A2: =+VLOOKUP(B2,studies!$A$2:$C$102,3) -> Cline (1992) | B2: 4 | C2: 1992 | D2: 0 | E2: 1989 | F2: 1990 | G2: 1 | H2: 245.51022 | I2: 0 | J2: 1 | K2: 0 | L2: 111.7847 | M2: 114.06602 | N2: 114.06602 | O2: 1 | P2: 1 | Q2: 0 | R2: 1 | S2: 0 | T2: 0 | U2: 0 | V2: 1.5 | W2: 0 | X2: 1.5 | Y2: 1 | Z2: =1/X2 -> 0.66666667 | AA2: 0 | AC2: 0 | AD2: 0 | AE2: 0 | AF2: 0
A3: =+VLOOKUP(B3,studies!$A$2:$C$102,3) -> Fankhauser (1994) | B3: 14 | C3: 1994 | D3: 1 | E3: 1988 | F3: 2015 | G3: 1 | H3: 46.634123 | I3: 1 | J3: 0 | K3: 0 | L3: 32.256805 | M3: 15.987338 | N3: 29.247424 | O3: 1 | P3: 1 | Q3: 0 | R3: 1 | S3: 0 | T3: 0 | U3: 0 | V3: NA | W3: NA | X3: 1 | AA3: 0 | AB3: 6 | AC3: 0 | AD3: 0 | AE3: 0 | AF3: 0
A4: =+VLOOKUP(B4,studies!$A$2:$C$102,3) -> Schauer (1995) | B4: 17 | C4: 1995 | D4: 1 | E4: 1990 | F4: 1990 | G4: 0.5 | H4: 6.3273708 | I4: 0 | J4: 0 | K4: 1 | L4: 75.942805 | M4: 75.942805 | N4: 75.942805 | O4: 1 | P4: 1 | Q4: 0 | R4: 1 | S4: 0 | T4: 0 | U4: 0 | V4: 4.91 | W4: 2.3 | AA4: 0 | AC4: 0 | AD4: 0 | AE4: 0 | AF4: 0
A5: =+VLOOKUP(B5,studies!$A$2:$C$102,3) -> Schauer (1995) | B5: 17 | C5: 1995 | D5: 1 | E5: 1990 | F5: 1990 | G5: 0.5 | H5: 192.08218 | I5: 0 | J5: 0 | K5: 1 | L5: 537.62912 | M5: 537.62912 | N5: 537.62912 | O5: 1 | P5: 1 | Q5: 0 | R5: 1 | S5: 0 | T5: 0 | U5: 0 | V5: 4.91 | W5: 2.3 | AA5: 0 | AC5: 0 | AD5: 0 | AE5: 0 | AF5: 0
A6: =+VLOOKUP(B6,studies!$A$2:$C$102,3) -> Hope & Maul (1996) | B6: 21 | C6: 1996 | D6: 1 | E6: 1990 | F6: 1990 | G6: 0.1 | H6: 25.122856 | I6: 1 | J6: 0 | K6: 0 | M6: 7.3244479 | N6: 7.3244479 | O6: 1 | P6: 1 | Q6: 0 | R6: 0 | S6: 0 | T6: 0 | U6: 1 | V6: 4 | W6: 2 | AA6: 0 | AC6: 1 | AD6: 0 | AE6: 0 | AF6: 0
A7: =+VLOOKUP(B7,studies!$A$2:$C$102,3) -> Hope & Maul (1996) | B7: 21 | C7: 1996 | D7: 1 | E7: 1990 | F7: 1990 | G7: 1 | H7: 86.135507 | I7: 1 | J7: 0 | K7: 0 | M7: 43.946687 | N7: 450.45354 | O7: 1 | P7: 1 | Q7: 0 | R7: 0 | S7: 0 | T7: 0 | U7: 1 | V7: 4 | W7: 2 | AA7: 0 | AC7: 1 | AD7: 0 | AE7: 0 | AF7: 0
A8: =+VLOOKUP(B8,studies!$A$2:$C$102,3) -> Hope & Maul (1996) | B8: 21 | C8: 1996 | D8: 1 | E8: 1990 | F8: 1990 | G8: 0.1 | H8: 32.300815 | I8: 1 | J8: 0 | K8: 0 | M8: 9.1555598 | N8: 9.1555598 | O8: 1 | P8: 1 | Q8: 0 | R8: 0 | S8: 0 | T8: 0 | U8: 1 | V8: 4 | W8: 2 | AA8: 0 | AC8: 1 | AD8: 0 | AE8: 0 | AF8: 0
A9: =+VLOOKUP(B9,studies!$A$2:$C$102,3) -> Hope & Maul (1996) | B9: 21 | C9: 1996 | D9: 1 | E9: 1990 | F9: 1990 | G9: 0.1 | H9: 68.19061 | I9: 1 | J9: 0 | K9: 0 | M9: 20.142232 | N9: 23.804456 | O9: 1 | P9: 1 | Q9: 0 | R9: 0 | S9: 0 | T9: 0 | U9: 1 | V9: 4 | W9: 2 | AA9: 0 | AC9: 1 | AD9: 0 | AE9: 0 | AF9: 0
A10: =+VLOOKUP(B10,studies!$A$2:$C$102,3) -> Hope & Maul (1996) | B10: 21 | C10: 1996 | D10: 1 | E10: 1990 | F10: 1990 | G10: 0.6 | H10: 17.944897 | I10: 1 | J10: 0 | K10: 0 | M10: 5.4933359 | N10: 3.6622239 | O10: 1 | P10: 1 | Q10: 0 | R10: 1 | S10: 0 | T10: 0 | U10: 1 | V10: 4 | W10: 2 | AA10: 0 | AC10: 1 | AD10: 0 | AE10: 0 | AF10: 0
A11: =+VLOOKUP(B11,studies!$A$2:$C$102,3) -> Hope & Maul (1996) | B11: 21 | C11: 1996 | D11: 1 | E11: 1990 | F11: 1990 | G11: 0.1 | H11: 104.0804 | I11: 1 | J11: 0 | K11: 0 | M11: 31.128903 | N11: 29.297791 | O11: 1 | P11: 1 | Q11: 0 | R11: 0 | S11: 0 | T11: 0 | U11: 1 | V11: 4 | W11: 2 | AA11: 0 | AC11: 1 | AD11: 0 | AE11: 0 | AF11: 0
A12: =+VLOOKUP(B12,studies!$A$2:$C$102,3) -> Plambeck & Hope (1996) | B12: 23 | C12: 1996 | D12: 1 | E12: 1990 | F12: 1990 | G12: 0.125 | H12: 10.766938 | I12: 1 | J12: 0 | K12: 0 | M12: 3.6622239 | N12: 5.4933359 | O12: 1 | P12: 1 | Q12: 0 | R12: 1 | S12: 0 | T12: 0 | U12: 1 | V12: 5 | W12: 3 | AA12: 0 | AC12: 1 | AD12: 0 | AE12: 0 | AF12: 0
A13: =+VLOOKUP(B13,studies!$A$2:$C$102,3) -> Plambeck & Hope (1996) | B13: 23 | C13: 1996 | D13: 1 | E13: 1990 | F13: 1990 | G13: 0.0625 | H13: 17.944897 | I13: 1 | J13: 0 | K13: 0 | M13: 5.4933359 | N13: 12.817784 | O13: 1 | P13: 1 | Q13: 0 | R13: 1 | S13: 0 | T13: 0 | U13: 1 | V13: 5 | W13: 3 | AA13: 0 | AC13: 1 | AD13: 0 | AE13: 0 | AF13: 0
A14: =+VLOOKUP(B14,studies!$A$2:$C$102,3) -> Plambeck & Hope (1996) | B14: 23 | C14: 1996 | D14: 1 | E14: 1990 | F14: 1990 | G14: 0.125 | H14: 28.711836 | I14: 1 | J14: 0 | K14: 0 | M14: 9.1555598 | N14: 7.3244479 | O14: 1 | P14: 1 | Q14: 0 | R14: 1 | S14: 0 | T14: 0 | U14: 1 | V14: 5 | W14: 3 | AA14: 0 | AC14: 1 | AD14: 0 | AE14: 0 | AF14: 0
A15: =+VLOOKUP(B15,studies!$A$2:$C$102,3) -> Plambeck & Hope (1996) | B15: 23 | C15: 1996 | D15: 1 | E15: 1990 | F15: 1990 | G15: 0.125 | H15: 28.711836 | I15: 1 | J15: 0 | K15: 0 | M15: 3.6622239 | N15: 18.31112 | O15: 1 | P15: 1 | Q15: 0 | R15: 1 | S15: 0 | T15: 0 | U15: 1 | V15: 5 | W15: 3 | AA15: 0 | AC15: 1 | AD15: 0 | AE15: 0 | AF15: 0
A16: =+VLOOKUP(B16,studies!$A$2:$C$102,3) -> Plambeck & Hope (1996) | B16: 23 | C16: 1996 | D16: 1 | E16: 1990 | F16: 1990 | G16: 0.25 | H16: 75.368568 | I16: 1 | J16: 0 | K16: 0 | M16: 20.142232 | N16: 49.440023 | O16: 1 | P16: 1 | Q16: 0 | R16: 1 | S16: 0 | T16: 0 | U16: 1 | V16: 5 | W16: 3 | AA16: 0 | AC16: 1 | AD16: 0 | AE16: 0 | AF16: 0
A17: =+VLOOKUP(B17,studies!$A$2:$C$102,3) -> Plambeck & Hope (1996) | B17: 23 | C17: 1996 | D17: 1 | E17: 1990 | F17: 1990 | G17: 0.125 | H17: 165.09305 | I17: 1 | J17: 0 | K17: 0 | M17: 47.608911 | N17: 87.893374 | O17: 1 | P17: 1 | Q17: 0 | R17: 1 | S17: 0 | T17: 0 | U17: 1 | V17: 4 | W17: 2 | AA17: 0 | AC17: 1 | AD17: 0 | AE17: 0 | AF17: 0
... A19: =+VLOOKUP(B19,studies!$A$2:$C$102,3) -> Plambeck & Hope (1996) | B19: 23 | C19: 1996 | D19: 1 | E19: 1990 | F19: 1990 | G19: 0.0625 | H19: 114.84734 | I19: 1 | J19: 0 | K19: 0 | M19: 18.31112 | N19: 43.946687 | O19: 1 | P19: 1 | Q19: 0 | R19: 1 | S19: 0 | T19: 0 | U19: 1 | V19: 5 | W19: 3 | AA19: 0 | AC19: 1 | AD19: 0 | AE19: 0 | AF19: 0
A20: =+VLOOKUP(B20,studies!$A$2:$C$102,3) -> Cline (1997) | B20: 24 | C20: 1997 | D20: 0 | E20: 1995 | F20: 1995 | G20: 1 | H20: 231.72507 | I20: 0 | J20: 1 | K20: 0 | L20: 105.29957 | M20: 107.44854 | N20: 107.44854 | O20: 1 | P20: 1 | Q20: 0 | R20: 1 | S20: 0 | T20: 1 | U20: 0 | V20: NA | W20: NA | AA20: 0 | AC20: 0 | AD20: 0 | AE20: 0 | AF20: 1
A21: =+VLOOKUP(B21,studies!$A$2:$C$102,3) -> Nordhaus & Popp (1997) | B21: 25 | C21: 1997 | D21: 1 | E21: 1990 | F21: 2000 | G21: 0.9 | H21: 30.750526 | I21: 1 | J21: 0 | K21: 0 | L21: 2.063244 | M21: 18.62909 | N21: 35.668284 | O21: 0 | P21: 1 | Q21: 0 | R21: 1 | S21: 0 | T21: 1 | U21: 0 | V21: 5 | W21: 3 | X21: 1 | Y21: 2 | AA21: 0 | AC21: 0 | AD21: 1 | AE21: 0 | AF21: 1
A22: =+VLOOKUP(B22,studies!$A$2:$C$102,3) -> Roughgarden & Schneider (1999) | B22: 27 | C22: 1999 | D22: 1 | E22: 1990 | F22: 1995 | G22: 1 | H22: 70.359294 | I22: 0 | J22: 0 | K22: 1 | M22: 35.897599 | N22: 267.7631 | O22: 1 | P22: 1 | Q22: 0 | R22: 1 | S22: 0 | T22: 1 | U22: 0 | V22: 5 | W22: 3 | AA22: 0 | AC22: 0 | AD22: 0 | AE22: 0 | AF22: 1
A23: =+VLOOKUP(B23,studies!$A$2:$C$102,3) -> Tol (1999) | B23: 28 | C23: 1999 | D23: 1 | E23: 1995 | F23: 2000 | G23: 0.5 | H23: 158.59454 | I23: 0 | J23: 0 | K23: 1 | L23: 115.54745 | M23: 50.861222 | N23: 124.84118 | O23: 1 | P23: 1 | Q23: 1 | R23: 1 | S23: 1 | T23: 0 | U23: 0 | V23: 3 | W23: 1 | AA23: 1 | AC23: 0 | AD23: 0 | AE23: 1 | AF23: 0
A24: =+VLOOKUP(B24,studies!$A$2:$C$102,3) -> Tol (1999) | B24: 28 | C24: 1999 | D24: 1 | E24: 1995 | F24: 2000 | G24: 0.1 | H24: 917.58268 | I24: 0 | J24: 0 | K24: 1 | L24: 604.92488 | M24: 285.51641 | N24: 643.85683 | O24: 1 | P24: 1 | Q24: 1 | R24: 1 | S24: 1 | T24: 0 | U24: 0 | V24: 0 | W24: -2 | AA24: 1 | AC24: 0 | AD24: 0 | AE24: 1 | AF24: 0
A25: =+VLOOKUP(B25,studies!$A$2:$C$102,3) -> Tol (1999) | B25: 28 | C25: 1999 | D25: 1 | E25: 1995 | F25: 2000 | G25: 0.1 | H25: 475.78361 | I25: 0 | J25: 0 | K25: 1 | L25: 323.98598 | M25: 149.11586 | N25: 349.09293 | O25: 1 | P25: 1 | Q25: 1 | R25: 1 | S25: 1 | T25: 0 | U25: 0 | V25: 1 | W25: -1 | AA25: 1 | AC25: 0 | AD25: 0 | AE25: 1 | AF25: 0
A26: =+VLOOKUP(B26,studies!$A$2:$C$102,3) -> Tol (1999) | B26: 28 | C26: 1999 | D26: 1 | E26: 1995 | F26: 2000 | G26: 0.2 | H26: 65.703451 | I26: 0 | J26: 0 | K26: 1 | L26: 49.843998 | M26: 20.806864 | N26: 55.484969 | O26: 1 | P26: 1 | Q26: 1 | R26: 1 | S26: 1 | T26: 0 | U26: 0 | V26: 5 | W26: 3 | AA26: 1 | AC26: 0 | AD26: 0 | AE26: 1 | AF26: 0
A27: =+VLOOKUP(B27,studies!$A$2:$C$102,3) -> Tol (1999) | B27: 28 | C27: 1999 | D27: 1 | E27: 1995 | F27: 2000 | G27: 0.1 | H27: 13.593818 | I27: 0 | J27: 0 | K27: 1 | L27: 11.328181 | M27: 4.6237475 | N27: 12.715305 | O27: 1 | P27: 1 | Q27: 1 | R27: 1 | S27: 1 | T27: 0 | U27: 0 | V27: 10 | W27: 8 | AA27: 1 | AC27: 0 | AD27: 0 | AE27: 1 | AF27: 0
A28: =+VLOOKUP(B28,studies!$A$2:$C$102,3) -> Tol & Downing (2001) | B28: 30 | C28: 2001 | D28: 0 | E28: 1995 | F28: 1995 | G28: 1 | H28: 10.562966 | I28: 0 | J28: 0 | K28: 1 | L28: 8.4503728 | M28: 8.4503728 | N28: 8.4503728 | O28: 0 | P28: 1 | Q28: 1 | R28: 1 | S28: 1 | T28: 0 | U28: 0 | V28: 3 | W28: 1 | AA28: 0 | AC28: 0 | AD28: 0 | AE28: 1 | AF28: 0
A29: =+VLOOKUP(B29,studies!$A$2:$C$102,3) -> Clarkson & Deyes (2002) | B29: 31 | C29: 2002 | D29: 0 | E29: 2000 | F29: 2000 | G29: 1 | H29: 203.52045 | I29: 0 | J29: 1 | K29: 0 | M29: 51.662725 | N29: 103.83696 | O29: 0 | P29: 1 | Q29: 0 | R29: 1 | S29: 1 | T29: 0 | U29: 0 | V29: 3 | W29: 1 | AA29: 1 | AC29: 0 | AD29: 0 | AE29: 0 | AF29: 0
A30: =+VLOOKUP(B30,studies!$A$2:$C$102,3) -> Pearce (2003) | B30: 33 | C30: 2003 | D30: 1 | E30: 2000 | F30: 2000 | G30: 1 | H30: 51.799128 | I30: 0 | J30: 1 | K30: 0 | M30: 19.607965 | N30: 19.607965 | O30: 0 | P30: 1 | Q30: 0 | R30: 1 | S30: 0 | T30: 1 | U30: 0 | V30: 3 | W30: 1 | AA30: 1 | AC30: 0 | AD30: 0 | AE30: 0 | AF30: 0
A31: =+VLOOKUP(B31,studies!$A$2:$C$102,3) -> Mendelsohn (2004) | B31: 39 | C31: 2004 | D31: 0 | E31: 1990 | F31: 2000 | G31: 1 | H31: 3.9626966 | I31: 0 | J31: 1 | K31: 0 | L31: 0.66044944 | M31: 0.673928 | N31: 0.673928 | O31: 1 | P31: 0 | Q31: 0 | R31: 0 | S31: 0 | T31: 0 | U31: 0 | V31: 5 | W31: 3 | AA31: 0 | AC31: 0 | AD31: 0 | AE31: 0 | AF31: 0
A32: =+VLOOKUP(B32,studies!$A$2:$C$102,3) -> Hope (2005b) | B32: 42 | C32: 2005 | D32: 0 | E32: 2000 | F32: 2000 | G32: 0.16666667 | H32: 86.220485 | I32: 1 | J32: 0 | K32: 0 | M32: 33.759801 | N32: 82.864965 | O32: 0 | P32: 1 | Q32: 0 | R32: 1 | S32: 0 | T32: 0 | U32: 1 | W32: 3 | AA32: 1 | AC32: 1 | AD32: 0 | AE32: 0 | AF32: 0
A33: =+VLOOKUP(B33,studies!$A$2:$C$102,3) -> Hope (2005b) | B33: 42 | C33: 2005 | D33: 0 | E33: 2000 | F33: 2000 | G33: 0.16666667 | H33: 70.179464 | I33: 1 | J33: 0 | K33: 0 | M33: 27.621655 | N33: 70.588674 | O33: 0 | P33: 1 | Q33: 0 | R33: 1 | S33: 0 | T33: 0 | U33: 1 | W33: 3 | AA33: 1 | AC33: 1 | AD33: 0 | AE33: 0 | AF33: 0
A34: =+VLOOKUP(B34,studies!$A$2:$C$102,3) -> Hope (2005b) | B34: 42 | C34: 2005 | D34: 0 | E34: 2000 | F34: 2000 | G34: 0.16666667 | H34: 62.158954 | I34: 1 | J34: 0 | K34: 0 | M34: 23.529558 | N34: 62.40448 | O34: 0 | P34: 1 | Q34: 0 | R34: 1 | S34: 0 | T34: 0 | U34: 1 | W34: 3 | AA34: 0 | AC34: 1 | AD34: 0 | AE34: 0 | AF34: 0
A35: =+VLOOKUP(B35,studies!$A$2:$C$102,3) -> Hope (2005b) | B35: 42 | C35: 2005 | D35: 0 | E35: 2000 | F35: 2000 | G35: 0.16666667 | H35: 92.235867 | I35: 1 | J35: 0 | K35: 0 | M35: 36.828873 | N35: 73.657747 | O35: 0 | P35: 1 | Q35: 0 | R35: 1 | S35: 0 | T35: 0 | U35: 1 | W35: 3 | AA35: 1 | AC35: 1 | AD35: 0 | AE35: 0 | AF35: 0
A36: =+VLOOKUP(B36,studies!$A$2:$C$102,3) -> Hope (2005b) | B36: 42 | C36: 2005 | D36: 0 | E36: 2000 | F36: 2000 | G36: 0.16666667 | H36: 74.189719 | I36: 1 | J36: 0 | K36: 0 | M36: 28.644679 | N36: 68.542626 | O36: 0 | P36: 1 | Q36: 0 | R36: 1 | S36: 0 | T36: 0 | U36: 1 | W36: 3 | AA36: 1 | AC36: 1 | AD36: 0 | AE36: 0 | AF36: 0
A37: =+VLOOKUP(B37,studies!$A$2:$C$102,3) -> Hope (2005b) | B37: 42 | C37: 2005 | D37: 0 | E37: 2000 | F37: 2000 | G37: 0.16666667 | H37: 64.164082 | I37: 1 | J37: 0 | K37: 0 | M37: 24.552582 | N37: 59.335407 | O37: 0 | P37: 1 | Q37: 0 | R37: 1 | S37: 0 | T37: 0 | U37: 1 | W37: 3 | AA37: 0 | AC37: 1 | AD37: 0 | AE37: 0 | AF37: 0
A38: =+VLOOKUP(B38,studies!$A$2:$C$102,3) -> Hope (2005a) | B38: 43 | C38: 2005 | D38: 1 | E38: 2000 | F38: 2000 | G38: 1 | H38: 42.107679 | I38: 1 | J38: 0 | K38: 0 | M38: 11.253267 | N38: 27.621655 | O38: 0 | P38: 1 | Q38: 0 | R38: 1 | S38: 0 | T38: 0 | U38: 1 | W38: 3 | AA38: 0 | AC38: 1 | AD38: 0 | AE38: 0 | AF38: 0
A39: =+VLOOKUP(B39,studies!$A$2:$C$102,3) -> Hope (2006) | B39: 46 | C39: 2006 | D39: 1 | E39: 2000 | F39: 2000 | G39: 1 | H39: 38.097424 | I39: 1 | J39: 0 | K39: 0 | M39: 15.345364 | N39: 32.736776 | O39: 0 | P39: 1 | Q39: 0 | R39: 1 | S39: 0 | T39: 0 | U39: 1 | W39: 3 | AA39: 0 | AC39: 1 | AD39: 0 | AE39: 0 | AF39: 0
A40: =+VLOOKUP(B40,studies!$A$2:$C$102,3) -> Wahba & Hope (2006) | B40: 48 | C40: 2006 | D40: 1 | E40: 2000 | F40: 2000 | G40: 0.5 | H40: 38.097424 | I40: 1 | J40: 0 | K40: 0 | M40: 14.32234 | N40: 30.690728 | O40: 0 | P40: 1 | Q40: 0 | R40: 1 | S40: 0 | T40: 0 | U40: 1 | W40: 3 | X40: 1 | AA40: 0 | AC40: 1 | AD40: 0 | AE40: 0 | AF40: 0
A41: =+VLOOKUP(B41,studies!$A$2:$C$102,3) -> Wahba & Hope (2006) | B41: 48 | C41: 2006 | D41: 1 | E41: 2000 | F41: 2000 | G41: 0.5 | H41: 28.071786 | I41: 1 | J41: 0 | K41: 0 | M41: 11.253267 | N41: 27.621655 | O41: 0 | P41: 1 | Q41: 0 | R41: 1 | S41: 0 | T41: 0 | U41: 1 | W41: 3 | X41: 1 | AA41: 0 | AC41: 1 | AD41: 0 | AE41: 0 | AF41: 0
A42: =+VLOOKUP(B42,studies!$A$2:$C$102,3) -> Hope (2008b) | B42: 50 | C42: 2008 | D42: 1 | E42: 2000 | F42: 2000 | G42: 0.2 | H42: 28.071786 | I42: 1 | J42: 0 | K42: 0 | M42: 11.253267 | N42: 27.621655 | O42: 0 | P42: 1 | Q42: 0 | R42: 1 | S42: 0 | T42: 0 | U42: 1 | W42: 2 | X42: 1 | AA42: 0 | AB42: 3.9 | AC42: 1 | AD42: 0 | AE42: 0 | AF42: 0
A43: =+VLOOKUP(B43,studies!$A$2:$C$102,3) -> Hope (2008b) | B43: 50 | C43: 2008 | D43: 1 | E43: 2000 | F43: 2000 | G43: 0.2 | H43: 26.066658 | I43: 1 | J43: 0 | K43: 0 | M43: 10.230243 | N43: 24.552582 | O43: 0 | P43: 1 | Q43: 0 | R43: 1 | S43: 0 | T43: 0 | U43: 1 | W43: 2 | X43: 1 | AA43: 0 | AB43: 3.6 | AC43: 1 | AD43: 0 | AE43: 0 | AF43: 0
A44: =+VLOOKUP(B44,studies!$A$2:$C$102,3) -> Hope (2008b) | B44: 50 | C44: 2008 | D44: 1 | E44: 2000 | F44: 2000 | G44: 0.2 | H44: 26.066658 | I44: 1 | J44: 0 | K44: 0 | M44: 11.253267 | N44: 30.690728 | O44: 0 | P44: 1 | Q44: 0 | R44: 1 | S44: 0 | T44: 0 | U44: 1 | W44: 2 | X44: 1 | AA44: 0 | AB44: 3.3 | AC44: 1 | AD44: 0 | AE44: 0 | AF44: 0
A45: =+VLOOKUP(B45,studies!$A$2:$C$102,3) -> Hope (2008b) | B45: 50 | C45: 2008 | D45: 1 | E45: 2000 | F45: 2000 | G45: 0.2 | H45: 26.066658 | I45: 1 | J45: 0 | K45: 0 | M45: 11.253267 | N45: 24.552582 | O45: 0 | P45: 1 | Q45: 0 | R45: 1 | S45: 0 | T45: 0 | U45: 1 | W45: 2 | X45: 1 | AA45: 0 | AB45: 3.1 | AC45: 1 | AD45: 0 | AE45: 0 | AF45: 0
A46: =+VLOOKUP(B46,studies!$A$2:$C$102,3) -> Hope (2008b) | B46: 50 | C46: 2008 | D46: 1 | E46: 2000 | F46: 2000 | G46: 0.2 | H46: 24.061531 | I46: 1 | J46: 0 | K46: 0 | M46: 10.230243 | N46: 23.529558 | O46: 0 | P46: 1 | Q46: 0 | R46: 1 | S46: 0 | T46: 0 | U46: 1 | W46: 2 | X46: 1 | AA46: 0 | AB46: 3.3 | AC46: 1 | AD46: 0 | AE46: 0 | AF46: 1
A47: =+VLOOKUP(B47,studies!$A$2:$C$102,3) -> Hope (2008a) | B47: 51 | C47: 2008 | D47: 1 | E47: 2000 | F47: 2000 | G47: 0.1 | H47: 32.082041 | I47: 1 | J47: 0 | K47: 0 | M47: 12.276291 | N47: 28.644679 | O47: 0 | P47: 1 | Q47: 0 | R47: 1 | S47: 0 | T47: 0 | U47: 1 | W47: 3 | AA47: 0 | AC47: 1 | AD47: 0 | AE47: 0 | AF47: 0
A48: =+VLOOKUP(B48,studies!$A$2:$C$102,3) -> Hope (2008a) | B48: 51 | C48: 2008 | D48: 1 | E48: 2000 | F48: 2000 | G48: 0.1 | H48: 116.2974 | I48: 1 | J48: 0 | K48: 0 | M48: 46.036092 | N48: 100.25638 | O48: 0 | P48: 1 | Q48: 0 | R48: 1 | S48: 0 | T48: 0 | U48: 1 | V48: 3 | W48: 1 | AA48: 0 | AC48: 1 | AD48: 0 | AE48: 0 | AF48: 0
A49: =+VLOOKUP(B49,studies!$A$2:$C$102,3) -> Hope (2008a) | B49: 51 | C49: 2008 | D49: 1 | E49: 2000 | F49: 2000 | G49: 0.1 | H49: 156.39995 | I49: 1 | J49: 0 | K49: 0 | M49: 61.381456 | N49: 145.26945 | O49: 0 | P49: 1 | Q49: 0 | R49: 1 | S49: 0 | T49: 0 | U49: 1 | V49: 3 | W49: 1 | X49: 1 | AA49: 1 | AC49: 1 | AD49: 0 | AE49: 0 | AF49: 0
A50: =+VLOOKUP(B50,studies!$A$2:$C$102,3) -> Hope (2008a) | B50: 51 | C50: 2008 | D50: 1 | E50: 2000 | F50: 2000 | G50: 0.1 | H50: 130.33329 | I50: 1 | J50: 0 | K50: 0 | M50: 51.151213 | N50: 121.73989 | O50: 0 | P50: 1 | Q50: 0 | R50: 1 | S50: 0 | T50: 0 | U50: 1 | V50: 3 | W50: 1 | X50: 0.5 | AA50: 1 | AC50: 1 | AD50: 0 | AE50: 0 | AF50: 0
A51: =+VLOOKUP(B51,studies!$A$2:$C$102,3) -> Hope (2008a) | B51: 51 | C51: 2008 | D51: 1 | E51: 2000 | F51: 2000 | G51: 0.1 | H51: 50.128189 | I51: 1 | J51: 0 | K51: 0 | M51: 18.414437 | N51: 37.851898 | O51: 0 | P51: 1 | Q51: 0 | R51: 1 | S51: 0 | T51: 0 | U51: 1 | W51: 2 | X51: 1 | AA51: 1 | AC51: 1 | AD51: 0 | AE51: 0 | AF51: 0
A52: =+VLOOKUP(B52,studies!$A$2:$C$102,3) -> Hope (2008a) | B52: 51 | C52: 2008 | D52: 1 | E52: 2000 | F52: 2000 | G52: 0.1 | H52: 138.3538 | I52: 1 | J52: 0 | K52: 0 | M52: 55.24331 | N52: 126.85501 | O52: 0 | P52: 1 | Q52: 0 | R52: 1 | S52: 0 | T52: 0 | U52: 1 | W52: 1 | X52: 1 | AA52: 1 | AC52: 1 | AD52: 0 | AE52: 0 | AF52: 0
A53: =+VLOOKUP(B53,studies!$A$2:$C$102,3) -> Hope (2008a) | B53: 51 | C53: 2008 | D53: 1 | E53: 2000 | F53: 2000 | G53: 0.1 | H53: 124.31791 | I53: 1 | J53: 0 | K53: 0 | M53: 49.105165 | N53: 129.92408 | O53: 0 | P53: 1 | Q53: 0 | R53: 1 | S53: 0 | T53: 0 | U53: 1 | W53: 2 | X53: 0.5 | AA53: 1 | AC53: 1 | AD53: 0 | AE53: 0 | AF53: 0
A54: =+VLOOKUP(B54,studies!$A$2:$C$102,3) -> Hope (2008a) | B54: 51 | C54: 2008 | D54: 1 | E54: 2000 | F54: 2000 | G54: 0.1 | H54: 411.05115 | I54: 1 | J54: 0 | K54: 0 | M54: 166.75295 | N54: 401.02551 | O54: 0 | P54: 1 | Q54: 0 | R54: 1 | S54: 0 | T54: 0 | U54: 1 | W54: 1 | X54: 0.5 | AA54: 1 | AC54: 1 | AD54: 0 | AE54: 0 | AF54: 0
A55: =+VLOOKUP(B55,studies!$A$2:$C$102,3) -> Hope (2008a) | B55: 51 | C55: 2008 | D55: 1 | E55: 2000 | F55: 2000 | G55: 0.1 | H55: 405.03577 | I55: 1 | J55: 0 | K55: 0 | M55: 165.72993 | N55: 435.80834 | O55: 0 | P55: 1 | Q55: 0 | R55: 1 | S55: 0 | T55: 0 | U55: 1 | W55: 2 | X55: 0 | AA55: 0 | AC55: 1 | AD55: 0 | AE55: 0 | AF55: 0
A56: =+VLOOKUP(B56,studies!$A$2:$C$102,3) -> Hope (2008a) | B56: 51 | C56: 2008 | D56: 1 | E56: 2000 | F56: 2000 | G56: 0.1 | H56: 1634.179 | I56: 1 | J56: 0 | K56: 0 | M56: 685.42626 | N56: 1592.8488 | O56: 0 | P56: 1 | Q56: 0 | R56: 1 | S56: 0 | T56: 0 | U56: 1 | W56: 1 | X56: 0 | AA56: 0 | AC56: 1 | AD56: 0 | AE56: 0 | AF56: 0
A57: =+VLOOKUP(B57,studies!$A$2:$C$102,3) -> Anthoff et al. (2009b) | B57: 54 | C57: 2009 | D57: 1 | E57: 1995 | F57: 2010 | G57: 0.25 | H57: -3.1352821 | I57: 0 | J57: 1 | K57: 0 | L57: 3.6689472 | M57: 3.6689472 | N57: 3.6689472 | O57: 0 | P57: 1 | Q57: 1 | R57: 1 | S57: 1 | T57: 0 | U57: 0 | W57: NA | AA57: 0 | AC57: 0 | AD57: 0 | AE57: 1 | AF57: 0
A58: =+VLOOKUP(B58,studies!$A$2:$C$102,3) -> Anthoff et al. (2009b) | B58: 54 | C58: 2009 | D58: 1 | E58: 1995 | F58: 2010 | G58: 0.25 | H58: -0.58369614 | I58: 0 | J58: 1 | K58: 0 | L58: 8.0883608 | M58: 8.0883608 | N58: 8.0883608 | O58: 0 | P58: 1 | Q58: 1 | R58: 1 | S58: 1 | T58: 0 | U58: 0 | W58: NA | AA58: 1 | AC58: 0 | AD58: 0 | AE58: 1 | AF58: 0
A59: =+VLOOKUP(B59,studies!$A$2:$C$102,3) -> Anthoff et al. (2009b) | B59: 54 | C59: 2009 | D59: 1 | E59: 1995 | F59: 2010 | G59: 0.25 | H59: 14.942621 | I59: 1 | J59: 0 | K59: 0 | L59: 11.473798 | M59: 11.473798 | N59: 11.473798 | O59: 0 | P59: 1 | Q59: 1 | R59: 1 | S59: 1 | T59: 0 | U59: 0 | W59: NA | AA59: 0 | AC59: 0 | AD59: 0 | AE59: 1 | AF59: 0
A60: =+VLOOKUP(B60,studies!$A$2:$C$102,3) -> Anthoff et al. (2009b) | B60: 54 | C60: 2009 | D60: 1 | E60: 1995 | F60: 2010 | G60: 0.25 | H60: 73.96264 | I60: 1 | J60: 0 | K60: 0 | L60: 19.762284 | M60: 19.762284 | N60: 19.762284 | O60: 0 | P60: 1 | Q60: 1 | R60: 1 | S60: 1 | T60: 0 | U60: 0 | W60: NA | AA60: 1 | AC60: 0 | AD60: 0 | AE60: 1 | AF60: 0
A61: =+VLOOKUP(B61,studies!$A$2:$C$102,3) -> Dietz (2011) | B61: 66 | C61: 2011 | D61: 1 | E61: 2008 | F61: 2000 | G61: 0.25 | H61: 2614.6574 | I61: 1 | J61: 0 | K61: 0 | M61: 1270.6161 | N61: 4251.1577 | O61: 0 | P61: 1 | Q61: 0 | R61: 1 | S61: 0 | T61: 0 | U61: 1 | W61: 1 | X61: 0.1 | AA61: 0 | AC61: 0 | AD61: 0 | AE61: 0 | AF61: 0
A62: =+VLOOKUP(B62,studies!$A$2:$C$102,3) -> Dietz (2011) | B62: 66 | C62: 2011 | D62: 1 | E62: 2008 | F62: 2000 | G62: 0.25 | H62: 2035.8047 | I62: 1 | J62: 0 | K62: 0 | M62: 1024.6652 | N62: 3037.1241 | O62: 0 | P62: 1 | Q62: 0 | R62: 1 | S62: 0 | T62: 0 | U62: 1 | W62: 3 | X62: 1.3 | AA62: 0 | AC62: 0 | AD62: 0 | AE62: 0 | AF62: 0
A63: =+VLOOKUP(B63,studies!$A$2:$C$102,3) -> Hope (2011) | B63: 67 | C63: 2011 | D63: 1 | E63: 2005 | F63: 2009 | G63: 0.5 | H63: 502.20171 | I63: 1 | J63: 0 | K63: 0 | L63: 1279.2441 | M63: 231.12246 | N63: 421.5531 | O63: 0 | P63: 1 | Q63: 0 | R63: 1 | S63: 0 | T63: 0 | U63: 1 | W63: 1 | AA63: 1 | AC63: 1 | AD63: 0 | AE63: 0 | AF63: 0
A64: =+VLOOKUP(B64,studies!$A$2:$C$102,3) -> Hope (2011) | B64: 67 | C64: 2011 | D64: 1 | E64: 2005 | F64: 2009 | G64: 0.5 | H64: 260.22777 | I64: 1 | J64: 0 | K64: 0 | L64: 984.03392 | M64: 120.21782 | N64: 193.56851 | O64: 0 | P64: 1 | Q64: 0 | R64: 1 | S64: 0 | T64: 0 | U64: 1 | W64: 1 | AA64: 1 | AC64: 1 | AD64: 0 | AE64: 0 | AF64: 0
A65: =+VLOOKUP(B65,studies!$A$2:$C$102,3) -> Nordhaus (2011) | B65: 68 | C65: 2011 | D65: 0 | E65: 2005 | F65: 2015 | G65: 1 | H65: 45.22985 | I65: 0 | J65: 0 | K65: 1 | L65: 21.606703 | M65: 21.606703 | N65: 21.606703 | O65: 1 | P65: 1 | Q65: 0 | R65: 1 | S65: 0 | T65: 1 | U65: 0 | W65: 1.5 | AA65: 1 | AB65: 3 | AC65: 0 | AD65: 1 | AE65: 0 | AF65: 0
A66: =+VLOOKUP(B66,studies!$A$2:$C$102,3) -> Pycroft et al. (2011) | B66: 69 | C66: 2011 | D66: 1 | E66: 2005 | F66: 2009 | G66: 0.090909091 | H66: 241.08831 | I66: 0 | J66: 0 | K66: 1 | M66: 95.391043 | N66: 456.87289 | O66: 0 | P66: 1 | Q66: 0 | R66: 1 | S66: 0 | T66: 0 | U66: 1 | V66: NA | W66: NA | AA66: 1 | AC66: 1 | AD66: 0 | AE66: 0 | AF66: 0
A67: =+VLOOKUP(B67,studies!$A$2:$C$102,3) -> Pycroft et al. (2011) | B67: 69 | C67: 2011 | D67: 1 | E67: 2005 | F67: 2009 | G67: 0.090909091 | H67: 280.44967 | I67: 0 | J67: 0 | K67: 1 | M67: 112.96308 | N67: 795.76212 | O67: 0 | P67: 1 | Q67: 0 | R67: 1 | S67: 0 | T67: 0 | U67: 1 | V67: NA | W67: NA | AA67: 1 | AC67: 1 | AD67: 0 | AE67: 0 | AF67: 0
A68: =+VLOOKUP(B68,studies!$A$2:$C$102,3) -> Pycroft et al. (2011) | B68: 69 | C68: 2011 | D68: 1 | E68: 2005 | F68: 2009 | G68: 0.090909091 | H68: 280.44967 | I68: 0 | J68: 0 | K68: 1 | M68: 115.47337 | N68: 883.62229 | O68: 0 | P68: 1 | Q68: 0 | R68: 1 | S68: 0 | T68: 0 | U68: 1 | V68: NA | W68: NA | AA68: 1 | AC68: 1 | AD68: 0 | AE68: 0 | AF68: 0
A69: =+VLOOKUP(B69,studies!$A$2:$C$102,3) -> Pycroft et al. (2011) | B69: 69 | C69: 2011 | D69: 1 | E69: 2005 | F69: 2009 | G69: 0.090909091 | H69: 265.68916 | I69: 0 | J69: 0 | K69: 1 | M69: 105.43221 | N69: 1280.2482 | O69: 0 | P69: 1 | Q69: 0 | R69: 1 | S69: 0 | T69: 0 | U69: 1 | V69: NA | W69: NA | AA69: 1 | AC69: 1 | AD69: 0 | AE69: 0 | AF69: 0
A70: =+VLOOKUP(B70,studies!$A$2:$C$102,3) -> Pycroft et al. (2011) | B70: 69 | C70: 2011 | D70: 1 | E70: 2005 | F70: 2009 | G70: 0.090909091 | H70: 236.16814 | I70: 0 | J70: 0 | K70: 1 | M70: 92.880753 | N70: 446.83173 | O70: 0 | P70: 1 | Q70: 0 | R70: 1 | S70: 0 | T70: 0 | U70: 1 | V70: NA | W70: NA | AA70: 1 | AC70: 1 | AD70: 0 | AE70: 0 | AF70: 0
A71: =+VLOOKUP(B71,studies!$A$2:$C$102,3) -> Pycroft et al. (2011) | B71: 69 | C71: 2011 | D71: 1 | E71: 2005 | F71: 2009 | G71: 0.090909091 | H71: 246.00848 | I71: 0 | J71: 0 | K71: 1 | M71: 97.901334 | N71: 627.57265 | O71: 0 | P71: 1 | Q71: 0 | R71: 1 | S71: 0 | T71: 0 | U71: 1 | V71: NA | W71: NA | AA71: 1 | AC71: 1 | AD71: 0 | AE71: 0 | AF71: 0
A72: =+VLOOKUP(B72,studies!$A$2:$C$102,3) -> Pycroft et al. (2011) | B72: 69 | C72: 2011 | D72: 1 | E72: 2005 | F72: 2009 | G72: 0.090909091 | H72: 246.00848 | I72: 0 | J72: 0 | K72: 1 | M72: 97.901334 | N72: 627.57265 | O72: 0 | P72: 1 | Q72: 0 | R72: 1 | S72: 0 | T72: 0 | U72: 1 | V72: NA | W72: NA | AA72: 1 | AC72: 1 | AD72: 0 | AE72: 0 | AF72: 0
A73: =+VLOOKUP(B73,studies!$A$2:$C$102,3) -> Pycroft et al. (2011) | B73: 69 | C73: 2011 | D73: 1 | E73: 2005 | F73: 2009 | G73: 0.090909091 | H73: 246.00848 | I73: 0 | J73: 0 | K73: 1 | M73: 97.901334 | N73: 773.16951 | O73: 0 | P73: 1 | Q73: 0 | R73: 1 | S73: 0 | T73: 0 | U73: 1 | V73: NA | W73: NA | AA73: 1 | AC73: 1 | AD73: 0 | AE73: 0 | AF73: 0
A74: =+VLOOKUP(B74,studies!$A$2:$C$102,3) -> Pycroft et al. (2011) | B74: 69 | C74: 2011 | D74: 1 | E74: 2005 | F74: 2009 | G74: 0.090909091 | H74: 285.36984 | I74: 0 | J74: 0 | K74: 1 | M74: 115.47337 | N74: 1081.9353 | O74: 0 | P74: 1 | Q74: 0 | R74: 1 | S74: 0 | T74: 0 | U74: 1 | V74: NA | W74: NA | AA74: 1 | AC74: 1 | AD74: 0 | AE74: 0 | AF74: 0
A75: =+VLOOKUP(B75,studies!$A$2:$C$102,3) -> Pycroft et al. (2011) | B75: 69 | C75: 2011 | D75: 1 | E75: 2005 | F75: 2009 | G75: 0.090909091 | H75: 280.44967 | I75: 0 | J75: 0 | K75: 1 | M75: 112.96308 | N75: 1240.0836 | O75: 0 | P75: 1 | Q75: 0 | R75: 1 | S75: 0 | T75: 0 | U75: 1 | V75: NA | W75: NA | AA75: 1 | AC75: 1 | AD75: 0 | AE75: 0 | AF75: 0
A76: =+VLOOKUP(B76,studies!$A$2:$C$102,3) -> Pycroft et al. (2011) | B76: 69 | C76: 2011 | D76: 1 | E76: 2005 | F76: 2009 | G76: 0.090909091 | H76: 270.60933 | I76: 0 | J76: 0 | K76: 1 | M76: 110.45279 | N76: 1968.0678 | O76: 0 | P76: 1 | Q76: 0 | R76: 1 | S76: 0 | T76: 0 | U76: 1 | V76: NA | W76: NA | AA76: 1 | AC76: 1 | AD76: 0 | AE76: 0 | AF76: 0
A77: =+VLOOKUP(B77,studies!$A$2:$C$102,3) -> Ackerman & Stanton (2012) | B77: 72 | C77: 2012 | D77: 1 | E77: 2007 | F77: 2010 | G77: 0.07037037 | H77: 530.35895 | I77: 1 | J77: 0 | K77: 0 | M77: 334.7994 | N77: 334.7994 | O77: 0 | P77: 1 | Q77: 0 | R77: 1 | S77: 0 | T77: 1 | U77: 0 | V77: 1.5 | W77: -0.5 | AA77: 0 | AC77: 0 | AD77: 0 | AE77: 0 | AF77: 0
A78: =+VLOOKUP(B78,studies!$A$2:$C$102,3) -> Ackerman & Stanton (2012) | B78: 72 | C78: 2012 | D78: 1 | E78: 2007 | F78: 2010 | G78: 0.035185185 | H78: 125.84789 | I78: 1 | J78: 0 | K78: 0 | M78: 64.208105 | N78: 64.208105 | O78: 0 | P78: 1 | Q78: 0 | R78: 1 | S78: 0 | T78: 1 | U78: 0 | V78: 3 | W78: 1 | AA78: 0 | AC78: 0 | AD78: 0 | AE78: 0 | AF78: 0
A79: =+VLOOKUP(B79,studies!$A$2:$C$102,3) -> Ackerman & Stanton (2012) | B79: 72 | C79: 2012 | D79: 1 | E79: 2007 | F79: 2010 | G79: 0.14074074 | H79: 1083.1907 | I79: 1 | J79: 0 | K79: 0 | M79: 538.88945 | N79: 538.88945 | O79: 0 | P79: 1 | Q79: 0 | R79: 1 | S79: 0 | T79: 1 | U79: 0 | V79: 1.5 | W79: -0.5 | AA79: 0 | AC79: 0 | AD79: 0 | AE79: 0 | AF79: 0
A80: =+VLOOKUP(B80,studies!$A$2:$C$102,3) -> Ackerman & Stanton (2012) | B80: 72 | C80: 2012 | D80: 1 | E80: 2007 | F80: 2010 | G80: 0.07037037 | H80: 278.66318 | I80: 1 | J80: 0 | K80: 0 | M80: 121.53677 | N80: 121.53677 | O80: 0 | P80: 1 | Q80: 0 | R80: 1 | S80: 0 | T80: 1 | U80: 0 | V80: 3 | W80: 1 | AA80: 0 | AC80: 0 | AD80: 0 | AE80: 0 | AF80: 0
A81: =+VLOOKUP(B81,studies!$A$2:$C$102,3) -> Ackerman & Stanton (2012) | B81: 72 | C81: 2012 | D81: 1 | E81: 2007 | F81: 2010 | G81: 0.14074074 | H81: 1847.2672 | I81: 1 | J81: 0 | K81: 0 | M81: 1093.8309 | N81: 1093.8309 | O81: 0 | P81: 1 | Q81: 0 | R81: 1 | S81: 0 | T81: 1 | U81: 0 | V81: 1.5 | W81: -0.5 | AA81: 0 | AC81: 0 | AD81: 0 | AE81: 0 | AF81: 0
A82: =+VLOOKUP(B82,studies!$A$2:$C$102,3) -> Ackerman & Stanton (2012) | B82: 72 | C82: 2012 | D82: 1 | E82: 2007 | F82: 2010 | G82: 0.07037037 | H82: 346.08169 | I82: 1 | J82: 0 | K82: 0 | M82: 282.05703 | N82: 282.05703 | O82: 0 | P82: 1 | Q82: 0 | R82: 1 | S82: 0 | T82: 1 | U82: 0 | V82: 3 | W82: 1 | AA82: 0 | AC82: 0 | AD82: 0 | AE82: 0 | AF82: 0
A83: =+VLOOKUP(B83,studies!$A$2:$C$102,3) -> Ackerman & Stanton (2012) | B83: 72 | C83: 2012 | D83: 1 | E83: 2007 | F83: 2010 | G83: 0.28148148 | H83: 2000.0825 | I83: 1 | J83: 0 | K83: 0 | M83: 1025.0365 | N83: 1025.0365 | O83: 0 | P83: 1 | Q83: 0 | R83: 1 | S83: 0 | T83: 1 | U83: 0 | V83: 1.5 | W83: -0.5 | AA83: 0 | AC83: 0 | AD83: 0 | AE83: 0 | AF83: 0
A84: =+VLOOKUP(B84,studies!$A$2:$C$102,3) -> Ackerman & Stanton (2012) | B84: 72 | C84: 2012 | D84: 1 | E84: 2007 | F84: 2010 | G84: 0.14074074 | H84: 431.47846 | I84: 1 | J84: 0 | K84: 0 | M84: 275.17759 | N84: 275.17759 | O84: 0 | P84: 1 | Q84: 0 | R84: 1 | S84: 0 | T84: 1 | U84: 0 | V84: 3 | W84: 1 | AA84: 0 | AC84: 0 | AD84: 0 | AE84: 0 | AF84: 0
A85: =+VLOOKUP(B85,studies!$A$2:$C$102,3) -> Johnson & Hope (2012) | B85: 77 | C85: 2012 | D85: 1 | E85: 2007 | F85: 2010 | G85: 0.18867925 | H85: 1195.5549 | I85: 0 | J85: 1 | K85: 0 | M85: 1128.2281 | N85: 1128.2281 | O85: 0 | P85: 1 | Q85: 0 | R85: 1 | S85: 1 | T85: 1 | U85: 1 | V85: 1 | W85: NA | AA85: 0 | AC85: 0 | AD85: 0 | AE85: 0 | AF85: 0
A86: =+VLOOKUP(B86,studies!$A$2:$C$102,3) -> Johnson & Hope (2012) | B86: 77 | C86: 2012 | D86: 1 | E86: 2007 | F86: 2010 | G86: 0.18867925 | H86: 548.33722 | I86: 0 | J86: 1 | K86: 0 | M86: 538.88945 | N86: 538.88945 | O86: 0 | P86: 1 | Q86: 0 | R86: 1 | S86: 1 | T86: 1 | U86: 1 | V86: 1.5 | W86: NA | AA86: 0 | AC86: 0 | AD86: 0 | AE86: 0 | AF86: 0
A87: =+VLOOKUP(B87,studies!$A$2:$C$102,3) -> Johnson & Hope (2012) | B87: 77 | C87: 2012 | D87: 1 | E87: 2007 | F87: 2010 | G87: 0.18867925 | H87: 278.66318 | I87: 0 | J87: 1 | K87: 0 | M87: 286.64333 | N87: 286.64333 | O87: 0 | P87: 1 | Q87: 0 | R87: 1 | S87: 1 | T87: 1 | U87: 1 | V87: 2 | W87: NA | AA87: 0 | AC87: 0 | AD87: 0 | AE87: 0 | AF87: 0
A88: =+VLOOKUP(B88,studies!$A$2:$C$102,3) -> Johnson & Hope (2012) | B88: 77 | C88: 2012 | D88: 1 | E88: 2007 | F88: 2010 | G88: 0.018867925 | H88: 157.30986 | I88: 0 | J88: 1 | K88: 0 | M88: 165.10656 | N88: 165.10656 | O88: 0 | P88: 1 | Q88: 0 | R88: 1 | S88: 1 | T88: 1 | U88: 1 | V88: 2.5 | W88: NA | AA88: 0 | AC88: 0 | AD88: 0 | AE88: 0 | AF88: 0
A89: =+VLOOKUP(B89,studies!$A$2:$C$102,3) -> Johnson & Hope (2012) | B89: 77 | C89: 2012 | D89: 1 | E89: 2007 | F89: 2010 | G89: 0.018867925 | H89: 94.385914 | I89: 0 | J89: 1 | K89: 0 | M89: 100.89845 | N89: 100.89845 | O89: 0 | P89: 1 | Q89: 0 | R89: 1 | S89: 1 | T89: 1 | U89: 1 | V89: 3 | W89: NA | AA89: 0 | AC89: 0 | AD89: 0 | AE89: 0 | AF89: 0
A90: =+VLOOKUP(B90,studies!$A$2:$C$102,3) -> Johnson & Hope (2012) | B90: 77 | C90: 2012 | D90: 1 | E90: 2007 | F90: 2010 | G90: 0.018867925 | H90: 22.472837 | I90: 0 | J90: 1 | K90: 0 | M90: 25.224613 | N90: 25.224613 | O90: 0 | P90: 1 | Q90: 0 | R90: 1 | S90: 1 | T90: 1 | U90: 1 | V90: 5 | W90: NA | AA90: 0 | AC90: 0 | AD90: 0 | AE90: 0 | AF90: 0
A91: =+VLOOKUP(B91,studies!$A$2:$C$102,3) -> Johnson & Hope (2012) | B91: 77 | C91: 2012 | D91: 1 | E91: 2007 | F91: 2010 | G91: 0.18867925 | H91: 247.2012 | I91: 0 | J91: 1 | K91: 0 | M91: 231.60781 | N91: 231.60781 | O91: 0 | P91: 1 | Q91: 0 | R91: 1 | S91: 1 | T91: 1 | U91: 1 | V91: NA | W91: NA | AA91: 0 | AC91: 0 | AD91: 0 | AE91: 0 | AF91: 0
A92: =+VLOOKUP(B92,studies!$A$2:$C$102,3) -> Johnson & Hope (2012) | B92: 77 | C92: 2012 | D92: 1 | E92: 2007 | F92: 2010 | G92: 0.18867925 | H92: 786.54928 | I92: 0 | J92: 1 | K92: 0 | M92: 470.09505 | N92: 470.09505 | O92: 0 | P92: 1 | Q92: 0 | R92: 1 | S92: 1 | T92: 1 | U92: 1 | V92: NA | W92: NA | AA92: 0 | AC92: 0 | AD92: 0 | AE92: 0 | AF92: 0
A93: =+VLOOKUP(B93,studies!$A$2:$C$102,3) -> Kopp et al. (2012) | B93: 78 | C93: 2012 | D93: 1 | E93: 2005 | F93: 2015 | G93: 0.0069444444 | H93: 495.3619 | I93: 0 | J93: 0 | K93: 1 | M93: 219.31607 | N93: 268.05298 | O93: 0 | P93: 1 | Q93: 0 | R93: 1 | S93: 0 | T93: 1 | U93: 0 | V93: 3 | W93: 3 | AA93: 0 | AC93: 0 | AD93: 0 | AE93: 0 | AF93: 1
A94: =+VLOOKUP(B94,studies!$A$2:$C$102,3) -> Kopp et al. (2012) | B94: 78 | C94: 2012 | D94: 1 | E94: 2005 | F94: 2015 | G94: 0.0069444444 | H94: 525.38383 | I94: 0 | J94: 0 | K94: 1 | M94: 145.51447 | N94: 306.34626 | O94: 0 | P94: 1 | Q94: 0 | R94: 1 | S94: 0 | T94: 1 | U94: 0 | V94: 3 | W94: 3 | AA94: 0 | AC94: 0 | AD94: 0 | AE94: 0 | AF94: 1
A95: =+VLOOKUP(B95,studies!$A$2:$C$102,3) -> Kopp et al. (2012) | B95: 78 | C95: 2012 | D95: 1 | E95: 2005 | F95: 2015 | G95: 0.0069444444 | H95: 480.35093 | I95: 0 | J95: 0 | K95: 1 | M95: 137.85582 | N95: 314.00491 | O95: 0 | P95: 1 | Q95: 0 | R95: 1 | S95: 0 | T95: 1 | U95: 0 | V95: 3 | W95: 3 | AA95: 0 | AC95: 0 | AD95: 0 | AE95: 0 | AF95: 1
A96: =+VLOOKUP(B96,studies!$A$2:$C$102,3) -> Kopp et al. (2012) | B96: 78 | C96: 2012 | D96: 1 | E96: 2005 | F96: 2015 | G96: 0.0069444444 | H96: 690.50446 | I96: 0 | J96: 0 | K96: 1 | M96: 176.1491 | N96: 306.34626 | O96: 0 | P96: 1 | Q96: 0 | R96: 1 | S96: 0 | T96: 1 | U96: 0 | V96: 3 | W96: 3 | AA96: 0 | AC96: 0 | AD96: 0 | AE96: 0 | AF96: 1
A97: =+VLOOKUP(B97,studies!$A$2:$C$102,3) -> Kopp et al. (2012) | B97: 78 | C97: 2012 | D97: 1 | E97: 2005 | F97: 2015 | G97: 0.0069444444 | H97: 360.2632 | I97: 0 | J97: 0 | K97: 1 | M97: 91.903877 | N97: 168.49044 | O97: 0 | P97: 1 | Q97: 0 | R97: 1 | S97: 0 | T97: 1 | U97: 0 | V97: 3 | W97: 3 | AA97: 0 | AC97: 0 | AD97: 0 | AE97: 0 | AF97: 1
A98: =+VLOOKUP(B98,studies!$A$2:$C$102,3) -> Kopp et al. (2012) | B98: 78 | C98: 2012 | D98: 1 | E98: 2005 | F98: 2015 | G98: 0.0069444444 | H98: 705.51543 | I98: 0 | J98: 0 | K98: 1 | M98: 176.1491 | N98: 260.39432 | O98: 0 | P98: 1 | Q98: 0 | R98: 1 | S98: 0 | T98: 1 | U98: 0 | V98: 3 | W98: 3 | AA98: 0 | AC98: 0 | AD98: 0 | AE98: 0 | AF98: 1
A99: =+VLOOKUP(B99,studies!$A$2:$C$102,3) -> Kopp et al. (2012) | B99: 78 | C99: 2012 | D99: 1 | E99: 2005 | F99: 2015 | G99: 0.0069444444 | H99: 405.2961 | I99: 0 | J99: 0 | K99: 1 | M99: 99.562534 | N99: 214.44238 | O99: 0 | P99: 1 | Q99: 0 | R99: 1 | S99: 0 | T99: 1 | U99: 0 | V99: 3 | W99: 3 | AA99: 0 | AC99: 0 | AD99: 0 | AE99: 0 | AF99: 1
A100: =+VLOOKUP(B100,studies!$A$2:$C$102,3) -> Kopp et al. (2012) | B100: 78 | C100: 2012 | D100: 1 | E100: 2005 | F100: 2015 | G100: 0.0069444444 | H100: 525.38383 | I100: 0 | J100: 0 | K100: 1 | M100: 145.51447 | N100: 283.37029 | O100: 0 | P100: 1 | Q100: 0 | R100: 1 | S100: 0 | T100: 1 | U100: 0 | V100: 3 | W100: 3 | AA100: 0 | AC100: 0 | AD100: 0 | AE100: 0 | AF100: 1
A101: =+VLOOKUP(B101,studies!$A$2:$C$102,3) -> Kopp et al. (2012) | B101: 78 | C101: 2012 | D101: 1 | E101: 2005 | F101: 2015 | G101: 0.0069444444 | H101: 495.3619 | I101: 0 | J101: 0 | K101: 1 | M101: 130.19716 | N101: 268.05298 | O101: 0 | P101: 1 | Q101: 0 | R101: 1 | S101: 0 | T101: 1 | U101: 0 | V101: 3 | W101: 3 | AA101: 0 | AC101: 0 | AD101: 0 | AE101: 0 | AF101: 1
...

Sheet Dataset2
A1: label | B1: idstudy | C1: pubyear | D1: reviewed | E1: dollaryear | F1: emissionyear | G1: tolweight | H1: scc | I1: sccmean | J1: sccbg | K1: sccmed | L1: stdev | M1: stdlow | N1: stdup | O1: iie | P1: mmi | Q1: dim | R1: sce | S1: fund | T1: dicerice | U1: page | V1: cdr | W1: prtp | X1: rra | Y1: growth | Z1: ies | AA1: eweight | AB1: climatesens | AC1: hope | AD1: nordhaus | AE1: tol | AF1: pigou
A2: =+VLOOKUP(B2,studies!$A$2:$C$102,3) -> Nordhaus (1982) | B2: 1 | C2: 1982 | D2: 1 | E2: 1980 | F2: 1980 | H2: =+IF(VLOOKUP($A2,'Dataset2 ad'!$D$3:$L$855,4,FALSE)="","",VLOOKUP($A2,'Dataset2 ad'!$D$3:$L$855,4,FALSE)) -> 1134.285 | I2: 0 | J2: 1 | K2: 0 | M2: =+IF(VLOOKUP($A2,'Dataset2 ad'!$D$3:$L$855,8,FALSE)="","",VLOOKUP($A2,'Dataset2 ad'!$D$3:$L$855,8,FALSE)) -> 887.80844 | N2: =+IF(VLOOKUP($A2,'Dataset2 ad'!$D$3:$L$855,9,FALSE)="","",VLOOKUP($A2,'Dataset2 ad'!$D$3:$L$855,9,FALSE)) -> 999.09259 | O2: 1 | P2: 0 | Q2: 0 | R2: 0 | S2: 0 | T2: 0 | U2: 0 | W2: 1 | Y2: =+AVERAGE(Dataset0!Y2:Y3) -> 2.5 | AA2: 0 | AC2: 0 | AD2: 1 | AE2: 0 | AF2: 0
A3: =+VLOOKUP(B3,studies!$A$2:$C$102,3) -> Nordhaus (1991) | B3: 3 | C3: 1991 | D3: 1 | E3: 1989 | F3: 1990 | H3: =+IF(VLOOKUP($A3,'Dataset2 ad'!$D$3:$L$855,4,FALSE)="","",VLOOKUP($A3,'Dataset2 ad'!$D$3:$L$855,4,FALSE)) -> 101.67175 | I3: 0 | J3: 1 | K3: 0 | M3: =+IF(VLOOKUP($A3,'Dataset2 ad'!$D$3:$L$855,8,FALSE)="","",VLOOKUP($A3,'Dataset2 ad'!$D$3:$L$855,8,FALSE)) -> 47.10354 | N3: =+IF(VLOOKUP($A3,'Dataset2 ad'!$D$3:$L$855,9,FALSE)="","",VLOOKUP($A3,'Dataset2 ad'!$D$3:$L$855,9,FALSE)) -> 321.44486 | O3: 1 | P3: 0 | Q3: 0 | R3: 0 | S3: 0 | T3: 1 | U3: 0 | V3: =+AVERAGE(Dataset0!V5:V13) -> 3.6666667 | W3: =+AVERAGE(Dataset0!W5:W13) -> 1.6666667 | X3: =+AVERAGE(Dataset0!X5:X13) -> 1 | Y3: =+AVERAGE(Dataset0!Y5:Y13) -> 2 | Z3: =1/X3 -> 1 | AA3: 0 | AC3: 0 | AD3: 1 | AE3: 0 | AF3: 0
A4: =+VLOOKUP(B4,studies!$A$2:$C$102,3) -> Haraden (1993) | B4: 8 | C4: 1993 | D4: 1 | E4: 1989 | F4: 1989 | H4: =+IF(VLOOKUP($A4,'Dataset2 ad'!$D$3:$L$855,4,FALSE)="","",VLOOKUP($A4,'Dataset2 ad'!$D$3:$L$855,4,FALSE)) -> 11.623804 | I4: 0 | J4: 1 | K4: 0 | M4: =+IF(VLOOKUP($A4,'Dataset2 ad'!$D$3:$L$855,8,FALSE)="","",VLOOKUP($A4,'Dataset2 ad'!$D$3:$L$855,8,FALSE)) -> 2.0239366 | N4: =+IF(VLOOKUP($A4,'Dataset2 ad'!$D$3:$L$855,9,FALSE)="","",VLOOKUP($A4,'Dataset2 ad'!$D$3:$L$855,9,FALSE)) -> 10.388347 | O4: 0 | P4: 0 | Q4: 0 | R4: 0 | S4: 0 | T4: 0 | U4: 0 | V4: 4 | W4: 2 | X4: 1.25 | Y4: =+AVERAGE(Dataset0!Y18:Y20) -> 2.6333333 | Z4: =1/X4 -> 0.8 | AA4: 0 | AC4: 0 | AD4: 0 | AE4: 0 | AF4: 0
A5: =+VLOOKUP(B5,studies!$A$2:$C$102,3) -> Parry (1993) | B5: 10 | C5: 1993 | D5: 1 | E5: 1991 | F5: 1990 | H5: =+IF(VLOOKUP($A5,'Dataset2 ad'!$D$3:$L$855,4,FALSE)="","",VLOOKUP($A5,'Dataset2 ad'!$D$3:$L$855,4,FALSE)) -> 1.5406384 | I5: 0 | J5: 1 | K5: 0 | M5: =+IF(VLOOKUP($A5,'Dataset2 ad'!$D$3:$L$855,8,FALSE)="","",VLOOKUP($A5,'Dataset2 ad'!$D$3:$L$855,8,FALSE)) -> 0.75414738 | N5: =+IF(VLOOKUP($A5,'Dataset2 ad'!$D$3:$L$855,9,FALSE)="","",VLOOKUP($A5,'Dataset2 ad'!$D$3:$L$855,9,FALSE)) -> 892.40989 | O5: 0 | P5: 1 | Q5: 0 | R5: 0 | S5: 0 | T5: 1 | U5: 0 | W5: 0 | AA5: 0 | AC5: 0 | AD5: 0 | AE5: 0 | AF5: 0
A6: =+VLOOKUP(B6,studies!$A$2:$C$102,3) -> Peck & Teisberg (1993) | B6: 11 | C6: 1993 | D6: 1 | E6: 1989 | F6: 2030 | H6: =+IF(VLOOKUP($A6,'Dataset2 ad'!$D$3:$L$855,4,FALSE)="","",VLOOKUP($A6,'Dataset2 ad'!$D$3:$L$855,4,FALSE)) -> 24.543219 | I6: 0 | J6: 1 | K6: 0 | M6: =+IF(VLOOKUP($A6,'Dataset2 ad'!$D$3:$L$855,8,FALSE)="","",VLOOKUP($A6,'Dataset2 ad'!$D$3:$L$855,8,FALSE)) -> 8.6407814 | N6: =+IF(VLOOKUP($A6,'Dataset2 ad'!$D$3:$L$855,9,FALSE)="","",VLOOKUP($A6,'Dataset2 ad'!$D$3:$L$855,9,FALSE)) -> 15.695059 | O6: 0 | P6: 1 | Q6: 0 | R6: 1 | S6: 0 | T6: 0 | U6: 0 | V6: 5 | W6: 3 | AA6: 0 | AC6: 0 | AD6: 0 | AE6: 0 | AF6: 1
A7: =+VLOOKUP(B7,studies!$A$2:$C$102,3) -> Reilly & Richards (1993) | B7: 12 | C7: 1993 | D7: 1 | E7: 1990 | F7: 1990 | H7: =+IF(VLOOKUP($A7,'Dataset2 ad'!$D$3:$L$855,4,FALSE)="","",VLOOKUP($A7,'Dataset2 ad'!$D$3:$L$855,4,FALSE)) -> 71.719773 | I7: 0 | J7: 1 | K7: 0 | M7: =+IF(VLOOKUP($A7,'Dataset2 ad'!$D$3:$L$855,8,FALSE)="","",VLOOKUP($A7,'Dataset2 ad'!$D$3:$L$855,8,FALSE)) -> 18.060868 | N7: =+IF(VLOOKUP($A7,'Dataset2 ad'!$D$3:$L$855,9,FALSE)="","",VLOOKUP($A7,'Dataset2 ad'!$D$3:$L$855,9,FALSE)) -> 52.705506 | O7: 0 | P7: 1 | Q7: 0 | R7: 0 | S7: 0 | T7: 0 | U7: 0 | V7: =+AVERAGE(Dataset0!V109:V116) -> 5 | W7: =+AVERAGE(Dataset0!W109:W116) -> 3 | AA7: 0 | AC7: 0 | AD7: 0 | AE7: 0 | AF7: 0
A8: =+VLOOKUP(B8,studies!$A$2:$C$102,3) -> Azar (1994) | B8: 13 | C8: 1994 | D8: 1 | E8: 1990 | F8: 1990 | H8: =+IF(VLOOKUP($A8,'Dataset2 ad'!$D$3:$L$855,4,FALSE)="","",VLOOKUP($A8,'Dataset2 ad'!$D$3:$L$855,4,FALSE)) -> 717.79589 | I8: 0 | J8: 1 | K8: 0 | M8: =+IF(VLOOKUP($A8,'Dataset2 ad'!$D$3:$L$855,8,FALSE)="","",VLOOKUP($A8,'Dataset2 ad'!$D$3:$L$855,8,FALSE)) -> 247.20012 | N8: =+IF(VLOOKUP($A8,'Dataset2 ad'!$D$3:$L$855,9,FALSE)="","",VLOOKUP($A8,'Dataset2 ad'!$D$3:$L$855,9,FALSE)) -> 494.40023 | O8: 0 | P8: 0 | Q8: 0 | R8: 0 | S8: 0 | T8: 0 | U8: 0 | W8: 0 | AA8: 0 | AC8: 0 | AD8: 0 | AE8: 0 | AF8: 0
A9: =+VLOOKUP(B9,studies!$A$2:$C$102,3) -> Schauer (1995) | B9: 17 | C9: 1995 | D9: 1 | E9: 1990 | F9: 1990 | H9: =+IF(VLOOKUP($A9,'Dataset2 ad'!$D$3:$L$855,4,FALSE)="","",VLOOKUP($A9,'Dataset2 ad'!$D$3:$L$855,4,FALSE)) -> 99.204776 | I9: 0 | J9: 0 | K9: 1 | M9: =+IF(VLOOKUP($A9,'Dataset2 ad'!$D$3:$L$855,8,FALSE)="","",VLOOKUP($A9,'Dataset2 ad'!$D$3:$L$855,8,FALSE)) -> 93.705105 | N9: =+IF(VLOOKUP($A9,'Dataset2 ad'!$D$3:$L$855,9,FALSE)="","",VLOOKUP($A9,'Dataset2 ad'!$D$3:$L$855,9,FALSE)) -> 105.85465 | O9: 1 | P9: 1 | Q9: 0 | R9: 1 | S9: 0 | T9: 0 | U9: 0 | V9: 4.91 | W9: 2.3 | AA9: 0 | AC9: 0 | AD9: 0 | AE9: 0 | AF9: 0
A10: =+VLOOKUP(B10,studies!$A$2:$C$102,3) -> Azar & Sterner (1996) | B10: 18 | C10: 1996 | D10: 1 | E10: 1990 | F10: 1990 | H10: =+IF(VLOOKUP($A10,'Dataset2 ad'!$D$3:$L$855,4,FALSE)="","",VLOOKUP($A10,'Dataset2 ad'!$D$3:$L$855,4,FALSE)) -> 323.00815 | I10: 0 | J10: 1 | K10: 0 | M10: =+IF(VLOOKUP($A10,'Dataset2 ad'!$D$3:$L$855,8,FALSE)="","",VLOOKUP($A10,'Dataset2 ad'!$D$3:$L$855,8,FALSE)) -> 140.99562 | N10: =+IF(VLOOKUP($A10,'Dataset2 ad'!$D$3:$L$855,9,FALSE)="","",VLOOKUP($A10,'Dataset2 ad'!$D$3:$L$855,9,FALSE)) -> 668.35587 | O10: 0 | P10: 1 | Q10: 0 | R10: 1 | S10: 0 | T10: 0 | U10: 0 | V10: =+AVERAGE(Dataset0!V125:V140) -> 3.025 | W10: =+AVERAGE(Dataset0!W125:W140) -> 1.025 | AA10: 0 | AC10: 0 | AD10: 0 | AE10: 0 | AF10: 0
A11: =+VLOOKUP(B11,studies!$A$2:$C$102,3) -> Downing et al. (1996) | B11: 19 | C11: 1996 | D11: 0 | E11: 1990 | F11: 1995 | H11: =+IF(VLOOKUP($A11,'Dataset2 ad'!$D$3:$L$855,4,FALSE)="","",VLOOKUP($A11,'Dataset2 ad'!$D$3:$L$855,4,FALSE)) -> 110.47179 | I11: 0 | J11: 1 | K11: 0 | M11: =+IF(VLOOKUP($A11,'Dataset2 ad'!$D$3:$L$855,8,FALSE)="","",VLOOKUP($A11,'Dataset2 ad'!$D$3:$L$855,8,FALSE)) -> 61.493937 | N11: =+IF(VLOOKUP($A11,'Dataset2 ad'!$D$3:$L$855,9,FALSE)="","",VLOOKUP($A11,'Dataset2 ad'!$D$3:$L$855,9,FALSE)) -> 68.573883 | O11: 1 | P11: 0 | Q11: 1 | R11: 1 | S11: 0 | T11: 0 | U11: 0 | V11: 0 | W11: -2 | AA11: 0 | AC11: 0 | AD11: 0 | AE11: 0 | AF11: 0
A12: =+VLOOKUP(B12,studies!$A$2:$C$102,3) -> Hope & Maul (1996) | B12: 21 | C12: 1996 | D12: 1 | E12: 1990 | F12: 1990 | H12: =+IF(VLOOKUP($A12,'Dataset2 ad'!$D$3:$L$855,4,FALSE)="","",VLOOKUP($A12,'Dataset2 ad'!$D$3:$L$855,4,FALSE)) -> 50.245712 | I12: 1 | J12: 0 | K12: 0 | M12: =+IF(VLOOKUP($A12,'Dataset2 ad'!$D$3:$L$855,8,FALSE)="","",VLOOKUP($A12,'Dataset2 ad'!$D$3:$L$855,8,FALSE)) -> 15.564452 | N12: =+IF(VLOOKUP($A12,'Dataset2 ad'!$D$3:$L$855,9,FALSE)="","",VLOOKUP($A12,'Dataset2 ad'!$D$3:$L$855,9,FALSE)) -> 25.17779 | O12: 1 | P12: 1 | Q12: 0 | R12: 0 | S12: 0 | T12: 0 | U12: 1 | V12: 4 | W12: 2 | AA12: 0 | AC12: 1 | AD12: 0 | AE12: 0 | AF12: 0
A13: =+VLOOKUP(B13,studies!$A$2:$C$102,3) -> Plambeck & Hope (1996) | B13: 23 | C13: 1996 | D13: 1 | E13: 1990 | F13: 1990 | H13: =+IF(VLOOKUP($A13,'Dataset2 ad'!$D$3:$L$855,4,FALSE)="","",VLOOKUP($A13,'Dataset2 ad'!$D$3:$L$855,4,FALSE)) -> 52.040202 | I13: 1 | J13: 0 | K13: 0 | M13: =+IF(VLOOKUP($A13,'Dataset2 ad'!$D$3:$L$855,8,FALSE)="","",VLOOKUP($A13,'Dataset2 ad'!$D$3:$L$855,8,FALSE)) -> 19.776009 | N13: =+IF(VLOOKUP($A13,'Dataset2 ad'!$D$3:$L$855,9,FALSE)="","",VLOOKUP($A13,'Dataset2 ad'!$D$3:$L$855,9,FALSE)) -> 526.6278 | O13: 1 | P13: 1 | Q13: 0 | R13: 1 | S13: 0 | T13: 0 | U13: 1 | V13: =+AVERAGE(Dataset0!V151:V158) -> 4.5 | W13: =+AVERAGE(Dataset0!W151:W158) -> 2.5 | AA13: 0 | AC13: 1 | AD13: 0 | AE13: 0 | AF13: 0
A14: =+VLOOKUP(B14,studies!$A$2:$C$102,3) -> Nordhaus & Popp (1997) | B14: 25 | C14: 1997 | D14: 1 | E14: 1990 | F14: 2000 | H14: =+IF(VLOOKUP($A14,'Dataset2 ad'!$D$3:$L$855,4,FALSE)="","",VLOOKUP($A14,'Dataset2 ad'!$D$3:$L$855,4,FALSE)) -> 21.879918 | I14: 1 | J14: 0 | K14: 0 | M14: =+IF(VLOOKUP($A14,'Dataset2 ad'!$D$3:$L$855,8,FALSE)="","",VLOOKUP($A14,'Dataset2 ad'!$D$3:$L$855,8,FALSE)) -> 10.572391 | N14: =+IF(VLOOKUP($A14,'Dataset2 ad'!$D$3:$L$855,9,FALSE)="","",VLOOKUP($A14,'Dataset2 ad'!$D$3:$L$855,9,FALSE)) -> 11.732779 | O14: 0 | P14: 1 | Q14: 0 | R14: 1 | S14: 0 | T14: 1 | U14: 0 | V14: 5 | W14: 3 | X14: 1 | Y14: 2 | Z14: =1/X14 -> 1 | AA14: 0 | AC14: 0 | AD14: 1 | AE14: 0 | AF14: 1
A15: =+VLOOKUP(B15,studies!$A$2:$C$102,3) -> Eyre et al. (1999) | B15: 26 | C15: 1999 | D15: 0 | E15: 1995 | F15: 1995 | H15: =+IF(VLOOKUP($A15,'Dataset2 ad'!$D$3:$L$855,4,FALSE)="","",VLOOKUP($A15,'Dataset2 ad'!$D$3:$L$855,4,FALSE)) -> 308.96675 | I15: 0 | J15: 1 | K15: 0 | M15: =+IF(VLOOKUP($A15,'Dataset2 ad'!$D$3:$L$855,8,FALSE)="","",VLOOKUP($A15,'Dataset2 ad'!$D$3:$L$855,8,FALSE)) -> 62.515513 | N15: =+IF(VLOOKUP($A15,'Dataset2 ad'!$D$3:$L$855,9,FALSE)="","",VLOOKUP($A15,'Dataset2 ad'!$D$3:$L$855,9,FALSE)) -> 69.38683 | O15: 0 | P15: 1 | Q15: 1 | R15: 1 | S15: 1 | T15: 0 | U15: 0 | V15: =+AVERAGE(Dataset0!V162:V165) -> 2 | W15: =+AVERAGE(Dataset0!W162:W165) -> 0 | AA15: 1 | AC15: 0 | AD15: 0 | AE15: 0 | AF15: 0
A16: =+VLOOKUP(B16,studies!$A$2:$C$102,3) -> Tol (1999) | B16: 28 | C16: 1999 | D16: 1 | E16: 1995 | F16: 2000 | H16: =+IF(VLOOKUP($A16,'Dataset2 ad'!$D$3:$L$855,4,FALSE)="","",VLOOKUP($A16,'Dataset2 ad'!$D$3:$L$855,4,FALSE)) -> 143.8679 | I16: 0 | J16: 0 | K16: 1 | M16: =+IF(VLOOKUP($A16,'Dataset2 ad'!$D$3:$L$855,8,FALSE)="","",VLOOKUP($A16,'Dataset2 ad'!$D$3:$L$855,8,FALSE)) -> 66.46637 | N16: =+IF(VLOOKUP($A16,'Dataset2 ad'!$D$3:$L$855,9,FALSE)="","",VLOOKUP($A16,'Dataset2 ad'!$D$3:$L$855,9,FALSE)) -> 336.49322 | O16: 1 | P16: 1 | Q16: 1 | R16: 1 | S16: 1 | T16: 0 | U16: 0 | V16: =+AVERAGE(Dataset0!V167:V196) -> 3.8 | W16: =+AVERAGE(Dataset0!W167:W196) -> 1.8 | AA16: 1 | AC16: 0 | AD16: 0 | AE16: 1 | AF16: 0
A17: =+VLOOKUP(B17,studies!$A$2:$C$102,3) -> Tol & Downing (2001) | B17: 30 | C17: 2001 | D17: 0 | E17: 1995 | F17: 1995 | H17: =+IF(VLOOKUP($A17,'Dataset2 ad'!$D$3:$L$855,4,FALSE)="","",VLOOKUP($A17,'Dataset2 ad'!$D$3:$L$855,4,FALSE)) -> 39.743159 | I17: 0 | J17: 1 | K17: 0 | M17: =+IF(VLOOKUP($A17,'Dataset2 ad'!$D$3:$L$855,8,FALSE)="","",VLOOKUP($A17,'Dataset2 ad'!$D$3:$L$855,8,FALSE)) -> 15.460464 | N17: =+IF(VLOOKUP($A17,'Dataset2 ad'!$D$3:$L$855,9,FALSE)="","",VLOOKUP($A17,'Dataset2 ad'!$D$3:$L$855,9,FALSE)) -> 37.448678 | O17: 0 | P17: 1 | Q17: 1 | R17: 1 | S17: 1 | T17: 0 | U17: 0 | V17: 3 | W17: 1 | AA17: 1 | AC17: 0 | AD17: 0 | AE17: 1 | AF17: 0
A18: =+VLOOKUP(B18,studies!$A$2:$C$102,3) -> Newell & Pizer (2003) | B18: 32 | C18: 2003 | D18: 1 | E18: 1989 | F18: 2000 | H18: =+IF(VLOOKUP($A18,'Dataset2 ad'!$D$3:$L$855,4,FALSE)="","",VLOOKUP($A18,'Dataset2 ad'!$D$3:$L$855,4,FALSE)) -> 18.155201 | I18: 0 | J18: 1 | K18: 0 | M18: =+IF(VLOOKUP($A18,'Dataset2 ad'!$D$3:$L$855,8,FALSE)="","",VLOOKUP($A18,'Dataset2 ad'!$D$3:$L$855,8,FALSE)) -> 6.984081 | N18: =+IF(VLOOKUP($A18,'Dataset2 ad'!$D$3:$L$855,9,FALSE)="","",VLOOKUP($A18,'Dataset2 ad'!$D$3:$L$855,9,FALSE)) -> 32.834842 | O18: 0 | P18: 1 | Q18: 0 | R18: 1 | S18: 0 | T18: 0 | U18: 0 | V18: =+AVERAGE(Dataset0!V203:V211) -> 4.3333333 | W18: =+AVERAGE(Dataset0!W203:W211) -> 2.3333333 | AA18: 0 | AC18: 0 | AD18: 0 | AE18: 0 | AF18: 0
A19: =+VLOOKUP(B19,studies!$A$2:$C$102,3) -> Cline (2004) | B19: 35 | C19: 2004 | D19: 0 | E19: 1990 | F19: 1995 | H19: =+IF(VLOOKUP($A19,'Dataset2 ad'!$D$3:$L$855,4,FALSE)="","",VLOOKUP($A19,'Dataset2 ad'!$D$3:$L$855,4,FALSE)) -> 110.52577 | I19: 0 | J19: 1 | K19: 0 | M19: =+IF(VLOOKUP($A19,'Dataset2 ad'!$D$3:$L$855,8,FALSE)="","",VLOOKUP($A19,'Dataset2 ad'!$D$3:$L$855,8,FALSE)) -> 35.338172 | N19: =+IF(VLOOKUP($A19,'Dataset2 ad'!$D$3:$L$855,9,FALSE)="","",VLOOKUP($A19,'Dataset2 ad'!$D$3:$L$855,9,FALSE)) -> 340.79908 | O19: 0 | P19: 1 | Q19: 0 | R19: 1 | S19: 0 | T19: 1 | U19: 0 | W19: =+AVERAGE(Dataset0!W214:W222) -> 1.3333333 | AA19: 0 | AC19: 0 | AD19: 0 | AE19: 0 | AF19: 0
A20: =+VLOOKUP(B20,studies!$A$2:$C$102,3) -> Hohmeyer (2004) | B20: 36 | C20: 2004 | D20: 0 | E20: 1990 | F20: 1990 | H20: =+IF(VLOOKUP($A20,'Dataset2 ad'!$D$3:$L$855,4,FALSE)="","",VLOOKUP($A20,'Dataset2 ad'!$D$3:$L$855,4,FALSE)) -> 1116.1726 | I20: 0 | J20: 1 | K20: 0 | M20: =+IF(VLOOKUP($A20,'Dataset2 ad'!$D$3:$L$855,8,FALSE)="","",VLOOKUP($A20,'Dataset2 ad'!$D$3:$L$855,8,FALSE)) -> 1016.3488 | N20: =+IF(VLOOKUP($A20,'Dataset2 ad'!$D$3:$L$855,9,FALSE)="","",VLOOKUP($A20,'Dataset2 ad'!$D$3:$L$855,9,FALSE)) -> 1147.3348 | O20: 0 | P20: 1 | Q20: 0 | R20: 1 | S20: 0 | T20: 0 | U20: 0 | W20: =+AVERAGE(Dataset0!W223:W224) -> 0.5 | AA20: 1 | AC20: 0 | AD20: 0 | AE20: 0 | AF20: 0
A21: =+VLOOKUP(B21,studies!$A$2:$C$102,3) -> Link & Tol (2004) | B21: 37 | C21: 2004 | D21: 1 | E21: 1995 | F21: 2000 | H21: =+IF(VLOOKUP($A21,'Dataset2 ad'!$D$3:$L$855,4,FALSE)="","",VLOOKUP($A21,'Dataset2 ad'!$D$3:$L$855,4,FALSE)) -> 136.73115 | I21: 0 | J21: 1 | K21: 0 | M21: =+IF(VLOOKUP($A21,'Dataset2 ad'!$D$3:$L$855,8,FALSE)="","",VLOOKUP($A21,'Dataset2 ad'!$D$3:$L$855,8,FALSE)) -> 63.917529 | N21: =+IF(VLOOKUP($A21,'Dataset2 ad'!$D$3:$L$855,9,FALSE)="","",VLOOKUP($A21,'Dataset2 ad'!$D$3:$L$855,9,FALSE)) -> 125.34979 | O21: 1 | P21: 1 | Q21: 1 | R21: 1 | S21: 1 | T21: 0 | U21: 0 | W21: =+AVERAGE(Dataset0!W225:W236) -> 1.3333333 | AA21: 1 | AC21: 0 | AD21: 0 | AE21: 1 | AF21: 0
A22: =+VLOOKUP(B22,studies!$A$2:$C$102,3) -> Manne (2004) | B22: 38 | C22: 2004 | D22: 0 | E22: 2000 | F22: 2000 | H22: =+IF(VLOOKUP($A22,'Dataset2 ad'!$D$3:$L$855,4,FALSE)="","",VLOOKUP($A22,'Dataset2 ad'!$D$3:$L$855,4,FALSE)) -> 312.7999 | I22: 0 | J22: 1 | K22: 0 | M22: =+IF(VLOOKUP($A22,'Dataset2 ad'!$D$3:$L$855,8,FALSE)="","",VLOOKUP($A22,'Dataset2 ad'!$D$3:$L$855,8,FALSE)) -> 291.88592 | N22: =+IF(VLOOKUP($A22,'Dataset2 ad'!$D$3:$L$855,9,FALSE)="","",VLOOKUP($A22,'Dataset2 ad'!$D$3:$L$855,9,FALSE)) -> 329.65656 | O22: 0 | P22: 1 | Q22: 0 | R22: 1 | S22: 0 | T22: 0 | U22: 0 | W22: =+AVERAGE(Dataset0!W237:W238) -> 1.5 | AA22: 0 | AC22: 0 | AD22: 0 | AE22: 0 | AF22: 0
A23: =+VLOOKUP(B23,studies!$A$2:$C$102,3) -> Hope (2005b) | B23: 42 | C23: 2005 | D23: 0 | E23: 2000 | F23: 2000 | H23: =+IF(VLOOKUP($A23,'Dataset2 ad'!$D$3:$L$855,4,FALSE)="","",VLOOKUP($A23,'Dataset2 ad'!$D$3:$L$855,4,FALSE)) -> 72.184592 | I23: 1 | J23: 0 | K23: 0 | M23: =+IF(VLOOKUP($A23,'Dataset2 ad'!$D$3:$L$855,8,FALSE)="","",VLOOKUP($A23,'Dataset2 ad'!$D$3:$L$855,8,FALSE)) -> 4.8593652 | N23: =+IF(VLOOKUP($A23,'Dataset2 ad'!$D$3:$L$855,9,FALSE)="","",VLOOKUP($A23,'Dataset2 ad'!$D$3:$L$855,9,FALSE)) -> 9.4629744 | O23: 0 | P23: 1 | Q23: 0 | R23: 1 | S23: 0 | T23: 0 | U23: 1 | W23: 3 | AA23: 1 | AC23: 1 | AD23: 0 | AE23: 0 | AF23: 0
A24: =+VLOOKUP(B24,studies!$A$2:$C$102,3) -> Hope (2005a) | B24: 43 | C24: 2005 | D24: 1 | E24: 2000 | F24: 2000 | H24: =+IF(VLOOKUP($A24,'Dataset2 ad'!$D$3:$L$855,4,FALSE)="","",VLOOKUP($A24,'Dataset2 ad'!$D$3:$L$855,4,FALSE)) | I24: 1 | J24: 0 | K24: 0 | M24: =+IF(VLOOKUP($A24,'Dataset2 ad'!$D$3:$L$855,8,FALSE)="","",VLOOKUP($A24,'Dataset2 ad'!$D$3:$L$855,8,FALSE)) | N24: =+IF(VLOOKUP($A24,'Dataset2 ad'!$D$3:$L$855,9,FALSE)="","",VLOOKUP($A24,'Dataset2 ad'!$D$3:$L$855,9,FALSE)) | O24: 0 | P24: 1 | Q24: 0 | R24: 1 | S24: 0 | T24: 0 | U24: 1 | W24: 3 | AA24: 0 | AC24: 1 | AD24: 0 | AE24: 0 | AF24: 0
A25: =+VLOOKUP(B25,studies!$A$2:$C$102,3) -> Tol (2005) | B25: 44 | C25: 2005 | D25: 1 | E25: 1995 | F25: 2005 | H25: =+IF(VLOOKUP($A25,'Dataset2 ad'!$D$3:$L$855,4,FALSE)="","",VLOOKUP($A25,'Dataset2 ad'!$D$3:$L$855,4,FALSE)) -> 10.107828 | I25: 0 | J25: 1 | K25: 0 | M25: =+IF(VLOOKUP($A25,'Dataset2 ad'!$D$3:$L$855,8,FALSE)="","",VLOOKUP($A25,'Dataset2 ad'!$D$3:$L$855,8,FALSE)) -> 10.190142 | N25: =+IF(VLOOKUP($A25,'Dataset2 ad'!$D$3:$L$855,9,FALSE)="","",VLOOKUP($A25,'Dataset2 ad'!$D$3:$L$855,9,FALSE)) -> 13.636443 | O25: 1 | P25: 1 | Q25: 1 | R25: 1 | S25: 1 | T25: 0 | U25: 0 | V25: =+AVERAGE(Dataset0!V248:V253) -> 3.3333333 | W25: =+AVERAGE(Dataset0!W248:W253) -> 1.3333333 | AA25: 0 | AC25: 0 | AD25: 0 | AE25: 1 | AF25: 0
A26: =+VLOOKUP(B26,studies!$A$2:$C$102,3) -> Guo et al. (2006) | B26: 45 | C26: 2006 | D26: 1 | E26: 1995 | F26: 2000 | H26: =+IF(VLOOKUP($A26,'Dataset2 ad'!$D$3:$L$855,4,FALSE)="","",VLOOKUP($A26,'Dataset2 ad'!$D$3:$L$855,4,FALSE)) -> 37.382998 | I26: 0 | J26: 1 | K26: 0 | M26: =+IF(VLOOKUP($A26,'Dataset2 ad'!$D$3:$L$855,8,FALSE)="","",VLOOKUP($A26,'Dataset2 ad'!$D$3:$L$855,8,FALSE)) -> 21.558222 | N26: =+IF(VLOOKUP($A26,'Dataset2 ad'!$D$3:$L$855,9,FALSE)="","",VLOOKUP($A26,'Dataset2 ad'!$D$3:$L$855,9,FALSE)) -> 110.68095 | O26: 0 | P26: 1 | Q26: 1 | R26: 1 | S26: 1 | T26: 0 | U26: 0 | W26: =+AVERAGE(Dataset0!W254:W269) -> 1.3333333 | AA26: 0 | AC26: 0 | AD26: 0 | AE26: 1 | AF26: 0
A27: =+VLOOKUP(B27,studies!$A$2:$C$102,3) -> Wahba & Hope (2006) | B27: 48 | C27: 2006 | D27: 1 | E27: 2000 | F27: 2000 | H27: =+IF(VLOOKUP($A27,'Dataset2 ad'!$D$3:$L$855,4,FALSE)="","",VLOOKUP($A27,'Dataset2 ad'!$D$3:$L$855,4,FALSE)) -> 59.151263 | I27: 1 | J27: 0 | K27: 0 | M27: =+IF(VLOOKUP($A27,'Dataset2 ad'!$D$3:$L$855,8,FALSE)="","",VLOOKUP($A27,'Dataset2 ad'!$D$3:$L$855,8,FALSE)) -> 15.090944 | N27: =+IF(VLOOKUP($A27,'Dataset2 ad'!$D$3:$L$855,9,FALSE)="","",VLOOKUP($A27,'Dataset2 ad'!$D$3:$L$855,9,FALSE)) -> 98.824144 | O27: 0 | P27: 1 | Q27: 0 | R27: 1 | S27: 0 | T27: 0 | U27: 1 | W27: =+AVERAGE(Dataset0!W272:W279) -> 2.25 | X27: 1 | Z27: =1/X27 -> 1 | AA27: 0 | AC27: 1 | AD27: 0 | AE27: 0 | AF27: 0
A28: =+VLOOKUP(B28,studies!$A$2:$C$102,3) -> Stern & Taylor (2007) | B28: 49 | C28: 2007 | D28: 1 | E28: 2000 | F28: 2000 | H28: =+IF(VLOOKUP($A28,'Dataset2 ad'!$D$3:$L$855,4,FALSE)="","",VLOOKUP($A28,'Dataset2 ad'!$D$3:$L$855,4,FALSE)) -> 202.1837 | I28: 0 | J28: 1 | K28: 0 | M28: =+IF(VLOOKUP($A28,'Dataset2 ad'!$D$3:$L$855,8,FALSE)="","",VLOOKUP($A28,'Dataset2 ad'!$D$3:$L$855,8,FALSE)) -> 42.424148 | N28: =+IF(VLOOKUP($A28,'Dataset2 ad'!$D$3:$L$855,9,FALSE)="","",VLOOKUP($A28,'Dataset2 ad'!$D$3:$L$855,9,FALSE)) -> 44.828529 | O28: 0 | P28: 1 | Q28: 0 | R28: 1 | S28: 0 | T28: 0 | U28: 1 | W28: 0 | AA28: 0 | AC28: 0 | AD28: 0 | AE28: 0 | AF28: 1
A29: =+VLOOKUP(B29,studies!$A$2:$C$102,3) -> Hope (2008b) | B29: 50 | C29: 2008 | D29: 1 | E29: 2000 | F29: 2000 | H29: =+IF(VLOOKUP($A29,'Dataset2 ad'!$D$3:$L$855,4,FALSE)="","",VLOOKUP($A29,'Dataset2 ad'!$D$3:$L$855,4,FALSE)) -> 26.066658 | I29: 1 | J29: 0 | K29: 0 | M29: =+IF(VLOOKUP($A29,'Dataset2 ad'!$D$3:$L$855,8,FALSE)="","",VLOOKUP($A29,'Dataset2 ad'!$D$3:$L$855,8,FALSE)) -> 0.81841941 | N29: =+IF(VLOOKUP($A29,'Dataset2 ad'!$D$3:$L$855,9,FALSE)="","",VLOOKUP($A29,'Dataset2 ad'!$D$3:$L$855,9,FALSE)) -> 0.81841941 | O29: 0 | P29: 1 | Q29: 0 | R29: 1 | S29: 0 | T29: 0 | U29: 1 | W29: 2 | X29: 1 | Z29: =1/X29 -> 1 | AA29: 0 | AB29: =+AVERAGE(Dataset0!AB282:AB286) -> 3.44 | AC29: 1 | AD29: 0 | AE29: 0 | AF29: 0
A30: =+VLOOKUP(B30,studies!$A$2:$C$102,3) -> Hope (2008a) | B30: 51 | C30: 2008 | D30: 1 | E30: 2000 | F30: 2000 | H30: =+IF(VLOOKUP($A30,'Dataset2 ad'!$D$3:$L$855,4,FALSE)="","",VLOOKUP($A30,'Dataset2 ad'!$D$3:$L$855,4,FALSE)) -> 134.34355 | I30: 1 | J30: 0 | K30: 0 | M30: =+IF(VLOOKUP($A30,'Dataset2 ad'!$D$3:$L$855,8,FALSE)="","",VLOOKUP($A30,'Dataset2 ad'!$D$3:$L$855,8,FALSE)) -> 48.030989 | N30: =+IF(VLOOKUP($A30,'Dataset2 ad'!$D$3:$L$855,9,FALSE)="","",VLOOKUP($A30,'Dataset2 ad'!$D$3:$L$855,9,FALSE)) -> 484.40199 | O30: 0 | P30: 1 | Q30: 0 | R30: 1 | S30: 0 | T30: 0 | U30: 1 | W30: =+AVERAGE(Dataset0!W287:W296) -> 1.5 | AA30: 0 | AC30: 1 | AD30: 0 | AE30: 0 | AF30: 0
A31: =+VLOOKUP(B31,studies!$A$2:$C$102,3) -> Nordhaus (2008) | B31: 52 | C31: 2008 | D31: 0 | E31: 2005 | F31: 2005 | H31: =+IF(VLOOKUP($A31,'Dataset2 ad'!$D$3:$L$855,4,FALSE)="","",VLOOKUP($A31,'Dataset2 ad'!$D$3:$L$855,4,FALSE)) -> 44.702532 | I31: 0 | J31: 1 | K31: 0 | M31: =+IF(VLOOKUP($A31,'Dataset2 ad'!$D$3:$L$855,8,FALSE)="","",VLOOKUP($A31,'Dataset2 ad'!$D$3:$L$855,8,FALSE)) -> 1.1596815 | N31: =+IF(VLOOKUP($A31,'Dataset2 ad'!$D$3:$L$855,9,FALSE)="","",VLOOKUP($A31,'Dataset2 ad'!$D$3:$L$855,9,FALSE)) -> 129.56933 | O31: 1 | P31: 1 | Q31: 0 | R31: 1 | S31: 0 | T31: 1 | U31: 0 | V31: =+AVERAGE(Dataset0!V297:V300) -> 2.75 | W31: =+AVERAGE(Dataset0!W297:W300) -> 0.8 | X31: =+AVERAGE(Dataset0!X297:X300) -> 1.5 | Y31: =+AVERAGE(Dataset0!Y297:Y300) -> 1.3 | Z31: =+AVERAGE(Dataset0!Z297:Z300) -> 0.75 | AA31: 0 | AB31: 3 | AC31: 0 | AD31: 1 | AE31: 0 | AF31: 0
A32: =+VLOOKUP(B32,studies!$A$2:$C$102,3) -> Anthoff et al. (2009a) | B32: 53 | C32: 2009 | D32: 1 | E32: 1995 | F32: 2010 | H32: =+IF(VLOOKUP($A32,'Dataset2 ad'!$D$3:$L$855,4,FALSE)="","",VLOOKUP($A32,'Dataset2 ad'!$D$3:$L$855,4,FALSE)) -> 20.34598 | I32: 0 | J32: 1 | K32: 0 | M32: =+IF(VLOOKUP($A32,'Dataset2 ad'!$D$3:$L$855,8,FALSE)="","",VLOOKUP($A32,'Dataset2 ad'!$D$3:$L$855,8,FALSE)) -> 15.094416 | N32: =+IF(VLOOKUP($A32,'Dataset2 ad'!$D$3:$L$855,9,FALSE)="","",VLOOKUP($A32,'Dataset2 ad'!$D$3:$L$855,9,FALSE)) -> 65.295688 | O32: 0 | P32: 1 | Q32: 1 | R32: 1 | S32: 1 | T32: 0 | U32: 0 | W32: =+AVERAGE(Dataset0!W301:W333) -> 1.3333333 | AA32: 1 | AC32: 0 | AD32: 0 | AE32: 1 | AF32: 0
A33: =+VLOOKUP(B33,studies!$A$2:$C$102,3) -> Anthoff et al. (2009b) | B33: 54 | C33: 2009 | D33: 1 | E33: 1995 | F33: 2010 | H33: =+'Dataset2 ad'!G379 -> 7.1794625 | I33: 0 | J33: 1 | K33: 0 | M33: =+'Dataset2 ad'!K379 -> 5.0673504 | N33: =+'Dataset2 ad'!L379 -> 29.556211 | O33: 0 | P33: 1 | Q33: 1 | R33: 1 | S33: 1 | T33: 0 | U33: 0 | W33: NA | AA33: =+AVERAGE(Dataset0!AA334:AA337) -> 0.5 | AC33: 0 | AD33: 0 | AE33: 1 | AF33: 0
A34: =+VLOOKUP(B34,studies!$A$2:$C$102,3) -> Anthoff et al. (2009c) | B34: 55 | C34: 2009 | D34: 1 | E34: 1995 | F34: 2010 | H34: =+'Dataset2 ad'!G383 -> 99.561885 | I34: 1 | J34: 0 | K34: 0 | M34: =+'Dataset2 ad'!K383 -> 51.252095 | N34: =+'Dataset2 ad'!L383 -> 134.74787 | O34: 0 | P34: 1 | Q34: 1 | R34: 1 | S34: 1 | T34: 0 | U34: 0 | W34: NA | AA34: 1 | AC34: 0 | AD34: 0 | AE34: 1 | AF34: 0
A35: =+VLOOKUP(B35,studies!$A$2:$C$102,3) -> EPA & NHTSA (2009) | B35: 56 | C35: 2009 | D35: 0 | E35: 2007 | F35: 2015 | H35: =+IF(VLOOKUP($A35,'Dataset2 ad'!$D$3:$L$855,4,FALSE)="","",VLOOKUP($A35,'Dataset2 ad'!$D$3:$L$855,4,FALSE)) -> 353.47901 | I35: 0 | J35: 1 | K35: 0 | M35: =+IF(VLOOKUP($A35,'Dataset2 ad'!$D$3:$L$855,8,FALSE)="","",VLOOKUP($A35,'Dataset2 ad'!$D$3:$L$855,8,FALSE)) -> 164.21362 | N35: =+IF(VLOOKUP($A35,'Dataset2 ad'!$D$3:$L$855,9,FALSE)="","",VLOOKUP($A35,'Dataset2 ad'!$D$3:$L$855,9,FALSE)) -> 297.21092 | O35: 0 | P35: 0 | Q35: 0 | R35: 0 | S35: 1 | T35: 1 | U35: 1 | V35: =+AVERAGE(Dataset0!V350:V354) -> 4 | W35: NA | AA35: 0 | AC35: 0 | AD35: 0 | AE35: 0 | AF35: 0
A36: =+VLOOKUP(B36,studies!$A$2:$C$102,3) -> Narita et al. (2009) | B36: 57 | C36: 2009 | D36: 1 | E36: 2005 | F36: 2010 | H36: =+IF(VLOOKUP($A36,'Dataset2 ad'!$D$3:$L$855,4,FALSE)="","",VLOOKUP($A36,'Dataset2 ad'!$D$3:$L$855,4,FALSE)) -> 11.829473 | I36: 0 | J36: 1 | K36: 0 | M36: =+IF(VLOOKUP($A36,'Dataset2 ad'!$D$3:$L$855,8,FALSE)="","",VLOOKUP($A36,'Dataset2 ad'!$D$3:$L$855,8,FALSE)) -> 7.2066801 | N36: =+IF(VLOOKUP($A36,'Dataset2 ad'!$D$3:$L$855,9,FALSE)="","",VLOOKUP($A36,'Dataset2 ad'!$D$3:$L$855,9,FALSE)) -> 59.906276 | O36: 0 | P36: 1 | Q36: 1 | R36: 1 | S36: 1 | T36: 0 | U36: 0 | W36: =+AVERAGE(Dataset0!W355:W357) -> 1.3333333 | AA36: 0 | AC36: 0 | AD36: 0 | AE36: 1 | AF36: 0
A37: =+VLOOKUP(B37,studies!$A$2:$C$102,3) -> Anthoff & Tol (2010) | B37: 58 | C37: 2010 | D37: 1 | E37: 1995 | F37: 2010 | H37: =+IF(VLOOKUP($A37,'Dataset2 ad'!$D$3:$L$855,4,FALSE)="","",VLOOKUP($A37,'Dataset2 ad'!$D$3:$L$855,4,FALSE)) -> 25.949463 | I37: 0 | J37: 1 | K37: 0 | M37: =+IF(VLOOKUP($A37,'Dataset2 ad'!$D$3:$L$855,8,FALSE)="","",VLOOKUP($A37,'Dataset2 ad'!$D$3:$L$855,8,FALSE)) -> 12.358872 | N37: =+IF(VLOOKUP($A37,'Dataset2 ad'!$D$3:$L$855,9,FALSE)="","",VLOOKUP($A37,'Dataset2 ad'!$D$3:$L$855,9,FALSE)) -> 90.266566 | O37: 0 | P37: 1 | Q37: 1 | R37: 1 | S37: 1 | T37: 0 | U37: 0 | W37: =+AVERAGE(Dataset0!W358:W373) -> 1.125 | AA37: =+AVERAGE(Dataset0!AA358:AA373) -> 0.5 | AC37: 0 | AD37: 0 | AE37: 1 | AF37: 0
A38: =+VLOOKUP(B38,studies!$A$2:$C$102,3) -> Kemfert & Schill (2010) | B38: 59 | C38: 2010 | D38: 0 | E38: 2000 | F38: 2010 | H38: =+IF(VLOOKUP($A38,'Dataset2 ad'!$D$3:$L$855,4,FALSE)="","",VLOOKUP($A38,'Dataset2 ad'!$D$3:$L$855,4,FALSE)) -> 102.82427 | I38: 0 | J38: 1 | K38: 0 | M38: =+IF(VLOOKUP($A38,'Dataset2 ad'!$D$3:$L$855,8,FALSE)="","",VLOOKUP($A38,'Dataset2 ad'!$D$3:$L$855,8,FALSE)) -> 14.910071 | N38: =+IF(VLOOKUP($A38,'Dataset2 ad'!$D$3:$L$855,9,FALSE)="","",VLOOKUP($A38,'Dataset2 ad'!$D$3:$L$855,9,FALSE)) -> 67.09532 | O38: 0 | P38: 1 | Q38: 0 | R38: 1 | S38: 0 | T38: 0 | U38: 0 | W38: NA | AA38: 0 | AC38: 0 | AD38: 0 | AE38: 0 | AF38: 0
A39: =+VLOOKUP(B39,studies!$A$2:$C$102,3) -> Narita et al. (2010) | B39: 60 | C39: 2010 | D39: 1 | E39: 2005 | F39: 2010 | H39: =+IF(VLOOKUP($A39,'Dataset2 ad'!$D$3:$L$855,4,FALSE)="","",VLOOKUP($A39,'Dataset2 ad'!$D$3:$L$855,4,FALSE)) -> 28.643201 | I39: 0 | J39: 1 | K39: 0 | M39: =+IF(VLOOKUP($A39,'Dataset2 ad'!$D$3:$L$855,8,FALSE)="","",VLOOKUP($A39,'Dataset2 ad'!$D$3:$L$855,8,FALSE)) -> 12.548946 | N39: =+IF(VLOOKUP($A39,'Dataset2 ad'!$D$3:$L$855,9,FALSE)="","",VLOOKUP($A39,'Dataset2 ad'!$D$3:$L$855,9,FALSE)) -> 72.915349 | O39: 0 | P39: 1 | Q39: 1 | R39: 1 | S39: 1 | T39: 0 | U39: 0 | W39: =+AVERAGE(Dataset0!W377:W379) -> 0.5 | AA39: 0 | AC39: 0 | AD39: 0 | AE39: 1 | AF39: 0
A40: =+VLOOKUP(B40,studies!$A$2:$C$102,3) -> Anthoff et al. (2011) | B40: 64 | C40: 2011 | D40: 0 | E40: 1995 | F40: 2015 | H40: =+IF(VLOOKUP($A40,'Dataset2 ad'!$D$3:$L$855,4,FALSE)="","",VLOOKUP($A40,'Dataset2 ad'!$D$3:$L$855,4,FALSE)) -> 42.495165 | I40: 0 | J40: 1 | K40: 0 | M40: =+IF(VLOOKUP($A40,'Dataset2 ad'!$D$3:$L$855,8,FALSE)="","",VLOOKUP($A40,'Dataset2 ad'!$D$3:$L$855,8,FALSE)) -> 21.141659 | N40: =+IF(VLOOKUP($A40,'Dataset2 ad'!$D$3:$L$855,9,FALSE)="","",VLOOKUP($A40,'Dataset2 ad'!$D$3:$L$855,9,FALSE)) -> 1032.3028 | O40: 0 | P40: 1 | Q40: 1 | R40: 1 | S40: 1 | T40: 0 | U40: 0 | W40: =+AVERAGE(Dataset0!W383:W404) -> 1.25 | AA40: 0 | AC40: 0 | AD40: 0 | AE40: 1 | AF40: 0
A41: =+VLOOKUP(B41,studies!$A$2:$C$102,3) -> Ceronsky et al. (2011) | B41: 65 | C41: 2011 | D41: 0 | E41: 2010 | F41: 2010 | H41: =+IF(VLOOKUP($A41,'Dataset2 ad'!$D$3:$L$855,4,FALSE)="","",VLOOKUP($A41,'Dataset2 ad'!$D$3:$L$855,4,FALSE)) -> 155.01986 | I41: =+AVERAGE(Dataset0!I405:I452) -> 0.5 | J41: =+AVERAGE(Dataset0!J405:J452) -> 0.5 | K41: 0 | M41: =+IF(VLOOKUP($A41,'Dataset2 ad'!$D$3:$L$855,8,FALSE)="","",VLOOKUP($A41,'Dataset2 ad'!$D$3:$L$855,8,FALSE)) -> 75.910255 | N41: =+IF(VLOOKUP($A41,'Dataset2 ad'!$D$3:$L$855,9,FALSE)="","",VLOOKUP($A41,'Dataset2 ad'!$D$3:$L$855,9,FALSE)) -> 839.26473 | O41: 0 | P41: 1 | Q41: 1 | R41: 1 | S41: 1 | T41: 0 | U41: 0 | W41: =+AVERAGE(Dataset0!W405:W452) -> 1.3333333 | AA41: 0 | AC41: 0 | AD41: 0 | AE41: 1 | AF41: 0
A42: =+VLOOKUP(B42,studies!$A$2:$C$102,3) -> Dietz (2011) | B42: 66 | C42: 2011 | D42: 1 | E42: 2008 | F42: 2000 | H42: =+IF(VLOOKUP($A42,'Dataset2 ad'!$D$3:$L$855,4,FALSE)="","",VLOOKUP($A42,'Dataset2 ad'!$D$3:$L$855,4,FALSE)) -> 2325.2311 | I42: 1 | J42: 0 | K42: 0 | M42: =+IF(VLOOKUP($A42,'Dataset2 ad'!$D$3:$L$855,8,FALSE)="","",VLOOKUP($A42,'Dataset2 ad'!$D$3:$L$855,8,FALSE)) -> 555.73547 | N42: =+IF(VLOOKUP($A42,'Dataset2 ad'!$D$3:$L$855,9,FALSE)="","",VLOOKUP($A42,'Dataset2 ad'!$D$3:$L$855,9,FALSE)) -> 593.59611 | O42: 0 | P42: 1 | Q42: 0 | R42: 1 | S42: 0 | T42: 0 | U42: 1 | W42: =+AVERAGE(Dataset0!W453:W454) -> 2 | X42: =+AVERAGE(Dataset0!X453:X454) -> 0.7 | Z42: =1/X42 -> 1.4285714 | AA42: 0 | AC42: 0 | AD42: 0 | AE42: 0 | AF42: 0
A43: =+VLOOKUP(B43,studies!$A$2:$C$102,3) -> Hope (2011) | B43: 67 | C43: 2011 | D43: 1 | E43: 2005 | F43: 2009 | H43: =+IF(VLOOKUP($A43,'Dataset2 ad'!$D$3:$L$855,4,FALSE)="","",VLOOKUP($A43,'Dataset2 ad'!$D$3:$L$855,4,FALSE)) -> 381.21474 | I43: 1 | J43: 0 | K43: 0 | M43: =+IF(VLOOKUP($A43,'Dataset2 ad'!$D$3:$L$855,8,FALSE)="","",VLOOKUP($A43,'Dataset2 ad'!$D$3:$L$855,8,FALSE)) -> 155.02806 | N43: =+IF(VLOOKUP($A43,'Dataset2 ad'!$D$3:$L$855,9,FALSE)="","",VLOOKUP($A43,'Dataset2 ad'!$D$3:$L$855,9,FALSE)) -> 170.8547 | O43: 0 | P43: 1 | Q43: 0 | R43: 1 | S43: 0 | T43: 0 | U43: 1 | W43: 1 | AA43: 1 | AC43: 1 | AD43: 0 | AE43: 0 | AF43: 0
A44: =+VLOOKUP(B44,studies!$A$2:$C$102,3) -> Pycroft et al. (2011) | B44: 69 | C44: 2011 | D44: 1 | E44: 2005 | F44: 2009 | H44: =+IF(VLOOKUP($A44,'Dataset2 ad'!$D$3:$L$855,4,FALSE)="","",VLOOKUP($A44,'Dataset2 ad'!$D$3:$L$855,4,FALSE)) -> 265.68916 | I44: 0 | J44: 0 | K44: 1 | M44: =+IF(VLOOKUP($A44,'Dataset2 ad'!$D$3:$L$855,8,FALSE)="","",VLOOKUP($A44,'Dataset2 ad'!$D$3:$L$855,8,FALSE)) -> 13.806598 | N44: =+IF(VLOOKUP($A44,'Dataset2 ad'!$D$3:$L$855,9,FALSE)="","",VLOOKUP($A44,'Dataset2 ad'!$D$3:$L$855,9,FALSE)) -> 8.7860171 | O44: 0 | P44: 1 | Q44: 0 | R44: 1 | S44: 0 | T44: 0 | U44: 1 | V44: NA | W44: NA | AA44: 1 | AC44: 1 | AD44: 0 | AE44: 0 | AF44: 0
A45: =+VLOOKUP(B45,studies!$A$2:$C$102,3) -> Waldhoff et al. (2011) | B45: 70 | C45: 2011 | D45: 0 | E45: 1995 | F45: 2015 | H45: =+IF(VLOOKUP($A45,'Dataset2 ad'!$D$3:$L$855,4,FALSE)="","",VLOOKUP($A45,'Dataset2 ad'!$D$3:$L$855,4,FALSE)) -> 41.970534 | I45: 0 | J45: 1 | K45: 0 | M45: =+IF(VLOOKUP($A45,'Dataset2 ad'!$D$3:$L$855,8,FALSE)="","",VLOOKUP($A45,'Dataset2 ad'!$D$3:$L$855,8,FALSE)) -> 17.880304 | N45: =+IF(VLOOKUP($A45,'Dataset2 ad'!$D$3:$L$855,9,FALSE)="","",VLOOKUP($A45,'Dataset2 ad'!$D$3:$L$855,9,FALSE)) -> 73.341366 | O45: 0 | P45: 1 | Q45: 1 | R45: 1 | S45: 1 | T45: 0 | U45: 0 | W45: =+AVERAGE(Dataset0!W469:W481) -> 1.0846154 | AA45: 0 | AC45: 0 | AD45: 0 | AE45: 1 | AF45: 0
A46: =+VLOOKUP(B46,studies!$A$2:$C$102,3) -> Ackerman & Munitz (2012) | B46: 71 | C46: 2012 | D46: 1 | E46: 2005 | F46: 2010 | H46: =+IF(VLOOKUP($A46,'Dataset2 ad'!$D$3:$L$855,4,FALSE)="","",VLOOKUP($A46,'Dataset2 ad'!$D$3:$L$855,4,FALSE)) -> 77.349221 | I46: 1 | J46: 0 | K46: 0 | M46: =+IF(VLOOKUP($A46,'Dataset2 ad'!$D$3:$L$855,8,FALSE)="","",VLOOKUP($A46,'Dataset2 ad'!$D$3:$L$855,8,FALSE)) -> 22.699648 | N46: =+IF(VLOOKUP($A46,'Dataset2 ad'!$D$3:$L$855,9,FALSE)="","",VLOOKUP($A46,'Dataset2 ad'!$D$3:$L$855,9,FALSE)) -> 3.8782217 | O46: 0 | P46: 1 | Q46: 0 | R46: 1 | S46: 1 | T46: 0 | U46: 0 | V46: 0 | W46: 3 | AA46: 0 | AC46: 0 | AD46: 0 | AE46: 0 | AF46: 0
A47: =+VLOOKUP(B47,studies!$A$2:$C$102,3) -> Ackerman & Stanton (2012) | B47: 72 | C47: 2012 | D47: 1 | E47: 2007 | F47: 2010 | H47: =+IF(VLOOKUP($A47,'Dataset2 ad'!$D$3:$L$855,4,FALSE)="","",VLOOKUP($A47,'Dataset2 ad'!$D$3:$L$855,4,FALSE)) -> 480.91871 | I47: 1 | J47: 0 | K47: 0 | M47: =+IF(VLOOKUP($A47,'Dataset2 ad'!$D$3:$L$855,8,FALSE)="","",VLOOKUP($A47,'Dataset2 ad'!$D$3:$L$855,8,FALSE)) -> 153.87014 | N47: =+IF(VLOOKUP($A47,'Dataset2 ad'!$D$3:$L$855,9,FALSE)="","",VLOOKUP($A47,'Dataset2 ad'!$D$3:$L$855,9,FALSE)) -> 747.79511 | O47: 0 | P47: 1 | Q47: 0 | R47: 1 | S47: 0 | T47: 1 | U47: 0 | V47: =+AVERAGE(Dataset0!V485:V492) -> 2.25 | W47: =+AVERAGE(Dataset0!W485:W492) -> 0.25 | AA47: 0 | AC47: 0 | AD47: 0 | AE47: 0 | AF47: 0
A48: =+VLOOKUP(B48,studies!$A$2:$C$102,3) -> Botzen & van den Bergh (2012) | B48: 73 | C48: 2012 | D48: 1 | E48: 2005 | F48: 2015 | H48: =+IF(VLOOKUP($A48,'Dataset2 ad'!$D$3:$L$855,4,FALSE)="","",VLOOKUP($A48,'Dataset2 ad'!$D$3:$L$855,4,FALSE)) -> 47.050076 | I48: 0 | J48: 1 | K48: 0 | M48: =+IF(VLOOKUP($A48,'Dataset2 ad'!$D$3:$L$855,8,FALSE)="","",VLOOKUP($A48,'Dataset2 ad'!$D$3:$L$855,8,FALSE)) -> 6.3876582 | N48: =+IF(VLOOKUP($A48,'Dataset2 ad'!$D$3:$L$855,9,FALSE)="","",VLOOKUP($A48,'Dataset2 ad'!$D$3:$L$855,9,FALSE)) -> 6.4227114 | O48: 0 | P48: 1 | Q48: 0 | R48: 1 | S48: 0 | T48: 1 | U48: 0 | V48: NA | W48: 3 | AA48: 0 | AC48: 0 | AD48: 0 | AE48: 0 | AF48: 1
A49: =+VLOOKUP(B49,studies!$A$2:$C$102,3) -> Cai et al. (2012) | B49: 74 | C49: 2012 | D49: 1 | E49: 2005 | F49: 2015 | H49: =+IF(VLOOKUP($A49,'Dataset2 ad'!$D$3:$L$855,4,FALSE)="","",VLOOKUP($A49,'Dataset2 ad'!$D$3:$L$855,4,FALSE)) -> 40.752913 | I49: 0 | J49: 1 | K49: 0 | M49: =+IF(VLOOKUP($A49,'Dataset2 ad'!$D$3:$L$855,8,FALSE)="","",VLOOKUP($A49,'Dataset2 ad'!$D$3:$L$855,8,FALSE)) -> 9.6980837 | N49: =+IF(VLOOKUP($A49,'Dataset2 ad'!$D$3:$L$855,9,FALSE)="","",VLOOKUP($A49,'Dataset2 ad'!$D$3:$L$855,9,FALSE)) -> 10.35533 | O49: 0 | P49: 1 | Q49: 0 | R49: 1 | S49: 0 | T49: 1 | U49: 0 | W49: 3 | AA49: 0 | AC49: 0 | AD49: 0 | AE49: 0 | AF49: 1
A50: =+VLOOKUP(B50,studies!$A$2:$C$102,3) -> Espagne et al. (2012) | B50: 75 | C50: 2012 | D50: 0 | E50: 2005 | F50: 2010 | H50: =+IF(VLOOKUP($A50,'Dataset2 ad'!$D$3:$L$855,4,FALSE)="","",VLOOKUP($A50,'Dataset2 ad'!$D$3:$L$855,4,FALSE)) -> 437.40563 | I50: 1 | J50: 0 | K50: 0 | M50: =+IF(VLOOKUP($A50,'Dataset2 ad'!$D$3:$L$855,8,FALSE)="","",VLOOKUP($A50,'Dataset2 ad'!$D$3:$L$855,8,FALSE)) -> 361.36815 | N50: =+IF(VLOOKUP($A50,'Dataset2 ad'!$D$3:$L$855,9,FALSE)="","",VLOOKUP($A50,'Dataset2 ad'!$D$3:$L$855,9,FALSE)) -> 407.14271 | O50: 1 | P50: 1 | Q50: 1 | R50: 0 | S50: 0 | T50: 0 | U50: 0 | V50: =+AVERAGE(Dataset0!V497:V498) -> 2.75 | W50: =+AVERAGE(Dataset0!W497:W498) -> 0.8 | X50: =+AVERAGE(Dataset0!X497:X498) -> 1.5 | Y50: =+AVERAGE(Dataset0!Y497:Y498) -> 1.3 | Z50: =+AVERAGE(Dataset0!Z497:Z498) -> 0.75 | AA50: 0 | AB50: =+AVERAGE(Dataset0!AB497:AB498) -> 3.5 | AC50: 0 | AD50: 0 | AE50: 0 | AF50: 1
A51: =+VLOOKUP(B51,studies!$A$2:$C$102,3) -> Gerlagh & Liski (2012) | B51: 76 | C51: 2012 | D51: 0 | E51: 2010 | F51: 2010 | H51: =+IF(VLOOKUP($A51,'Dataset2 ad'!$D$3:$L$855,4,FALSE)="","",VLOOKUP($A51,'Dataset2 ad'!$D$3:$L$855,4,FALSE)) -> 163.34198 | I51: 1 | J51: 0 | K51: 0 | M51: =+IF(VLOOKUP($A51,'Dataset2 ad'!$D$3:$L$855,8,FALSE)="","",VLOOKUP($A51,'Dataset2 ad'!$D$3:$L$855,8,FALSE)) -> 53.574265 | N51: =+IF(VLOOKUP($A51,'Dataset2 ad'!$D$3:$L$855,9,FALSE)="","",VLOOKUP($A51,'Dataset2 ad'!$D$3:$L$855,9,FALSE)) -> 9.1841597 | O51: 0 | P51: 1 | Q51: 1 | R51: 0 | S51: 0 | T51: 0 | U51: 0 | W51: 2 | AA51: 0 | AB51: 3 | AC51: 0 | AD51: 0 | AE51: 0 | AF51: =+AVERAGE(Dataset0!AF499:AF501) -> 0.33333333
A52: =+VLOOKUP(B52,studies!$A$2:$C$102,3) -> Johnson & Hope (2012) | B52: 77 | C52: 2012 | D52: 1 | E52: 2007 | F52: 2010 | H52: =+IF(VLOOKUP($A52,'Dataset2 ad'!$D$3:$L$855,4,FALSE)="","",VLOOKUP($A52,'Dataset2 ad'!$D$3:$L$855,4,FALSE)) -> 202.25553 | I52: 0 | J52: 1 | K52: 0 | M52: =+IF(VLOOKUP($A52,'Dataset2 ad'!$D$3:$L$855,8,FALSE)="","",VLOOKUP($A52,'Dataset2 ad'!$D$3:$L$855,8,FALSE)) -> 102.82469 | N52: =+IF(VLOOKUP($A52,'Dataset2 ad'!$D$3:$L$855,9,FALSE)="","",VLOOKUP($A52,'Dataset2 ad'!$D$3:$L$855,9,FALSE)) -> 371.14578 | O52: 0 | P52: 1 | Q52: 0 | R52: 1 | S52: 1 | T52: 1 | U52: 1 | V52: =+AVERAGE(Dataset0!V502:V515) -> 3 | W52: NA | AA52: 0 | AC52: 0 | AD52: 0 | AE52: 0 | AF52: 0
A53: =+VLOOKUP(B53,studies!$A$2:$C$102,3) -> Kopp et al. (2012) | B53: 78 | C53: 2012 | D53: 1 | E53: 2005 | F53: 2015 | H53: =+IF(VLOOKUP($A53,'Dataset2 ad'!$D$3:$L$855,4,FALSE)="","",VLOOKUP($A53,'Dataset2 ad'!$D$3:$L$855,4,FALSE)) -> 450.329 | I53: 0 | J53: 0 | K53: 1 | M53: =+IF(VLOOKUP($A53,'Dataset2 ad'!$D$3:$L$855,8,FALSE)="","",VLOOKUP($A53,'Dataset2 ad'!$D$3:$L$855,8,FALSE)) -> 176.1491 | N53: =+IF(VLOOKUP($A53,'Dataset2 ad'!$D$3:$L$855,9,FALSE)="","",VLOOKUP($A53,'Dataset2 ad'!$D$3:$L$855,9,FALSE)) -> 581.29202 | O53: 0 | P53: 1 | Q53: 0 | R53: 1 | S53: 0 | T53: 1 | U53: 0 | V53: =+AVERAGE(Dataset0!V516:V659) -> 3 | W53: =+AVERAGE(Dataset0!W516:W659) -> 0.7475 | AA53: 0 | AC53: 0 | AD53: 0 | AE53: 0 | AF53: 1
A54: =+VLOOKUP(B54,studies!$A$2:$C$102,3) -> Marten & Newbold (2012) | B54: 79 | C54: 2012 | D54: 1 | E54: 2007 | F54: 2015 | H54: =+IF(VLOOKUP($A54,'Dataset2 ad'!$D$3:$L$855,4,FALSE)="","",VLOOKUP($A54,'Dataset2 ad'!$D$3:$L$855,4,FALSE)) -> 142.67698 | I54: 1 | J54: 0 | K54: 0 | M54: =+IF(VLOOKUP($A54,'Dataset2 ad'!$D$3:$L$855,8,FALSE)="","",VLOOKUP($A54,'Dataset2 ad'!$D$3:$L$855,8,FALSE)) -> 46.037526 | N54: =+IF(VLOOKUP($A54,'Dataset2 ad'!$D$3:$L$855,9,FALSE)="","",VLOOKUP($A54,'Dataset2 ad'!$D$3:$L$855,9,FALSE)) -> 37.184155 | O54: 0 | P54: 1 | Q54: 0 | R54: 1 | S54: 0 | T54: 1 | U54: 0 | V54: =+AVERAGE(Dataset0!V660:V662) -> 3.5 | W54: NA | AA54: 0 | AC54: 0 | AD54: 0 | AE54: 0 | AF54: 0
A55: =+VLOOKUP(B55,studies!$A$2:$C$102,3) -> Anthoff & Tol (2013) | B55: 82 | C55: 2013 | D55: 1 | E55: 1995 | F55: 2015 | H55: =+IF(VLOOKUP($A55,'Dataset2 ad'!$D$3:$L$855,4,FALSE)="","",VLOOKUP($A55,'Dataset2 ad'!$D$3:$L$855,4,FALSE)) -> 73.543822 | I55: 1 | J55: 0 | K55: 0 | M55: =+IF(VLOOKUP($A55,'Dataset2 ad'!$D$3:$L$855,8,FALSE)="","",VLOOKUP($A55,'Dataset2 ad'!$D$3:$L$855,8,FALSE)) -> 35.850642 | N55: =+IF(VLOOKUP($A55,'Dataset2 ad'!$D$3:$L$855,9,FALSE)="","",VLOOKUP($A55,'Dataset2 ad'!$D$3:$L$855,9,FALSE)) -> 219.06414 | O55: 0 | P55: 1 | Q55: 1 | R55: 1 | S55: 1 | T55: 0 | U55: 0 | W55: =+AVERAGE(Dataset0!W665:W675) -> 1.3 | X55: =+AVERAGE(Dataset0!X665:X675) -> 1.5 | Z55: =1/X55 -> 0.66666667 | AA55: 0 | AC55: 0 | AD55: 0 | AE55: 1 | AF55: 0
A56: =+VLOOKUP(B56,studies!$A$2:$C$102,3) -> van den Bijgaart et al. (2013) | B56: 83 | C56: 2013 | D56: 0 | E56: 2010 | F56: 2015 | H56: =+IF(VLOOKUP($A56,'Dataset2 ad'!$D$3:$L$855,4,FALSE)="","",VLOOKUP($A56,'Dataset2 ad'!$D$3:$L$855,4,FALSE)) -> 28.486056 | I56: 0 | J56: 0 | K56: 1 | M56: =+IF(VLOOKUP($A56,'Dataset2 ad'!$D$3:$L$855,8,FALSE)="","",VLOOKUP($A56,'Dataset2 ad'!$D$3:$L$855,8,FALSE)) -> 8.4187061 | N56: =+IF(VLOOKUP($A56,'Dataset2 ad'!$D$3:$L$855,9,FALSE)="","",VLOOKUP($A56,'Dataset2 ad'!$D$3:$L$855,9,FALSE)) -> 89.739681 | O56: 1 | P56: 1 | Q56: 1 | R56: 0 | S56: 0 | T56: 0 | U56: 0 | V56: =+AVERAGE(Dataset0!V676:V679) -> 1.525 | W56: 2 | AA56: 0 | AB56: 3 | AC56: 0 | AD56: 0 | AE56: 0 | AF56: 1
A57: =+VLOOKUP(B57,studies!$A$2:$C$102,3) -> Cai et al. (2013) | B57: 84 | C57: 2013 | D57: 0 | E57: 2005 | F57: 2015 | H57: =+IF(VLOOKUP($A57,'Dataset2 ad'!$D$3:$L$855,4,FALSE)="","",VLOOKUP($A57,'Dataset2 ad'!$D$3:$L$855,4,FALSE)) -> 286.573 | I57: 0 | J57: 1 | K57: 0 | M57: =+IF(VLOOKUP($A57,'Dataset2 ad'!$D$3:$L$855,8,FALSE)="","",VLOOKUP($A57,'Dataset2 ad'!$D$3:$L$855,8,FALSE)) -> 52.635857 | N57: =+IF(VLOOKUP($A57,'Dataset2 ad'!$D$3:$L$855,9,FALSE)="","",VLOOKUP($A57,'Dataset2 ad'!$D$3:$L$855,9,FALSE)) -> 122.19038 | O57: 0 | P57: 1 | Q57: 1 | R57: 1 | S57: 0 | T57: 1 | U57: 0 | X57: 10 | Z57: =+AVERAGE(Dataset0!Z680:Z682) -> 1.1111111 | AA57: 0 | AB57: 3 | AC57: 0 | AD57: 0 | AE57: 0 | AF57: 1
A58: =+VLOOKUP(B58,studies!$A$2:$C$102,3) -> Greenstone et al. (2013) | B58: 87 | C58: 2013 | D58: 1 | E58: 2007 | F58: 2010 | H58: =+IF(VLOOKUP($A58,'Dataset2 ad'!$D$3:$L$855,4,FALSE)="","",VLOOKUP($A58,'Dataset2 ad'!$D$3:$L$855,4,FALSE)) -> 86.74515 | I58: 1 | J58: 0 | K58: 0 | M58: =+IF(VLOOKUP($A58,'Dataset2 ad'!$D$3:$L$855,8,FALSE)="","",VLOOKUP($A58,'Dataset2 ad'!$D$3:$L$855,8,FALSE)) -> 46.757259 | N58: =+IF(VLOOKUP($A58,'Dataset2 ad'!$D$3:$L$855,9,FALSE)="","",VLOOKUP($A58,'Dataset2 ad'!$D$3:$L$855,9,FALSE)) -> 76.591097 | O58: 0 | P58: 1 | Q58: 1 | R58: 1 | S58: 1 | T58: 1 | U58: 1 | V58: =+AVERAGE(Dataset0!V685:V731) -> 3.5212766 | W58: NA | AA58: 0 | AC58: 0 | AD58: 0 | AE58: 0 | AF58: 0
A59: =+VLOOKUP(B59,studies!$A$2:$C$102,3) -> Hwang et al. (2013) | B59: 88 | C59: 2013 | D59: 1 | E59: 2005 | F59: 2005 | H59: =+IF(VLOOKUP($A59,'Dataset2 ad'!$D$3:$L$855,4,FALSE)="","",VLOOKUP($A59,'Dataset2 ad'!$D$3:$L$855,4,FALSE)) -> 71.291059 | I59: 0 | J59: 1 | K59: 0 | M59: =+IF(VLOOKUP($A59,'Dataset2 ad'!$D$3:$L$855,8,FALSE)="","",VLOOKUP($A59,'Dataset2 ad'!$D$3:$L$855,8,FALSE)) -> 23.410275 | N59: =+IF(VLOOKUP($A59,'Dataset2 ad'!$D$3:$L$855,9,FALSE)="","",VLOOKUP($A59,'Dataset2 ad'!$D$3:$L$855,9,FALSE)) -> 134.11572 | O59: 1 | P59: 1 | Q59: 0 | R59: 1 | S59: 0 | T59: 1 | U59: 0 | V59: =+W59+X59*Y59 -> 5.5 | W59: =+AVERAGE(Dataset0!W732:W743) -> 1.5 | X59: =+AVERAGE(Dataset0!X732:X743) -> 2.5 | Y59: =+AVERAGE(Dataset0!Y732:Y743) -> 1.6 | Z59: =1/X59 -> 0.4 | AA59: 0 | AC59: 0 | AD59: 0 | AE59: 1 | AF59: 0
A60: =+VLOOKUP(B60,studies!$A$2:$C$102,3) -> Moyer et al. (2013) | B60: 91 | C60: 2013 | D60: 0 | E60: 2007 | F60: 2010 | H60: =+IF(VLOOKUP($A60,'Dataset2 ad'!$D$3:$L$855,4,FALSE)="","",VLOOKUP($A60,'Dataset2 ad'!$D$3:$L$855,4,FALSE)) -> 507.88611 | I60: 0 | J60: 1 | K60: 0 | M60: =+IF(VLOOKUP($A60,'Dataset2 ad'!$D$3:$L$855,8,FALSE)="","",VLOOKUP($A60,'Dataset2 ad'!$D$3:$L$855,8,FALSE)) -> 445.38018 | N60: =+IF(VLOOKUP($A60,'Dataset2 ad'!$D$3:$L$855,9,FALSE)="","",VLOOKUP($A60,'Dataset2 ad'!$D$3:$L$855,9,FALSE)) -> 502.41098 | O60: 0 | P60: 1 | Q60: 0 | R60: 1 | S60: 0 | T60: 1 | U60: 0 | W60: 1 | X60: 2 | AA60: 0 | AC60: 0 | AD60: 0 | AE60: 0 | AF60: 0
A61: =+VLOOKUP(B61,studies!$A$2:$C$102,3) -> Newbold et al. (2013) | B61: 92 | C61: 2013 | D61: 1 | E61: 2005 | F61: 2015 | H61: =+IF(VLOOKUP($A61,'Dataset2 ad'!$D$3:$L$855,4,FALSE)="","",VLOOKUP($A61,'Dataset2 ad'!$D$3:$L$855,4,FALSE)) -> 61.178852 | I61: 0 | J61: 0 | K61: 1 | M61: =+IF(VLOOKUP($A61,'Dataset2 ad'!$D$3:$L$855,8,FALSE)="","",VLOOKUP($A61,'Dataset2 ad'!$D$3:$L$855,8,FALSE)) -> 20.094414 | N61: =+IF(VLOOKUP($A61,'Dataset2 ad'!$D$3:$L$855,9,FALSE)="","",VLOOKUP($A61,'Dataset2 ad'!$D$3:$L$855,9,FALSE)) -> 0.10545066 | O61: 1 | P61: 1 | Q61: 1 | R61: 1 | S61: 0 | T61: 0 | U61: 0 | V61: 4.7 | W61: 1.34 | X61: 1.71 | Y61: =+(V61-W61)/X61 -> 1.9649123 | Z61: =1/X61 -> 0.58479532 | AA61: 0 | AC61: 0 | AD61: 0 | AE61: 0 | AF61: 0
A62: =+VLOOKUP(B62,studies!$A$2:$C$102,3) -> Tol (2013) | B62: 94 | C62: 2013 | D62: 1 | E62: 2010 | F62: 2013 | H62: =+IF(VLOOKUP($A62,'Dataset2 ad'!$D$3:$L$855,4,FALSE)="","",VLOOKUP($A62,'Dataset2 ad'!$D$3:$L$855,4,FALSE)) -> 0.90371857 | I62: 0 | J62: 1 | K62: 0 | M62: =+IF(VLOOKUP($A62,'Dataset2 ad'!$D$3:$L$855,8,FALSE)="","",VLOOKUP($A62,'Dataset2 ad'!$D$3:$L$855,8,FALSE)) -> 0.62652758 | N62: =+IF(VLOOKUP($A62,'Dataset2 ad'!$D$3:$L$855,9,FALSE)="","",VLOOKUP($A62,'Dataset2 ad'!$D$3:$L$855,9,FALSE)) -> 111.48394 | O62: 0 | P62: 1 | Q62: 0 | R62: 0 | S62: 0 | T62: 0 | U62: 0 | V62: NA | W62: NA | X62: 1.5 | Z62: =1/X62 -> 0.66666667 | AA62: 1 | AB62: =+AVERAGE(Dataset0!AB752:AB765) -> 3 | AC62: 0 | AD62: 0 | AE62: 1 | AF62: 1
A63: =+VLOOKUP(B63,studies!$A$2:$C$102,3) -> Weitzman (2013) | B63: 95 | C63: 2013 | D63: 1 | E63: 2007 | F63: 2010 | H63: =+IF(VLOOKUP($A63,'Dataset2 ad'!$D$3:$L$855,4,FALSE)="","",VLOOKUP($A63,'Dataset2 ad'!$D$3:$L$855,4,FALSE)) -> 346.08169 | I63: 0 | J63: 1 | K63: 0 | M63: =+IF(VLOOKUP($A63,'Dataset2 ad'!$D$3:$L$855,8,FALSE)="","",VLOOKUP($A63,'Dataset2 ad'!$D$3:$L$855,8,FALSE)) -> 174.27914 | N63: =+IF(VLOOKUP($A63,'Dataset2 ad'!$D$3:$L$855,9,FALSE)="","",VLOOKUP($A63,'Dataset2 ad'!$D$3:$L$855,9,FALSE)) -> 433.40471 | O63: 0 | P63: 1 | Q63: 1 | R63: 1 | S63: 1 | T63: 1 | U63: 1 | V63: =+AVERAGE(Dataset0!V766:V779) -> 2.0714286 | Y63: NA | AA63: 0 | AC63: 0 | AD63: 0 | AE63: 0 | AF63: 0
A64: =+VLOOKUP(B64,studies!$A$2:$C$102,3) -> Golosov et al. (2014) | B64: 96 | C64: 2014 | D64: 1 | E64: 2013 | F64: 2013 | H64: =+IF(VLOOKUP($A64,'Dataset2 ad'!$D$3:$L$855,4,FALSE)="","",VLOOKUP($A64,'Dataset2 ad'!$D$3:$L$855,4,FALSE)) -> 227.77698 | I64: 1 | J64: 0 | K64: 0 | M64: =+IF(VLOOKUP($A64,'Dataset2 ad'!$D$3:$L$855,8,FALSE)="","",VLOOKUP($A64,'Dataset2 ad'!$D$3:$L$855,8,FALSE)) -> 101.8518 | N64: =+IF(VLOOKUP($A64,'Dataset2 ad'!$D$3:$L$855,9,FALSE)="","",VLOOKUP($A64,'Dataset2 ad'!$D$3:$L$855,9,FALSE)) -> 1531.2213 | O64: 1 | P64: 1 | Q64: 0 | R64: 0 | S64: 0 | T64: 0 | U64: 0 | W64: 0.1 | X64: =1/Z64 -> 2 | Z64: 0.5 | AA64: 0 | AC64: 0 | AD64: 0 | AE64: 0 | AF64: 1
A65: =+VLOOKUP(B65,studies!$A$2:$C$102,3) -> Howarth et al. (2014) | B65: 97 | C65: 2014 | D65: 1 | E65: 2005 | F65: 2010 | H65: =+IF(VLOOKUP($A65,'Dataset2 ad'!$D$3:$L$855,4,FALSE)="","",VLOOKUP($A65,'Dataset2 ad'!$D$3:$L$855,4,FALSE)) -> 128.83584 | I65: 0 | J65: 1 | K65: 0 | M65: =+IF(VLOOKUP($A65,'Dataset2 ad'!$D$3:$L$855,8,FALSE)="","",VLOOKUP($A65,'Dataset2 ad'!$D$3:$L$855,8,FALSE)) -> 87.360849 | N65: =+IF(VLOOKUP($A65,'Dataset2 ad'!$D$3:$L$855,9,FALSE)="","",VLOOKUP($A65,'Dataset2 ad'!$D$3:$L$855,9,FALSE)) -> 97.972226 | O65: 0 | P65: 1 | Q65: 0 | R65: 1 | S65: 0 | T65: 1 | U65: 0 | X65: =+AVERAGE(Dataset0!X787:X788) -> 2.75 | Z65: =1/X65 -> 0.36363636 | AA65: 0 | AC65: 0 | AD65: 0 | AE65: 0 | AF65: 0
A66: =+VLOOKUP(B66,studies!$A$2:$C$102,3) -> Jensen & Traeger (2014a) | B66: 98 | C66: 2014 | D66: 1 | E66: 2012 | F66: 2012 | H66: =+IF(VLOOKUP($A66,'Dataset2 ad'!$D$3:$L$855,4,FALSE)="","",VLOOKUP($A66,'Dataset2 ad'!$D$3:$L$855,4,FALSE)) -> 53.668083 | I66: 0 | J66: 1 | K66: 0 | M66: =+IF(VLOOKUP($A66,'Dataset2 ad'!$D$3:$L$855,8,FALSE)="","",VLOOKUP($A66,'Dataset2 ad'!$D$3:$L$855,8,FALSE)) -> 7.3198537 | N66: =+IF(VLOOKUP($A66,'Dataset2 ad'!$D$3:$L$855,9,FALSE)="","",VLOOKUP($A66,'Dataset2 ad'!$D$3:$L$855,9,FALSE)) -> 16.808553 | O66: 0 | P66: 1 | Q66: 0 | R66: 0 | S66: 0 | T66: 1 | U66: 0 | X66: =+AVERAGE(Dataset0!X789:X794) -> 7.3333333 | Z66: =+AVERAGE(Dataset0!Z789:Z794) -> 1 | AA66: 0 | AB66: 3 | AC66: 0 | AD66: 0 | AE66: 0 | AF66: 0
A67: =+VLOOKUP(B67,studies!$A$2:$C$102,3) -> Lemoine & Traeger (2014) | B67: 99 | C67: 2014 | D67: 1 | E67: 2005 | F67: 2015 | H67: =+IF(VLOOKUP($A67,'Dataset2 ad'!$D$3:$L$855,4,FALSE)="","",VLOOKUP($A67,'Dataset2 ad'!$D$3:$L$855,4,FALSE)) -> 49.1268 | I67: 0 | J67: 1 | K67: 0 | M67: =+IF(VLOOKUP($A67,'Dataset2 ad'!$D$3:$L$855,8,FALSE)="","",VLOOKUP($A67,'Dataset2 ad'!$D$3:$L$855,8,FALSE)) -> 3.3419592 | N67: =+IF(VLOOKUP($A67,'Dataset2 ad'!$D$3:$L$855,9,FALSE)="","",VLOOKUP($A67,'Dataset2 ad'!$D$3:$L$855,9,FALSE)) -> 5.8484285 | O67: 1 | P67: 1 | Q67: 1 | R67: 0 | S67: 0 | T67: 1 | U67: 0 | X67: 2 | Z67: 0.5 | AA67: 0 | AB67: 3 | AC67: 0 | AD67: 0 | AE67: 0 | AF67: 1
A68: =+VLOOKUP(B68,studies!$A$2:$C$102,3) -> Pycroft et al. (2014) | B68: 101 | C68: 2014 | D68: 1 | E68: 2005 | F68: 2009 | H68: =+IF(VLOOKUP($A68,'Dataset2 ad'!$D$3:$L$855,4,FALSE)="","",VLOOKUP($A68,'Dataset2 ad'!$D$3:$L$855,4,FALSE)) -> 292.75009 | I68: 1 | J68: 0 | K68: 0 | M68: =+IF(VLOOKUP($A68,'Dataset2 ad'!$D$3:$L$855,8,FALSE)="","",VLOOKUP($A68,'Dataset2 ad'!$D$3:$L$855,8,FALSE)) -> 22.71813 | N68: =+IF(VLOOKUP($A68,'Dataset2 ad'!$D$3:$L$855,9,FALSE)="","",VLOOKUP($A68,'Dataset2 ad'!$D$3:$L$855,9,FALSE)) -> 22.969159 | O68: 0 | P68: 1 | Q68: 0 | R68: 1 | S68: 0 | T68: 0 | U68: 1 | V68: NA | W68: NA | AA68: 1 | AC68: 1 | AD68: 0 | AE68: 0 | AF68: 0
A69: =+VLOOKUP(B69,studies!$A$2:$C$102,3) -> Rezai & van der Ploeg (2014) | B69: 102 | C69: 2014 | D69: 0 | E69: 2010 | F69: 2010 | H69: =+IF(VLOOKUP($A69,'Dataset2 ad'!$D$3:$L$855,4,FALSE)="","",VLOOKUP($A69,'Dataset2 ad'!$D$3:$L$855,4,FALSE)) -> 99.072844 | I69: 0 | J69: 1 | K69: 0 | M69: =+IF(VLOOKUP($A69,'Dataset2 ad'!$D$3:$L$855,8,FALSE)="","",VLOOKUP($A69,'Dataset2 ad'!$D$3:$L$855,8,FALSE)) -> 23.09091 | N69: =+IF(VLOOKUP($A69,'Dataset2 ad'!$D$3:$L$855,9,FALSE)="","",VLOOKUP($A69,'Dataset2 ad'!$D$3:$L$855,9,FALSE)) -> 24.615614 | O69: 1 | P69: 1 | Q69: 0 | R69: 0 | S69: 0 | T69: 0 | U69: 0 | W69: 0.96 | X69: 2 | Z69: 0.5 | AA69: 0 | AB69: 2.3 | AC69: 0 | AD69: 0 | AE69: 0 | AF69: 1

Sheet Dataset2 ad
A1: Name | B1: ID | C1: SCC | E1: percentile | F1: percentile | G1: percentile | H1: percentile | I1: percentile | J1: STDEV | K1: STDlow | L1: STDup | M1: STDEV | N1: STDlow | O1: STDup
C2: $/tC | E2: 0.05 | F2: 0.25 | G2: 0.5 | H2: 0.75 | I2: 0.95 | M2: $/tC | N2: $/tC | O2: $/tC
A3: =+VLOOKUP(B3,studies!$A$2:$C$102,3) -> Nordhaus (1982) | B3: 1 | C3: 1984.9987 | D3: =+A3 -> Nordhaus (1982) | F3: =+C4 -> 283.57124 | G3: =+MEDIAN(C3:C4) -> 1134.285 | H3: =+C3 -> 1984.9987 | J3: =+STDEV(C3:C4) -> 1203.0909 | K3: =G3-F3/1.1505 -> 887.80844 | L3: =H3-G3/1.1505 -> 999.09259
A4: =+VLOOKUP(B4,studies!$A$2:$C$102,3) -> Nordhaus (1982) | B4: 1 | C4: 283.57124 | D4: =+IF(B4=B3,"",A4)
A5: =+VLOOKUP(B5,studies!$A$2:$C$102,3) -> Ayres & Walter (1991) | B5: 2 | C5: 450.7956 | D5: =+IF(B5=B4,"",A5) -> Ayres & Walter (1991)
A6: =+VLOOKUP(B6,studies!$A$2:$C$102,3) -> Nordhaus (1991) | B6: 3 | C6: 914.62959 | D6: =+IF(B6=B5,"",A6) -> Nordhaus (1991) | E6: =+PERCENTILE($C6:$C14,E$2) -> 9.3488072 | F6: =+PERCENTILE($C6:$C14,F$2) -> 25.38326 | G6: =+PERCENTILE($C6:$C14,G$2) -> 101.67175 | H6: =+PERCENTILE($C6:$C14,H$2) -> 203.20478 | I6: =+PERCENTILE($C6:$C14,I$2) -> 731.70367 | J6: =+STDEV($C6:$C14) -> 300.68178 | K6: =+IF(I6="","",(G6-E6)/1.96) -> 47.10354 | L6: =+IF(I6="","",(I6-G6)/1.96) -> 321.44486
A7: =+VLOOKUP(B7,studies!$A$2:$C$102,3) -> Nordhaus (1991) | B7: 3 | C7: 457.31479 | D7: =+IF(B7=B6,"",A7) | K7: =+IF(I7="","",(G7-E7)/1.96) | L7: =+IF(I7="","",(I7-G7)/1.96)
A8: =+VLOOKUP(B8,studies!$A$2:$C$102,3) -> Nordhaus (1991) | B8: 3 | C8: 114.29402 | D8: =+IF(B8=B7,"",A8) | K8: =+IF(I8="","",(G8-E8)/1.96) | L8: =+IF(I8="","",(I8-G8)/1.96)
A9: =+VLOOKUP(B9,studies!$A$2:$C$102,3) -> Nordhaus (1991) | B9: 3 | C9: 203.20478 | D9: =+IF(B9=B8,"",A9) | K9: =+IF(I9="","",(G9-E9)/1.96) | L9: =+IF(I9="","",(I9-G9)/1.96)
A10: =+VLOOKUP(B10,studies!$A$2:$C$102,3) -> Nordhaus (1991) | B10: 3 | C10: 101.67175 | D10: =+IF(B10=B9,"",A10) | K10: =+IF(I10="","",(G10-E10)/1.96) | L10: =+IF(I10="","",(I10-G10)/1.96)
A11: =+VLOOKUP(B11,studies!$A$2:$C$102,3) -> Nordhaus (1991) | B11: 3 | C11: 25.38326 | D11: =+IF(B11=B10,"",A11) | K11: =+IF(I11="","",(G11-E11)/1.96) | L11: =+IF(I11="","",(I11-G11)/1.96)
A12: =+VLOOKUP(B12,studies!$A$2:$C$102,3) -> Nordhaus (1991) | B12: 3 | C12: 33.844346 | D12: =+IF(B12=B11,"",A12) | K12: =+IF(I12="","",(G12-E12)/1.96) | L12: =+IF(I12="","",(I12-G12)/1.96)
A13: =+VLOOKUP(B13,studies!$A$2:$C$102,3) -> Nordhaus (1991) | B13: 3 | C13: 16.922173 | D13: =+IF(B13=B12,"",A13) | K13: =+IF(I13="","",(G13-E13)/1.96) | L13: =+IF(I13="","",(I13-G13)/1.96)
A14: =+VLOOKUP(B14,studies!$A$2:$C$102,3) -> Nordhaus (1991) | B14: 3 | C14: 4.2998965 | D14: =+IF(B14=B13,"",A14) | K14: =+IF(I14="","",(G14-E14)/1.96) | L14: =+IF(I14="","",(I14-G14)/1.96)
A15: =+VLOOKUP(B15,studies!$A$2:$C$102,3) -> Cline (1992) | B15: 4 | C15: 245.51022 | D15: =+IF(B15=B14,"",A15) -> Cline (1992) | K15: =+IF(I15="","",(G15-E15)/1.96) | L15: =+IF(I15="","",(I15-G15)/1.96) | M15: 111.7847 | N15: 114.06602 | O15: 114.06602
A16: =+VLOOKUP(B16,studies!$A$2:$C$102,3) -> Haraden (1992) | B16: 5 | C16: 72.59118 | D16: =+IF(B16=B15,"",A16) -> Haraden (1992) | K16: =+IF(I16="","",(G16-E16)/1.96) | L16: =+IF(I16="","",(I16-G16)/1.96)
A17: =+VLOOKUP(B17,studies!$A$2:$C$102,3) -> Hohmeyer & Gaertner (1992) | B17: 6 | C17: 6383.0401 | D17: =+IF(B17=B16,"",A17) -> Hohmeyer & Gaertner (1992) | K17: =+IF(I17="","",(G17-E17)/1.96) | L17: =+IF(I17="","",(I17-G17)/1.96)
A18: =+VLOOKUP(B18,studies!$A$2:$C$102,3) -> Penner et al. (1992) | B18: 7 | C18: 65.023092 | D18: =+IF(B18=B17,"",A18) -> Penner et al. (1992) | K18: =+IF(I18="","",(G18-E18)/1.96) | L18: =+IF(I18="","",(I18-G18)/1.96)
A19: =+VLOOKUP(B19,studies!$A$2:$C$102,3) -> Haraden (1993) | B19: 8 | C19: 7.2161199 | D19: =+IF(B19=B18,"",A19) -> Haraden (1993) | E19: =+PERCENTILE($C19:$C21,E$2) -> 7.6568884 | F19: =+PERCENTILE($C19:$C21,F$2) -> 9.419962 | G19: =+PERCENTILE($C19:$C21,G$2) -> 11.623804 | H19: =+PERCENTILE($C19:$C21,H$2) -> 22.93556 | I19: =+PERCENTILE($C19:$C21,I$2) -> 31.984964 | J19: =+STDEV($C19:$C21) -> 14.502508 | K19: =+IF(I19="","",(G19-E19)/1.96) -> 2.0239366 | L19: =+IF(I19="","",(I19-G19)/1.96) -> 10.388347
A20: =+VLOOKUP(B20,studies!$A$2:$C$102,3) -> Haraden (1993) | B20: 8 | C20: 11.623804 | D20: =+IF(B20=B19,"",A20) | K20: =+IF(I20="","",(G20-E20)/1.96) | L20: =+IF(I20="","",(I20-G20)/1.96)
A21: =+VLOOKUP(B21,studies!$A$2:$C$102,3) -> Haraden (1993) | B21: 8 | C21: 34.247315 | D21: =+IF(B21=B20,"",A21) | K21: =+IF(I21="","",(G21-E21)/1.96) | L21: =+IF(I21="","",(I21-G21)/1.96)
A22: =+VLOOKUP(B22,studies!$A$2:$C$102,3) -> Nordhaus (1993) | B22: 9 | C22: 18.914501 | D22: =+IF(B22=B21,"",A22) -> Nordhaus (1993) | K22: =+IF(I22="","",(G22-E22)/1.96) | L22: =+IF(I22="","",(I22-G22)/1.96)
A23: =+VLOOKUP(B23,studies!$A$2:$C$102,3) -> Parry (1993) | B23: 10 | C23: 0.025256367 | D23: =+IF(B23=B22,"",A23) -> Parry (1993) | E23: =+PERCENTILE($C23:$C82,E$2) -> 0.062509508 | F23: =+PERCENTILE($C23:$C82,F$2) -> 0.32201868 | G23: =+PERCENTILE($C23:$C82,G$2) -> 1.5406384 | H23: =+PERCENTILE($C23:$C82,H$2) -> 12.287222 | I23: =+PERCENTILE($C23:$C82,I$2) -> 1750.664 | J23: =+STDEV($C23:$C82) -> 1460.2285 | K23: =+IF(I23="","",(G23-E23)/1.96) -> 0.75414738 | L23: =+IF(I23="","",(I23-G23)/1.96) -> 892.40989
A24: =+VLOOKUP(B24,studies!$A$2:$C$102,3) -> Parry (1993) | B24: 10 | C24: 0.1515382 | D24: =+IF(B24=B23,"",A24) | K24: =+IF(I24="","",(G24-E24)/1.96) | L24: =+IF(I24="","",(I24-G24)/1.96)
A25: =+VLOOKUP(B25,studies!$A$2:$C$102,3) -> Parry (1993) | B25: 10 | C25: 0.03788455 | D25: =+IF(B25=B24,"",A25) | K25: =+IF(I25="","",(G25-E25)/1.96) | L25: =+IF(I25="","",(I25-G25)/1.96)
A26: =+VLOOKUP(B26,studies!$A$2:$C$102,3) -> Parry (1993) | B26: 10 | C26: 0.2273073 | D26: =+IF(B26=B25,"",A26) | K26: =+IF(I26="","",(G26-E26)/1.96) | L26: =+IF(I26="","",(I26-G26)/1.96)
A27: =+VLOOKUP(B27,studies!$A$2:$C$102,3) -> Parry (1993) | B27: 10 | C27: 0.075769101 | D27: =+IF(B27=B26,"",A27) | K27: =+IF(I27="","",(G27-E27)/1.96) | L27: =+IF(I27="","",(I27-G27)/1.96)
A28: =+VLOOKUP(B28,studies!$A$2:$C$102,3) -> Parry (1993) | B28: 10 | C28: 0.4546146 | D28: =+IF(B28=B27,"",A28) | K28: =+IF(I28="","",(G28-E28)/1.96) | L28: =+IF(I28="","",(I28-G28)/1.96)
A29: =+VLOOKUP(B29,studies!$A$2:$C$102,3) -> Parry (1993) | B29: 10 | C29: 0.13891002 | D29: =+IF(B29=B28,"",A29) | K29: =+IF(I29="","",(G29-E29)/1.96) | L29: =+IF(I29="","",(I29-G29)/1.96)
A30: =+VLOOKUP(B30,studies!$A$2:$C$102,3) -> Parry (1993) | B30: 10 | C30: 0.83346011 | D30: =+IF(B30=B29,"",A30) | K30: =+IF(I30="","",(G30-E30)/1.96) | L30: =+IF(I30="","",(I30-G30)/1.96)
A31: =+VLOOKUP(B31,studies!$A$2:$C$102,3) -> Parry (1993) | B31: 10 | C31: 0.34096095 | D31: =+IF(B31=B30,"",A31) | K31: =+IF(I31="","",(G31-E31)/1.96) | L31: =+IF(I31="","",(I31-G31)/1.96)
A32: =+VLOOKUP(B32,studies!$A$2:$C$102,3) -> Parry (1993) | B32: 10 | C32: 2.0457657 | D32: =+IF(B32=B31,"",A32) | K32: =+IF(I32="","",(G32-E32)/1.96) | L32: =+IF(I32="","",(I32-G32)/1.96)
A33: =+VLOOKUP(B33,studies!$A$2:$C$102,3) -> Parry (1993) | B33: 10 | C33: 0.050512734 | D33: =+IF(B33=B32,"",A33) | K33: =+IF(I33="","",(G33-E33)/1.96) | L33: =+IF(I33="","",(I33-G33)/1.96)
A34: =+VLOOKUP(B34,studies!$A$2:$C$102,3) -> Parry (1993) | B34: 10 | C34: 0.3030764 | D34: =+IF(B34=B33,"",A34) | K34: =+IF(I34="","",(G34-E34)/1.96) | L34: =+IF(I34="","",(I34-G34)/1.96)
A35: =+VLOOKUP(B35,studies!$A$2:$C$102,3) -> Parry (1993) | B35: 10 | C35: 0.075769101 | D35: =+IF(B35=B34,"",A35) | K35: =+IF(I35="","",(G35-E35)/1.96) | L35: =+IF(I35="","",(I35-G35)/1.96)
... A82: =+VLOOKUP(B82,studies!$A$2:$C$102,3) -> Parry (1993) | B82: 10 | C82: 10396.657 | D82: =+IF(B82=B81,"",A82) | K82: =+IF(I82="","",(G82-E82)/1.96) | L82: =+IF(I82="","",(I82-G82)/1.96)
A83: =+VLOOKUP(B83,studies!$A$2:$C$102,3) -> Peck & Teisberg (1993) | B83: 11 | C83: 11.105529 | D83: =+IF(B83=B82,"",A83) -> Peck & Teisberg (1993) | E83: =+PERCENTILE($C83:$C109,E$2) -> 7.6072873 | F83: =+PERCENTILE($C83:$C109,F$2) -> 20.26759 | G83: =+PERCENTILE($C83:$C109,G$2) -> 24.543219 | H83: =+PERCENTILE($C83:$C109,H$2) -> 27.708295 | I83: =+PERCENTILE($C83:$C109,I$2) -> 55.305534 | J83: =+STDEV($C83:$C109) -> 14.135646 | K83: =+IF(I83="","",(G83-E83)/1.96) -> 8.6407814 | L83: =+IF(I83="","",(I83-G83)/1.96) -> 15.695059
A84: =+VLOOKUP(B84,studies!$A$2:$C$102,3) -> Peck & Teisberg (1993) | B84: 11 | C84: 24.210053 | D84: =+IF(B84=B83,"",A84) | K84: =+IF(I84="","",(G84-E84)/1.96) | L84: =+IF(I84="","",(I84-G84)/1.96)
A85: =+VLOOKUP(B85,studies!$A$2:$C$102,3) -> Peck & Teisberg (1993) | B85: 11 | C85: 24.543219 | D85: =+IF(B85=B84,"",A85) | K85: =+IF(I85="","",(G85-E85)/1.96) | L85: =+IF(I85="","",(I85-G85)/1.96)
A86: =+VLOOKUP(B86,studies!$A$2:$C$102,3) -> Peck & Teisberg (1993) | B86: 11 | C86: 25.431661 | D86: =+IF(B86=B85,"",A86) | K86: =+IF(I86="","",(G86-E86)/1.96) | L86: =+IF(I86="","",(I86-G86)/1.96)
A87: =+VLOOKUP(B87,studies!$A$2:$C$102,3) -> Peck & Teisberg (1993) | B87: 11 | C87: 24.210053 | D87: =+IF(B87=B86,"",A87) | K87: =+IF(I87="","",(G87-E87)/1.96) | L87: =+IF(I87="","",(I87-G87)/1.96)
A88: =+VLOOKUP(B88,studies!$A$2:$C$102,3) -> Peck & Teisberg (1993) | B88: 11 | C88: 24.543219 | D88: =+IF(B88=B87,"",A88) | K88: =+IF(I88="","",(G88-E88)/1.96) | L88: =+IF(I88="","",(I88-G88)/1.96)
A89: =+VLOOKUP(B89,studies!$A$2:$C$102,3) -> Peck & Teisberg (1993) | B89: 11 | C89: 3.7758798 | D89: =+IF(B89=B88,"",A89) | K89: =+IF(I89="","",(G89-E89)/1.96) | L89: =+IF(I89="","",(I89-G89)/1.96)
A90: =+VLOOKUP(B90,studies!$A$2:$C$102,3) -> Peck & Teisberg (1993) | B90: 11 | C90: 6.1080409 | D90: =+IF(B90=B89,"",A90) | K90: =+IF(I90="","",(G90-E90)/1.96) | L90: =+IF(I90="","",(I90-G90)/1.96)
A91: =+VLOOKUP(B91,studies!$A$2:$C$102,3) -> Peck & Teisberg (1993) | B91: 11 | C91: 13.326635 | D91: =+IF(B91=B90,"",A91) | K91: =+IF(I91="","",(G91-E91)/1.96) | L91: =+IF(I91="","",(I91-G91)/1.96)
A92: =+VLOOKUP(B92,studies!$A$2:$C$102,3) -> Peck & Teisberg (1993) | B92: 11 | C92: 11.882916 | D92: =+IF(B92=B91,"",A92) | K92: =+IF(I92="","",(G92-E92)/1.96) | L92: =+IF(I92="","",(I92-G92)/1.96)
A93: =+VLOOKUP(B93,studies!$A$2:$C$102,3) -> Peck & Teisberg (1993) | B93: 11 | C93: 21.21156 | D93: =+IF(B93=B92,"",A93) | K93: =+IF(I93="","",(G93-E93)/1.96) | L93: =+IF(I93="","",(I93-G93)/1.96)
A94: =+VLOOKUP(B94,studies!$A$2:$C$102,3) -> Peck & Teisberg (1993) | B94: 11 | C94: 21.322615 | D94: =+IF(B94=B93,"",A94) | K94: =+IF(I94="","",(G94-E94)/1.96) | L94: =+IF(I94="","",(I94-G94)/1.96)
A95: =+VLOOKUP(B95,studies!$A$2:$C$102,3) -> Peck & Teisberg (1993) | B95: 11 | C95: 19.32362 | D95: =+IF(B95=B94,"",A95) | K95: =+IF(I95="","",(G95-E95)/1.96) | L95: =+IF(I95="","",(I95-G95)/1.96)
... A109: =+VLOOKUP(B109,studies!$A$2:$C$102,3) -> Peck & Teisberg (1993) | B109: 11 | C109: 49.863825 | D109: =+IF(B109=B108,"",A109) | K109: =+IF(I109="","",(G109-E109)/1.96) | L109: =+IF(I109="","",(I109-G109)/1.96)
A110: =+VLOOKUP(B110,studies!$A$2:$C$102,3) -> Reilly & Richards (1993) | B110: 12 | C110: 51.322406 | D110: =+IF(B110=B109,"",A110) -> Reilly & Richards (1993) | E110: =+PERCENTILE($C110:$C117,E$2) -> 36.320472 | F110: =+PERCENTILE($C110:$C117,F$2) -> 50.993416 | G110: =+PERCENTILE($C110:$C117,G$2) -> 71.719773 | H110: =+PERCENTILE($C110:$C117,H$2) -> 99.683904 | I110: =+PERCENTILE($C110:$C117,I$2) -> 175.02256 | J110: =+STDEV($C110:$C117) -> 54.836361 | K110: =+IF(I110="","",(G110-E110)/1.96) -> 18.060868 | L110: =+IF(I110="","",(I110-G110)/1.96) -> 52.705506
A111: =+VLOOKUP(B111,studies!$A$2:$C$102,3) -> Reilly & Richards (1993) | B111: 12 | C111: 76.32563 | D111: =+IF(B111=B110,"",A111) | K111: =+IF(I111="","",(G111-E111)/1.96) | L111: =+IF(I111="","",(I111-G111)/1.96)
A112: =+VLOOKUP(B112,studies!$A$2:$C$102,3) -> Reilly & Richards (1993) | B112: 12 | C112: 184.23428 | D112: =+IF(B112=B111,"",A112) | K112: =+IF(I112="","",(G112-E112)/1.96) | L112: =+IF(I112="","",(I112-G112)/1.96)
A113: =+VLOOKUP(B113,studies!$A$2:$C$102,3) -> Reilly & Richards (1993) | B113: 12 | C113: 157.9151 | D113: =+IF(B113=B112,"",A113) | K113: =+IF(I113="","",(G113-E113)/1.96) | L113: =+IF(I113="","",(I113-G113)/1.96)
A114: =+VLOOKUP(B114,studies!$A$2:$C$102,3) -> Reilly & Richards (1993) | B114: 12 | C114: 28.951101 | D114: =+IF(B114=B113,"",A114) | K114: =+IF(I114="","",(G114-E114)/1.96) | L114: =+IF(I114="","",(I114-G114)/1.96)
A115: =+VLOOKUP(B115,studies!$A$2:$C$102,3) -> Reilly & Richards (1993) | B115: 12 | C115: 50.006447 | D115: =+IF(B115=B114,"",A115) | K115: =+IF(I115="","",(G115-E115)/1.96) | L115: =+IF(I115="","",(I115-G115)/1.96)
A116: =+VLOOKUP(B116,studies!$A$2:$C$102,3) -> Reilly & Richards (1993) | B116: 12 | C116: 67.113916 | D116: =+IF(B116=B115,"",A116) | K116: =+IF(I116="","",(G116-E116)/1.96) | L116: =+IF(I116="","",(I116-G116)/1.96)
A117: =+VLOOKUP(B117,studies!$A$2:$C$102,3) -> Reilly & Richards (1993) | B117: 12 | C117: 80.273507 | D117: =+IF(B117=B116,"",A117) | K117: =+IF(I117="","",(G117-E117)/1.96) | L117: =+IF(I117="","",(I117-G117)/1.96)
A118: =+VLOOKUP(B118,studies!$A$2:$C$102,3) -> Azar (1994) | B118: 13 | C118: 179.44897 | D118: =+IF(B118=B117,"",A118) -> Azar (1994) | E118: =+PERCENTILE($C118:$C120,E$2) -> 233.28366 | F118: =+PERCENTILE($C118:$C120,F$2) -> 448.62243 | G118: =+PERCENTILE($C118:$C120,G$2) -> 717.79589 | H118: =+PERCENTILE($C118:$C120,H$2) -> 1256.1428 | I118: =+PERCENTILE($C118:$C120,I$2) -> 1686.8203 | J118: =+STDEV($C118:$C120) -> 822.3385 | K118: =+IF(I118="","",(G118-E118)/1.96) -> 247.20012 | L118: =+IF(I118="","",(I118-G118)/1.96) -> 494.40023
A119: =+VLOOKUP(B119,studies!$A$2:$C$102,3) -> Azar (1994) | B119: 13 | C119: 717.79589 | D119: =+IF(B119=B118,"",A119) | K119: =+IF(I119="","",(G119-E119)/1.96) | L119: =+IF(I119="","",(I119-G119)/1.96)
A120: =+VLOOKUP(B120,studies!$A$2:$C$102,3) -> Azar (1994) | B120: 13 | C120: 1794.4897 | D120: =+IF(B120=B119,"",A120) | K120: =+IF(I120="","",(G120-E120)/1.96) | L120: =+IF(I120="","",(I120-G120)/1.96)
A121: =+VLOOKUP(B121,studies!$A$2:$C$102,3) -> Fankhauser (1994) | B121: 14 | C121: 46.634123 | D121: =+IF(B121=B120,"",A121) -> Fankhauser (1994) | K121: =+IF(I121="","",(G121-E121)/1.96) | L121: =+IF(I121="","",(I121-G121)/1.96) | M121: 32.256805 | N121: 15.987338 | O121: 29.247424
A122: =+VLOOKUP(B122,studies!$A$2:$C$102,3) -> Nordhaus (1994) | B122: 15 | C122: 17.200864 | D122: =+IF(B122=B121,"",A122) -> Nordhaus (1994) | K122: =+IF(I122="","",(G122-E122)/1.96) | L122: =+IF(I122="","",(I122-G122)/1.96)
A123: =+VLOOKUP(B123,studies!$A$2:$C$102,3) -> Maddison (1995) | B123: 16 | C123: 43.033788 | D123: =+IF(B123=B122,"",A123) -> Maddison (1995) | K123: =+IF(I123="","",(G123-E123)/1.96) | L123: =+IF(I123="","",(I123-G123)/1.96)
A124: =+VLOOKUP(B124,studies!$A$2:$C$102,3) -> Schauer (1995) | B124: 17 | C124: 6.3273708 | D124: =+IF(B124=B123,"",A124) -> Schauer (1995) | F124: =+C124 -> 6.3273708 | G124: =+MEDIAN(C124:C125) -> 99.204776 | H124: =+C125 -> 192.08218 | J124: =+STDEV(C124:C125) -> 131.34849 | K124: =G124-F124/1.1505 -> 93.705105 | L124: =H124-G124/1.1505 -> 105.85465 | M124: 75.942805 | N124: 75.942805 | O124: 75.942805
A125: =+VLOOKUP(B125,studies!$A$2:$C$102,3) -> Schauer (1995) | B125: 17 | C125: 192.08218 | D125: =+IF(B125=B124,"",A125) | K125: =+IF(I125="","",(G125-E125)/1.96) | L125: =+IF(I125="","",(I125-G125)/1.96) | M125: 537.62912 | N125: 537.62912 | O125: 537.62912
A126: =+VLOOKUP(B126,studies!$A$2:$C$102,3) -> Azar & Sterner (1996) | B126: 18 | C126: 305.06325 | D126: =+IF(B126=B125,"",A126) -> Azar & Sterner (1996) | E126: =+PERCENTILE($C126:$C141,E$2) -> 46.656733 | F126: =+PERCENTILE($C126:$C141,F$2) -> 134.58673 | G126: =+PERCENTILE($C126:$C141,G$2) -> 323.00815 | H126: =+PERCENTILE($C126:$C141,H$2) -> 744.71324 | I126: =+PERCENTILE($C126:$C141,I$2) -> 1632.9857 | J126: =+STDEV($C126:$C141) -> 576.86858 | K126: =+IF(I126="","",(G126-E126)/1.96) -> 140.99562 | L126: =+IF(I126="","",(I126-G126)/1.96) -> 668.35587
A127: =+VLOOKUP(B127,studies!$A$2:$C$102,3) -> Azar & Sterner (1996) | B127: 18 | C127: 717.79589 | D127: =+IF(B127=B126,"",A127) | K127: =+IF(I127="","",(G127-E127)/1.96) | L127: =+IF(I127="","",(I127-G127)/1.96)
A128: =+VLOOKUP(B128,studies!$A$2:$C$102,3) -> Azar & Sterner (1996) | B128: 18 | C128: 269.17346 | D128: =+IF(B128=B127,"",A128) | K128: =+IF(I128="","",(G128-E128)/1.96) | L128: =+IF(I128="","",(I128-G128)/1.96)
A129: =+VLOOKUP(B129,studies!$A$2:$C$102,3) -> Azar & Sterner (1996) | B129: 18 | C129: 502.45712 | D129: =+IF(B129=B128,"",A129) | K129: =+IF(I129="","",(G129-E129)/1.96) | L129: =+IF(I129="","",(I129-G129)/1.96)
A130: =+VLOOKUP(B130,studies!$A$2:$C$102,3) -> Azar & Sterner (1996) | B130: 18 | C130: 114.84734 | D130: =+IF(B130=B129,"",A130) | K130: =+IF(I130="","",(G130-E130)/1.96) | L130: =+IF(I130="","",(I130-G130)/1.96)
A131: =+VLOOKUP(B131,studies!$A$2:$C$102,3) -> Azar & Sterner (1996) | B131: 18 | C131: 118.43632 | D131: =+IF(B131=B130,"",A131) | K131: =+IF(I131="","",(G131-E131)/1.96) | L131: =+IF(I131="","",(I131-G131)/1.96)
A132: =+VLOOKUP(B132,studies!$A$2:$C$102,3) -> Azar & Sterner (1996) | B132: 18 | C132: 46.656733 | D132: =+IF(B132=B131,"",A132) | K132: =+IF(I132="","",(G132-E132)/1.96) | L132: =+IF(I132="","",(I132-G132)/1.96)
A133: =+VLOOKUP(B133,studies!$A$2:$C$102,3) -> Azar & Sterner (1996) | B133: 18 | C133: 46.656733 | D133: =+IF(B133=B132,"",A133) | K133: =+IF(I133="","",(G133-E133)/1.96) | L133: =+IF(I133="","",(I133-G133)/1.96)
A134: =+VLOOKUP(B134,studies!$A$2:$C$102,3) -> Azar & Sterner (1996) | B134: 18 | C134: 933.13466 | D134: =+IF(B134=B133,"",A134) | K134: =+IF(I134="","",(G134-E134)/1.96) | L134: =+IF(I134="","",(I134-G134)/1.96)
A135: =+VLOOKUP(B135,studies!$A$2:$C$102,3) -> Azar & Sterner (1996) | B135: 18 | C135: 2117.4979 | D135: =+IF(B135=B134,"",A135) | K135: =+IF(I135="","",(G135-E135)/1.96) | L135: =+IF(I135="","",(I135-G135)/1.96)
A136: =+VLOOKUP(B136,studies!$A$2:$C$102,3) -> Azar & Sterner (1996) | B136: 18 | C136: 825.46527 | D136: =+IF(B136=B135,"",A136) | K136: =+IF(I136="","",(G136-E136)/1.96) | L136: =+IF(I136="","",(I136-G136)/1.96)
A137: =+VLOOKUP(B137,studies!$A$2:$C$102,3) -> Azar & Sterner (1996) | B137: 18 | C137: 1471.4816 | D137: =+IF(B137=B136,"",A137) | K137: =+IF(I137="","",(G137-E137)/1.96) | L137: =+IF(I137="","",(I137-G137)/1.96)
A138: =+VLOOKUP(B138,studies!$A$2:$C$102,3) -> Azar & Sterner (1996) | B138: 18 | C138: 340.95305 | D138: =+IF(B138=B137,"",A138) | K138: =+IF(I138="","",(G138-E138)/1.96) | L138: =+IF(I138="","",(I138-G138)/1.96)
... A141: =+VLOOKUP(B141,studies!$A$2:$C$102,3) -> Azar & Sterner (1996) | B141: 18 | C141: 139.9702 | D141: =+IF(B141=B140,"",A141) | K141: =+IF(I141="","",(G141-E141)/1.96) | L141: =+IF(I141="","",(I141-G141)/1.96)
A142: =+VLOOKUP(B142,studies!$A$2:$C$102,3) -> Downing et al. (1996) | B142: 19 | C142: 164.59456 | D142: =+IF(B142=B141,"",A142) -> Downing et al. (1996) | F142: =+C143 -> 56.349019 | G142: =+MEDIAN(C142:C143) -> 110.47179 | H142: =+C142 -> 164.59456 | J142: =+STDEV(C142:C143) -> 76.541156 | K142: =G142-F142/1.1505 -> 61.493937 | L142: =H142-G142/1.1505 -> 68.573883
A143: =+VLOOKUP(B143,studies!$A$2:$C$102,3) -> Downing et al. (1996) | B143: 19 | C143: 56.349019 | D143: =+IF(B143=B142,"",A143) | K143: =+IF(I143="","",(G143-E143)/1.96) | L143: =+IF(I143="","",(I143-G143)/1.96)
A144: =+VLOOKUP(B144,studies!$A$2:$C$102,3) -> Hohmeyer (1996) | B144: 20 | C144: 2463.3451 | D144: =+IF(B144=B143,"",A144) -> Hohmeyer (1996) | K144: =+IF(I144="","",(G144-E144)/1.96) | L144: =+IF(I144="","",(I144-G144)/1.96)
A145: =+VLOOKUP(B145,studies!$A$2:$C$102,3) -> Hope & Maul (1996) | B145: 21 | C145: 25.122856 | D145: =+IF(B145=B144,"",A145) -> Hope & Maul (1996) | E145: =+PERCENTILE($C145:$C150,E$2) -> 19.739387 | F145: =+PERCENTILE($C145:$C150,F$2) -> 26.917346 | G145: =+PERCENTILE($C145:$C150,G$2) -> 50.245712 | H145: =+PERCENTILE($C145:$C150,H$2) -> 81.649283 | I145: =+PERCENTILE($C145:$C150,I$2) -> 99.59418 | J145: =+STDEV($C145:$C150) -> 35.583424 | K145: =+IF(I145="","",(G145-E145)/1.96) -> 15.564452 | L145: =+IF(I145="","",(I145-G145)/1.96) -> 25.17779 | N145: 7.3244479 | O145: 7.3244479
A146: =+VLOOKUP(B146,studies!$A$2:$C$102,3) -> Hope & Maul (1996) | B146: 21 | C146: 86.135507 | D146: =+IF(B146=B145,"",A146) | K146: =+IF(I146="","",(G146-E146)/1.96) | L146: =+IF(I146="","",(I146-G146)/1.96) | N146: 43.946687 | O146: 450.45354
A147: =+VLOOKUP(B147,studies!$A$2:$C$102,3) -> Hope & Maul (1996) | B147: 21 | C147: 32.300815 | D147: =+IF(B147=B146,"",A147) | K147: =+IF(I147="","",(G147-E147)/1.96) | L147: =+IF(I147="","",(I147-G147)/1.96) | N147: 9.1555598 | O147: 9.1555598
A148: =+VLOOKUP(B148,studies!$A$2:$C$102,3) -> Hope & Maul (1996) | B148: 21 | C148: 68.19061 | D148: =+IF(B148=B147,"",A148) | K148: =+IF(I148="","",(G148-E148)/1.96) | L148: =+IF(I148="","",(I148-G148)/1.96) | N148: 20.142232 | O148: 23.804456
A149: =+VLOOKUP(B149,studies!$A$2:$C$102,3) -> Hope & Maul (1996) | B149: 21 | C149: 17.944897 | D149: =+IF(B149=B148,"",A149) | K149: =+IF(I149="","",(G149-E149)/1.96) | L149: =+IF(I149="","",(I149-G149)/1.96) | N149: 5.4933359 | O149: 3.6622239
A150: =+VLOOKUP(B150,studies!$A$2:$C$102,3) -> Hope & Maul (1996) | B150: 21 | C150: 104.0804 | D150: =+IF(B150=B149,"",A150) | K150: =+IF(I150="","",(G150-E150)/1.96) | L150: =+IF(I150="","",(I150-G150)/1.96) | N150: 31.128903 | O150: 29.297791
A151: =+VLOOKUP(B151,studies!$A$2:$C$102,3) -> Nordhaus & Yang (1996) | B151: 22 | C151: 14.973347 | D151: =+IF(B151=B150,"",A151) -> Nordhaus & Yang (1996) | K151: =+IF(I151="","",(G151-E151)/1.96) | L151: =+IF(I151="","",(I151-G151)/1.96)
A152: =+VLOOKUP(B152,studies!$A$2:$C$102,3) -> Plambeck & Hope (1996) | B152: 23 | C152: 10.766938 | D152: =+IF(B152=B151,"",A152) -> Plambeck & Hope (1996) | E152: =+PERCENTILE($C152:$C159,E$2) -> 13.279224 | F152: =+PERCENTILE($C152:$C159,F$2) -> 26.020101 | G152: =+PERCENTILE($C152:$C159,G$2) -> 52.040202 | H152: =+PERCENTILE($C152:$C159,H$2) -> 127.40877 | I152: =+PERCENTILE($C152:$C159,I$2) -> 1084.2307 | J152: =+STDEV($C152:$C159) -> 538.72598 | K152: =+IF(I152="","",(G152-E152)/1.96) -> 19.776009 | L152: =+IF(I152="","",(I152-G152)/1.96) -> 526.6278 | N152: 3.6622239 | O152: 5.4933359
A153: =+VLOOKUP(B153,studies!$A$2:$C$102,3) -> Plambeck & Hope (1996) | B153: 23 | C153: 17.944897 | D153: =+IF(B153=B152,"",A153) | K153: =+IF(I153="","",(G153-E153)/1.96) | L153: =+IF(I153="","",(I153-G153)/1.96) | N153: 5.4933359 | O153: 12.817784
A154: =+VLOOKUP(B154,studies!$A$2:$C$102,3) -> Plambeck & Hope (1996) | B154: 23 | C154: 28.711836 | D154: =+IF(B154=B153,"",A154) | K154: =+IF(I154="","",(G154-E154)/1.96) | L154: =+IF(I154="","",(I154-G154)/1.96) | N154: 9.1555598 | O154: 7.3244479
A155: =+VLOOKUP(B155,studies!$A$2:$C$102,3) -> Plambeck & Hope (1996) | B155: 23 | C155: 28.711836 | D155: =+IF(B155=B154,"",A155) | K155: =+IF(I155="","",(G155-E155)/1.96) | L155: =+IF(I155="","",(I155-G155)/1.96) | N155: 3.6622239 | O155: 18.31112
A156: =+VLOOKUP(B156,studies!$A$2:$C$102,3) -> Plambeck & Hope (1996) | B156: 23 | C156: 75.368568 | D156: =+IF(B156=B155,"",A156) | K156: =+IF(I156="","",(G156-E156)/1.96) | L156: =+IF(I156="","",(I156-G156)/1.96) | N156: 20.142232 | O156: 49.440023
A157: =+VLOOKUP(B157,studies!$A$2:$C$102,3) -> Plambeck & Hope (1996) | B157: 23 | C157: 165.09305 | D157: =+IF(B157=B156,"",A157) | K157: =+IF(I157="","",(G157-E157)/1.96) | L157: =+IF(I157="","",(I157-G157)/1.96) | N157: 47.608911 | O157: 87.893374
A158: =+VLOOKUP(B158,studies!$A$2:$C$102,3) -> Plambeck & Hope (1996) | B158: 23 | C158: 1579.151 | D158: =+IF(B158=B157,"",A158) | K158: =+IF(I158="","",(G158-E158)/1.96) | L158: =+IF(I158="","",(I158-G158)/1.96) | N158: 91.555598 | O158: 73.244479
A159: =+VLOOKUP(B159,studies!$A$2:$C$102,3) -> Plambeck & Hope (1996) | B159: 23 | C159: 114.84734 | D159: =+IF(B159=B158,"",A159) | K159: =+IF(I159="","",(G159-E159)/1.96) | L159: =+IF(I159="","",(I159-G159)/1.96) | N159: 18.31112 | O159: 43.946687
A160: =+VLOOKUP(B160,studies!$A$2:$C$102,3) -> Cline (1997) | B160: 24 | C160: 231.72507 | D160: =+IF(B160=B159,"",A160) -> Cline (1997) | K160: =+IF(I160="","",(G160-E160)/1.96) | L160: =+IF(I160="","",(I160-G160)/1.96) | M160: 105.29957 | N160: 107.44854 | O160: 107.44854
A161: =+VLOOKUP(B161,studies!$A$2:$C$102,3) -> Nordhaus & Popp (1997) | B161: 25 | C161: 30.750526 | D161: =+IF(B161=B160,"",A161) -> Nordhaus & Popp (1997) | F161: =+C162 -> 13.00931 | G161: =+MEDIAN(C161:C162) -> 21.879918 | H161: =+C161 -> 30.750526 | J161: =+STDEV(C161:C162) -> 12.544934 | K161: =G161-F161/1.1505 -> 10.572391 | L161: =H161-G161/1.1505 -> 11.732779 | M161: 2.063244 | N161: 18.62909 | O161: 35.668284
...

Sheet SCC
D1: Publication year | G1: Dollar | I1: Emission | J1: Weight | L1: Growth 2015 | M1: Median recalc 2015 [$/tC] | N1: Best guess [$/tC] | O1: Mean value [$/tC] | S1: STDEV | T1: STDEV recalc 2015 | U1: STDlow | V1: STDup | W1: Percentile | AF1: Methods | AJ1: Derivation of: | AM1: CDR | AN1: PRTP | AO1: RRA | AP1: growth rate | AQ1: IES | AR1: EW | AS1: EWinPaper | AT1: COV | AU1: Climate | AV1: Period of emission | AX1: Group relation | BA1: Pigou
A2: Author | B2: Author year | C2: ID | E2: Citation | F2: Peer-rev | G2: year | H2: CPI | I2: year | J2: Tol | K2: for growth | L2: =+SUMPRODUCT(L3:L1048576,K3:K1048576)/SUM(K3:K1048576) -> 0.031115085 | P2: SCCmean | Q2: SCCbg | R2: SCCmed | U2: recalc 2015 | V2: recalc 2015 | W2: 0.01 | X2: 0.05 | Y2: 0.1 | Z2: 0.25 | AA2: 0.5 | AB2: 0.75 | AC2: 0.9 | AD2: 0.95 | AE2: 0.99 | AF2: IIE | AG2: MMI | AH2: DIM | AI2: SCE | AJ2: FUND | AK2: DICE/RICE | AL2: PAGE | AM2: [%/year] | AN2: [%/year] | AP2: [%/year] | AU2: sensitivity in °C | AV2: From | AW2: Till | AX2: Hope | AY2: Nordhaus | AZ2: Tol
A3: Nordhaus | B3: =+A3&" "&D3 -> Nordhaus 1982 | C3: 1 | D3: 1982 | E3: Nordhaus, W. (1982): "How Fast Should We Graze the Global Commons?," American Economic Review, American Economic Association 72(2), 242-46. | F3: 1 | G3: 1980 | H3: =LOOKUP(G3,CPI!A$69:A$100,CPI!O$69:O$100) -> 2.6463107 | I3: 1980 | J3: 0.5 | M3: =AA3*H3*(1+$L$2)^(2015-I3) -> 1984.9987 | N3: =70*44/12 -> 256.66667 | O3: =N3 -> 256.66667 | P3: 0 | Q3: 1 | R3: 0 | T3: =IF(OR(M3="",S3=""),"",S3*H3*(1+$L$2)^(2015-I3)) | U3: =+V3 | V3: =+T3 | AA3: =N3 -> 256.66667 | AF3: 1 | AG3: 0 | AH3: 0 | AI3: 0 | AJ3: 0 | AK3: 0 | AL3: 0 | AN3: 1 | AP3: 4 | AR3: 0 | AS3: 0 | AV3: 1980 | AW3: 2005 | AX3: 0 | AY3: 1 | AZ3: 0 | BA3: 0
B4: =+IF(A4="",B3,A4&" "&D4) -> Nordhaus 1982 | C4: =+IF(A4="",C3,C3+1) -> 1 | D4: 1982 | F4: 1 | G4: 1980 | H4: =LOOKUP(G4,CPI!A$69:A$100,CPI!O$69:O$100) -> 2.6463107 | I4: 1980 | J4: 0.5 | M4: =AA4*H4*(1+$L$2)^(2015-I4) -> 283.57124 | N4: =10*44/12 -> 36.666667 | O4: =N4 -> 36.666667 | P4: 0 | Q4: 1 | R4: 0 | T4: =IF(OR(M4="",S4=""),"",S4*H4*(1+$L$2)^(2015-I4)) | U4: =+V4 | V4: =+T4 | AA4: =N4 -> 36.666667 | AF4: 1 | AG4: 0 | AH4: 0 | AI4: 0 | AJ4: 0 | AK4: 0 | AL4: 0 | AN4: 1 | AP4: 1 | AR4: 0 | AS4: 0 | AV4: 1980 | AW4: 2180 | AX4: 0 | AY4: 1 | AZ4: 0 | BA4: 0
A5: Ayres & Walter | B5: =+IF(A5="",B4,A5&" "&D5) -> Ayres & Walter 1991 | C5: =+IF(A5="",C4,C4+1) -> 2 | D5: 1991 | E5: Ayres, R.U. and J. Walter (1991): "The Greenhouse Effect: Damages, Costs and Abatement," Environmental and Resource Economics 1(3), 237-270. | F5: 1 | G5: 1989 | H5: =LOOKUP(G5,CPI!A$69:A$100,CPI!O$69:O$100) -> 1.7585161 | I5: 1990 | J5: 1 | M5: =AA5*H5*(1+$L$2)^(2015-I5) -> 450.7956 | N5: =(30+35)/2*44/12 -> 119.16667 | O5: =N5 -> 119.16667 | P5: 0 | Q5: 1 | R5: 0 | T5: =IF(OR(M5="",S5=""),"",S5*H5*(1+$L$2)^(2015-I5)) | U5: =+V5 | V5: =+T5 | AA5: =N5 -> 119.16667 | AF5: 1 | AG5: 0 | AH5: 0 | AI5: 0 | AJ5: 0 | AK5: 0 | AL5: 0 | AM5: 3 | AN5: 1 | AP5: 0 | AR5: 0 | AS5: 0 | AV5: 1990 | AW5: =+AV5+50 -> 2040 | AX5: 0 | AY5: 0 | AZ5: 0 | BA5: 0
A6: Nordhaus | B6: =+IF(A6="",B5,A6&" "&D6) -> Nordhaus 1991 | C6: =+IF(A6="",C5,C5+1) -> 3 | D6: 1991 | E6: Nordhaus, W.D. (1991): "To Slow or Not to Slow: The Economics of the Greenhouse Effect," Economic Journal 101(407), 920-937. | F6: 1 | G6: 1989 | H6: =LOOKUP(G6,CPI!A$69:A$100,CPI!O$69:O$100) -> 1.7585161 | I6: 1990 | J6: =1/16 -> 0.0625 | M6: =AA6*H6*(1+$L$2)^(2015-I6) -> 914.62959 | N6: =65.94*44/12 -> 241.78 | O6: =N6 -> 241.78 | P6: 0 | Q6: 1 | R6: 0 | T6: =IF(OR(M6="",S6=""),"",S6*H6*(1+$L$2)^(2015-I6)) | U6: =+V6 | V6: =+T6 | AA6: =N6 -> 241.78 | AF6: 1 | AG6: 0 | AH6: 0 | AI6: 0 | AJ6: 0 | AK6: 1 | AL6: 0 | AM6: 1 | AN6: 0 | AO6: 1 | AP6: =+AM6-AN6 -> 1 | AR6: 0 | AS6: 0 | AX6: 0 | AY6: 1 | AZ6: 0 | BA6: 0
B7: =+IF(A7="",B6,A7&" "&D7) -> Nordhaus 1991 | C7: =+IF(A7="",C6,C6+1) -> 3 | D7: 1991 | F7: 1 | G7: 1989 | H7: =LOOKUP(G7,CPI!A$69:A$100,CPI!O$69:O$100) -> 1.7585161 | I7: 1990 | J7: =2/16 -> 0.125 | M7: =AA7*H7*(1+$L$2)^(2015-I7) -> 457.31479 | N7: =32.97*44/12 -> 120.89 | O7: =N7 -> 120.89 | P7: 0 | Q7: 1 | R7: 0 | T7: =IF(OR(M7="",S7=""),"",S7*H7*(1+$L$2)^(2015-I7)) | U7: =+V7 | V7: =+T7 | AA7: =N7 -> 120.89 | AF7: 1 | AG7: 0 | AH7: 0 | AI7: 0 | AJ7: 0 | AK7: 1 | AL7: 0 | AM7: 1 | AN7: 0 | AO7: 1 | AP7: =+AM7-AN7 -> 1 | AR7: 0 | AS7: 0 | AX7: 0 | AY7: 1 | AZ7: 0 | BA7: 0
B8: =+IF(A8="",B7,A8&" "&D8) -> Nordhaus 1991 | C8: =+IF(A8="",C7,C7+1) -> 3 | D8: 1991 | F8: 1 | G8: 1989 | H8: =LOOKUP(G8,CPI!A$69:A$100,CPI!O$69:O$100) -> 1.7585161 | I8: 1990 | J8: =1/16 -> 0.0625 | M8: =AA8*H8*(1+$L$2)^(2015-I8) -> 114.29402 | N8: =8.24*44/12 -> 30.213333 | O8: =N8 -> 30.213333 | P8: 0 | Q8: 1 | R8: 0 | T8: =IF(OR(M8="",S8=""),"",S8*H8*(1+$L$2)^(2015-I8)) | U8: =+V8 | V8: =+T8 | AA8: =N8 -> 30.213333 | AF8: 1 | AG8: 0 | AH8: 0 | AI8: 0 | AJ8: 0 | AK8: 1 | AL8: 0 | AM8: 1 | AN8: 0 | AO8: 1 | AP8: =+AM8-AN8 -> 1 | AR8: 0 | AS8: 0 | AX8: 0 | AY8: 1 | AZ8: 0 | BA8: 0
B9: =+IF(A9="",B8,A9&" "&D9) -> Nordhaus 1991 | C9: =+IF(A9="",C8,C8+1) -> 3 | D9: 1991 | F9: 1 | G9: 1989 | H9: =LOOKUP(G9,CPI!A$69:A$100,CPI!O$69:O$100) -> 1.7585161 | I9: 1990 | J9: =2/16 -> 0.125 | M9: =AA9*H9*(1+$L$2)^(2015-I9) -> 203.20478 | N9: =14.65*44/12 -> 53.716667 | O9: =N9 -> 53.716667 | P9: 0 | Q9: 1 | R9: 0 | T9: =IF(OR(M9="",S9=""),"",S9*H9*(1+$L$2)^(2015-I9)) | U9: =+V9 | V9: =+T9 | AA9: =N9 -> 53.716667 | AF9: 1 | AG9: 0 | AH9: 0 | AI9: 0 | AJ9: 0 | AK9: 1 | AL9: 0 | AM9: 3 | AN9: 1 | AO9: 1 | AP9: =+AM9-AN9 -> 2 | AR9: 0 | AS9: 0 | AX9: 0 | AY9: 1 | AZ9: 0 | BA9: 0
B10: =+IF(A10="",B9,A10&" "&D10) -> Nordhaus 1991 | C10: =+IF(A10="",C9,C9+1) -> 3 | D10: 1991 | F10: 1 | G10: 1989 | H10: =LOOKUP(G10,CPI!A$69:A$100,CPI!O$69:O$100) -> 1.7585161 | I10: 1990 | J10: =4/16 -> 0.25 | M10: =AA10*H10*(1+$L$2)^(2015-I10) -> 101.67175 | N10: =7.33*44/12 -> 26.876667 | O10: =N10 -> 26.876667 | P10: 0 | Q10: 1 | R10: 0 | T10: =IF(OR(M10="",S10=""),"",S10*H10*(1+$L$2)^(2015-I10)) | U10: =+V10 | V10: =+T10 | AA10: =N10 -> 26.876667 | AF10: 1 | AG10: 0 | AH10: 0 | AI10: 0 | AJ10: 0 | AK10: 1 | AL10: 0 | AM10: 3 | AN10: 1 | AO10: 1 | AP10: =+AM10-AN10 -> 2 | AR10: 0 | AS10: 0 | AX10: 0 | AY10: 1 | AZ10: 0 | BA10: 0
B11: =+IF(A11="",B10,A11&" "&D11) -> Nordhaus 1991 | C11: =+IF(A11="",C10,C10+1) -> 3 | D11: 1991 | F11: 1 | G11: 1989 | H11: =LOOKUP(G11,CPI!A$69:A$100,CPI!O$69:O$100) -> 1.7585161 | I11: 1990 | J11: =2/16 -> 0.125 | M11: =AA11*H11*(1+$L$2)^(2015-I11) -> 25.38326 | N11: =1.83*44/12 -> 6.71 | O11: =N11 -> 6.71 | P11: 0 | Q11: 1 | R11: 0 | T11: =IF(OR(M11="",S11=""),"",S11*H11*(1+$L$2)^(2015-I11)) | U11: =+V11 | V11: =+T11 | AA11: =N11 -> 6.71 | AF11: 1 | AG11: 0 | AH11: 0 | AI11: 0 | AJ11: 0 | AK11: 1 | AL11: 0 | AM11: 3 | AN11: 1 | AO11: 1 | AP11: =+AM11-AN11 -> 2 | AR11: 0 | AS11: 0 | AX11: 0 | AY11: 1 | AZ11: 0 | BA11: 0
B12: =+IF(A12="",B11,A12&" "&D12) -> Nordhaus 1991 | C12: =+IF(A12="",C11,C11+1) -> 3 | D12: 1991 | F12: 1 | G12: 1989 | H12: =LOOKUP(G12,CPI!A$69:A$100,CPI!O$69:O$100) -> 1.7585161 | I12: 1990 | J12: =1/16 -> 0.0625 | M12: =AA12*H12*(1+$L$2)^(2015-I12) -> 33.844346 | N12: =2.44*44/12 -> 8.9466667 | O12: =N12 -> 8.9466667 | P12: 0 | Q12: 1 | R12: 0 | T12: =IF(OR(M12="",S12=""),"",S12*H12*(1+$L$2)^(2015-I12)) | U12: =+V12 | V12: =+T12 | AA12: =N12 -> 8.9466667 | AF12: 1 | AG12: 0 | AH12: 0 | AI12: 0 | AJ12: 0 | AK12: 1 | AL12: 0 | AM12: 7 | AN12: 4 | AO12: =+(AM12-AN12)/AP12 -> 1 | AP12: 3 | AR12: 0 | AS12: 0 | AX12: 0 | AY12: 1 | AZ12: 0 | BA12: 0
B13: =+IF(A13="",B12,A13&" "&D13) -> Nordhaus 1991 | C13: =+IF(A13="",C12,C12+1) -> 3 | D13: 1991 | F13: 1 | G13: 1989 | H13: =LOOKUP(G13,CPI!A$69:A$100,CPI!O$69:O$100) -> 1.7585161 | I13: 1990 | J13: =2/16 -> 0.125 | M13: =AA13*H13*(1+$L$2)^(2015-I13) -> 16.922173 | N13: =1.22*44/12 -> 4.4733333 | O13: =N13 -> 4.4733333 | P13: 0 | Q13: 1 | R13: 0 | T13: =IF(OR(M13="",S13=""),"",S13*H13*(1+$L$2)^(2015-I13)) | U13: =+V13 | V13: =+T13 | AA13: =N13 -> 4.4733333 | AF13: 1 | AG13: 0 | AH13: 0 | AI13: 0 | AJ13: 0 | AK13: 1 | AL13: 0 | AM13: 7 | AN13: 4 | AO13: =+(AM13-AN13)/AP13 -> 1 | AP13: 3 | AR13: 0 | AS13: 0 | AX13: 0 | AY13: 1 | AZ13: 0 | BA13: 0
B14: =+IF(A14="",B13,A14&" "&D14) -> Nordhaus 1991 | C14: =+IF(A14="",C13,C13+1) -> 3 | D14: 1991 | F14: 1 | G14: 1989 | H14: =LOOKUP(G14,CPI!A$69:A$100,CPI!O$69:O$100) -> 1.7585161 | I14: 1990 | J14: =1/16 -> 0.0625 | M14: =AA14*H14*(1+$L$2)^(2015-I14) -> 4.2998965 | N14: =0.31*44/12 -> 1.1366667 | O14: =N14 -> 1.1366667 | P14: 0 | Q14: 1 | R14: 0 | T14: =IF(OR(M14="",S14=""),"",S14*H14*(1+$L$2)^(2015-I14)) | U14: =+V14 | V14: =+T14 | AA14: =N14 -> 1.1366667 | AF14: 1 | AG14: 0 | AH14: 0 | AI14: 0 | AJ14: 0 | AK14: 1 | AL14: 0 | AM14: 7 | AN14: 4 | AO14: =+(AM14-AN14)/AP14 -> 1 | AP14: 3 | AR14: 0 | AS14: 0 | AX14: 0 | AY14: 1 | AZ14: 0 | BA14: 0
A15: Cline | B15: =+IF(A15="",B14,A15&" "&D15) -> Cline 1992 | C15: =+IF(A15="",C14,C14+1) -> 4 | D15: 1992 | E15: Cline, W.R. (1992), Optimal Carbon Emissions over Time: Experiments with the Nordhaus DICE Model ,Institute for International Economics, Washington, D.C. ----l ---------------------Cline, W.R. (1992): The Economics of Global Warming, Institute for International Economics, Washington, D.C. | F15: 0 | G15: 1989 | H15: =LOOKUP(G15,CPI!A$69:A$100,CPI!O$69:O$100) -> 1.7585161 | I15: 1990 | J15: 1 | M15: =AA15*H15*(1+$L$2)^(2015-I15) -> 245.51022 | N15: =(X15+AD15)/2 -> 64.9 | O15: =N15 -> 64.9 | P15: 0 | Q15: 1 | R15: 0 | S15: =(AA15-X15)/2 -> 29.55 | T15: =IF(OR(M15="",S15=""),"",S15*H15*(1+$L$2)^(2015-I15)) -> 111.7847 | U15: =+(AA15-X15)/1.96*H15*(1+$L$2)^(2015-I15) -> 114.06602 | V15: =+(AD15-AA15)/1.96*H15*(1+$L$2)^(2015-I15) -> 114.06602 | X15: 5.8 | AA15: =N15 -> 64.9 | AD15: 124 | AF15: 1 | AG15: 1 | AH15: 0 | AI15: 1 | AJ15: 0 | AK15: 0 | AL15: 0 | AM15: 1.5 | AN15: 0 | AO15: 1.5 | AP15: 1 | AR15: 0 | AS15: 0 | AX15: 0 | AY15: 0 | AZ15: 0 | BA15: 0
A16: Haraden | B16: =+IF(A16="",B15,A16&" "&D16) -> Haraden 1992 | C16: =+IF(A16="",C15,C15+1) -> 5 | D16: 1992 | E16: Haraden, J. (1992): "An improved shadow price for CO2," Energy 17(5), 419-426. | F16: 1 | G16: 1984 | H16: =LOOKUP(G16,CPI!A$69:A$100,CPI!O$69:O$100) -> 2.0987103 | I16: 1987 | J16: 1 | K16: 1 | L16: =(AA17/AA16)^(1/(I17-I16))-1 -> 0.041349897 | M16: =AA16*H16*(1+$L$2)^(2015-I16) -> 72.59118 | N16: =4*44/12 -> 14.666667 | O16: =N16 -> 14.666667 | P16: 0 | Q16: 1 | R16: 0 | T16: =IF(OR(M16="",S16=""),"",S16*H16*(1+$L$2)^(2015-I16)) | U16: =+V16 | V16: =+T16 | AA16: =N16 -> 14.666667 | AF16: 1 | AG16: 0 | AH16: 0 | AI16: 0 | AJ16: 0 | AK16: 0 | AL16: 0 | AM16: 4 | AN16: 2 | AO16: =+(AM16-AN16)/AP16 -> 1 | AP16: 2 | AR16: 0 | AS16: 0 | AV16: 1987 | AX16: 0 | AY16: 0 | AZ16: 0 | BA16: 0
B17: =+IF(A17="",B16,A17&" "&D17) -> Haraden 1992 | C17: =+IF(A17="",C16,C16+1) -> 5 | D17: 1992 | F17: 1 | G17: 1984 | H17: =LOOKUP(G17,CPI!A$69:A$100,CPI!O$69:O$100) -> 2.0987103 | I17: 2087 | J17: 0 | N17: =230*44/12 -> 843.33333 | O17: =N17 -> 843.33333 | P17: 0 | Q17: 1 | R17: 0 | T17: =IF(OR(M17="",S17=""),"",S17*H17*(1+$L$2)^(2015-I17)) | U17: =+V17 | V17: =+T17 | AA17: =N17 -> 843.33333 | AF17: 1 | AG17: 0 | AH17: 0 | AI17: 0 | AJ17: 0 | AK17: 0 | AL17: 0 | AM17: 4 | AN17: 2 | AO17: =+(AM17-AN17)/AP17 -> 1 | AP17: 2 | AR17: 0 | AS17: 0 | AV17: 2087 | AX17: 0 | AY17: 0 | AZ17: 0 | BA17: 0
A18: Hohmeyer & Gaertner | B18: =+IF(A18="",B17,A18&" "&D18) -> Hohmeyer & Gaertner 1992 | C18: =+IF(A18="",C17,C17+1) -> 6 | D18: 1992 | E18: Hohmeyer, O. and M.Gaertner (1992), The Costs of Climate Change - A Rough Estimate of Orders of Magnitude, Fraunhofer-Institut fur Systemtechnik und Innovationsforschung, Karlsruhe. | F18: 0 | G18: 1990 | H18: =LOOKUP(G18,CPI!A$69:A$100,CPI!O$69:O$100) -> 1.6683703 | I18: 1990 | J18: 1 | M18: =AA18*H18*(1+$L$2)^(2015-I18) -> 6383.0401 | N18: =485/0.2727 -> 1778.5112 | O18: =N18 -> 1778.5112 | P18: 0 | Q18: 1 | R18: 0 | T18: =IF(OR(M18="",S18=""),"",S18*H18*(1+$L$2)^(2015-I18)) | U18: =+V18 | V18: =+T18 | AA18: =N18 -> 1778.5112 | AF18: 1 | AG18: 0 | AH18: 0 | AI18: 1 | AJ18: 0 | AK18: 0 | AL18: 0 | AM18: 0 | AN18: 2 | AR18: 0 | AS18: 0 | AX18: 0 | AY18: 0 | AZ18: 0 | BA18: 0
A19: Penner et al. | B19: =+IF(A19="",B18,A19&" "&D19) -> Penner et al. 1992 | C19: =+IF(A19="",C18,C18+1) -> 7 | D19: 1992 | E19: Penner, S.S., J.Haraden, and S.Mates (1992), 'Long-term global energy supplies with acceptable environmental impacts', Energy, 17, (10), pp. 883-899. | F19: 1 | G19: 1989 | H19: =LOOKUP(G19,CPI!A$69:A$100,CPI!O$69:O$100) -> 1.7585161 | I19: 1989 | J19: 0.25 | M19: =AA19*H19*(1+$L$2)^(2015-I19) -> 65.023092 | N19: 16.67 | O19: =N19 -> 16.67 | P19: 0 | Q19: 1 | R19: 0 | T19: =IF(OR(M19="",S19=""),"",S19*H19*(1+$L$2)^(2015-I19)) | U19: =+V19 | V19: =+T19 | AA19: =N19 -> 16.67 | AF19: 0 | AG19: 0 | AH19: 0 | AI19: 0 | AJ19: 0 | AK19: 1 | AL19: 0 | AM19: 4 | AN19: 2 | AR19: 0 | AS19: 0 | AX19: 0 | AY19: 0 | AZ19: 0 | BA19: 0
A20: Haradan | B20: =+IF(A20="",B19,A20&" "&D20) -> Haradan 1993 | C20: =+IF(A20="",C19,C19+1) -> 8 | D20: 1993 | E20: Haraden, J. 1993. ʻAn updated shadow price for CO2ʼ. Energy 18(3): 303–307 | F20: 1 | G20: 1989 | H20: =LOOKUP(G20,CPI!A$69:A$100,CPI!O$69:O$100) -> 1.7585161 | I20: 1989 | J20: 0.25 | K20: 0.33333333 | L20: =(AA21/AA20)^(1/(I21-I20))-1 -> 0.015822032 | M20: =AA20*H20*(1+$L$2)^(2015-I20) -> 7.2161199 | N20: 1.85 | O20: =N20 -> 1.85 | P20: 0 | Q20: 1 | R20: 0 | T20: =IF(OR(M20="",S20=""),"",S20*H20*(1+$L$2)^(2015-I20)) | U20: =+V20 | V20: =+T20 | AA20: =N20 -> 1.85 | AF20: 0 | AG20: 0 | AH20: 0 | AI20: 0 | AJ20: 0 | AK20: 0 | AL20: 0 | AM20: 4 | AN20: 2 | AO20: =+(AM20-AN20)/AP20 -> 1.25 | AP20: 1.6 | AR20: 0 | AS20: 0 | AX20: 0 | AY20: 0 | AZ20: 0 | BA20: 0
B21: =+IF(A21="",B20,A21&" "&D21) -> Haradan 1993 | C21: =+IF(A21="",C20,C20+1) -> 8 | D21: 1993 | F21: 1 | G21: 1989 | H21: =LOOKUP(G21,CPI!A$69:A$100,CPI!O$69:O$100) -> 1.7585161 | I21: 2050 | J21: 0 | N21: 4.82 | O21: =N21 -> 4.82 | P21: 0 | Q21: 1 | R21: 0 | T21: =IF(OR(M21="",S21=""),"",S21*H21*(1+$L$2)^(2015-I21)) | U21: =+V21 | V21: =+T21 | AA21: =N21 -> 4.82 | AF21: 0 | AG21: 0 | AH21: 0 | AI21: 0 | AJ21: 0 | AK21: 0 | AL21: 0 | AM21: 4 | AN21: 2 | AO21: =+(AM21-AN21)/AP21 -> 1.25 | AP21: 1.6 | AR21: 0 | AS21: 0 | AX21: 0 | AY21: 0 | AZ21: 0 | BA21: 0
B22: =+IF(A22="",B21,A22&" "&D22) -> Haradan 1993 | C22: =+IF(A22="",C21,C21+1) -> 8 | D22: 1993 | F22: 1 | G22: 1989 | H22: =LOOKUP(G22,CPI!A$69:A$100,CPI!O$69:O$100) -> 1.7585161 | I22: 1989 | J22: 0.5 | K22: 0.33333333 | L22: =(AA23/AA22)^(1/(I23-I22))-1 -> 0.021425697 | M22: =AA22*H22*(1+$L$2)^(2015-I22) -> 11.623804 | N22: 2.98 | O22: =N22 -> 2.98 | P22: 0 | Q22: 1 | R22: 0 | T22: =IF(OR(M22="",S22=""),"",S22*H22*(1+$L$2)^(2015-I22)) | U22: =+V22 | V22: =+T22 | AA22: =N22 -> 2.98 | AF22: 0 | AG22: 0 | AH22: 0 | AI22: 0 | AJ22: 0 | AK22: 0 | AL22: 0 | AM22: 4 | AN22: 2 | AO22: =+(AM22-AN22)/AP22 -> 0.86956522 | AP22: 2.3 | AR22: 0 | AS22: 0 | AX22: 0 | AY22: 0 | AZ22: 0 | BA22: 0
B23: =+IF(A23="",B22,A23&" "&D23) -> Haradan 1993 | C23: =+IF(A23="",C22,C22+1) -> 8 | D23: 1993 | F23: 1 | G23: 1989 | H23: =LOOKUP(G23,CPI!A$69:A$100,CPI!O$69:O$100) -> 1.7585161 | I23: 2050 | J23: 0 | N23: 10.86 | O23: =N23 -> 10.86 | P23: 0 | Q23: 1 | R23: 0 | T23: =IF(OR(M23="",S23=""),"",S23*H23*(1+$L$2)^(2015-I23)) | U23: =+V23 | V23: =+T23 | AA23: =N23 -> 10.86 | AF23: 0 | AG23: 0 | AH23: 0 | AI23: 0 | AJ23: 0 | AK23: 0 | AL23: 0 | AM23: 4 | AN23: 2 | AO23: =+(AM23-AN23)/AP23 -> 0.86956522 | AP23: 2.3 | AR23: 0 | AS23: 0 | AX23: 0 | AY23: 0 | AZ23: 0 | BA23: 0
B24: =+IF(A24="",B23,A24&" "&D24) -> Haradan 1993 | C24: =+IF(A24="",C23,C23+1) -> 8 | D24: 1993 | F24: 1 | G24: 1989 | H24: =LOOKUP(G24,CPI!A$69:A$100,CPI!O$69:O$100) -> 1.7585161 | I24: 1989 | J24: 0.25 | K24: 0.33333333 | L24: =(AA25/AA24)^(1/(I25-I24))-1 -> 0.025145402 | M24: =AA24*H24*(1+$L$2)^(2015-I24) -> 34.247315 | N24: 8.78 | O24: =N24 -> 8.78 | P24: 0 | Q24: 1 | R24: 0 | T24: =IF(OR(M24="",S24=""),"",S24*H24*(1+$L$2)^(2015-I24)) | U24: =+V24 | V24: =+T24 | AA24: =N24 -> 8.78 | AF24: 0 | AG24: 0 | AH24: 0 | AI24: 0 | AJ24: 0 | AK24: 0 | AL24: 0 | AM24: 4 | AN24: 2 | AO24: =+(AM24-AN24)/AP24 -> 0.5 | AP24: 4 | AR24: 0 | AS24: 0 | AX24: 0 | AY24: 0 | AZ24: 0 | BA24: 0
