Workbook

Sheet bma
A1: =+#REF! -> #REF! | B1: =+#REF! -> #REF! | C1: =+#REF! -> #REF! | D1: =+#REF! -> #REF! | E1: =+#REF! -> #REF! | F1: =+#REF! -> #REF! | G1: =+#REF! -> #REF! | H1: =+#REF! -> #REF! | ... N1: =+#REF! -> #REF! | O1: public | P1: =+#REF! -> #REF! | Q1: =+#REF! -> #REF! | R1: =+#REF! -> #REF! | S1: =+#REF! -> #REF!
A2: =+#REF! -> #REF! | B2: =+#REF! -> #REF! | C2: =+#REF! -> #REF! | D2: =+#REF! -> #REF! | E2: =+#REF! -> #REF! | F2: =+#REF! -> #REF! | G2: =+#REF! -> #REF! | H2: =+#REF! -> #REF! | ... S2: =+#REF! -> #REF!
A3: =+#REF! -> #REF! | B3: =+#REF! -> #REF! | C3: =+#REF! -> #REF! | D3: =+#REF! -> #REF! | E3: =+#REF! -> #REF! | F3: =+#REF! -> #REF! | G3: =+#REF! -> #REF! | H3: =+#REF! -> #REF! | ... S3: =+#REF! -> #REF!
A4: =+#REF! -> #REF! | B4: =+#REF! -> #REF! | C4: =+#REF! -> #REF! | D4: =+#REF! -> #REF! | E4: =+#REF! -> #REF! | F4: =+#REF! -> #REF! | G4: =+#REF! -> #REF! | H4: =+#REF! -> #REF! | ... S4: =+#REF! -> #REF!
A5: =+#REF! -> #REF! | B5: =+#REF! -> #REF! | C5: =+#REF! -> #REF! | D5: =+#REF! -> #REF! | E5: =+#REF! -> #REF! | F5: =+#REF! -> #REF! | G5: =+#REF! -> #REF! | H5: =+#REF! -> #REF! | ... S5: =+#REF! -> #REF!
A6: =+#REF! -> #REF! | B6: =+#REF! -> #REF! | C6: =+#REF! -> #REF! | D6: =+#REF! -> #REF! | E6: =+#REF! -> #REF! | F6: =+#REF! -> #REF! | G6: =+#REF! -> #REF! | H6: =+#REF! -> #REF! | ... S6: =+#REF! -> #REF!
A7: =+#REF! -> #REF! | B7: =+#REF! -> #REF! | C7: =+#REF! -> #REF! | D7: =+#REF! -> #REF! | E7: =+#REF! -> #REF! | F7: =+#REF! -> #REF! | G7: =+#REF! -> #REF! | H7: =+#REF! -> #REF! | ... S7: =+#REF! -> #REF!
A8: =+#REF! -> #REF! | B8: =+#REF! -> #REF! | C8: =+#REF! -> #REF! | D8: =+#REF! -> #REF! | E8: =+#REF! -> #REF! | F8: =+#REF! -> #REF! | G8: =+#REF! -> #REF! | H8: =+#REF! -> #REF! | ... S8: =+#REF! -> #REF!
A9: =+#REF! -> #REF! | B9: =+#REF! -> #REF! | C9: =+#REF! -> #REF! | D9: =+#REF! -> #REF! | E9: =+#REF! -> #REF! | F9: =+#REF! -> #REF! | G9: =+#REF! -> #REF! | H9: =+#REF! -> #REF! | ... S9: =+#REF! -> #REF!
A10: =+#REF! -> #REF! | B10: =+#REF! -> #REF! | C10: =+#REF! -> #REF! | D10: =+#REF! -> #REF! | E10: =+#REF! -> #REF! | F10: =+#REF! -> #REF! | G10: =+#REF! -> #REF! | H10: =+#REF! -> #REF! | ... S10: =+#REF! -> #REF!
A11: =+#REF! -> #REF! | B11: =+#REF! -> #REF! | C11: =+#REF! -> #REF! | D11: =+#REF! -> #REF! | E11: =+#REF! -> #REF! | F11: =+#REF! -> #REF! | G11: =+#REF! -> #REF! | H11: =+#REF! -> #REF! | ... S11: =+#REF! -> #REF!
A12: =+#REF! -> #REF! | B12: =+#REF! -> #REF! | C12: =+#REF! -> #REF! | D12: =+#REF! -> #REF! | E12: =+#REF! -> #REF! | F12: =+#REF! -> #REF! | G12: =+#REF! -> #REF! | H12: =+#REF! -> #REF! | ... S12: =+#REF! -> #REF!
A13: =+#REF! -> #REF! | B13: =+#REF! -> #REF! | C13: =+#REF! -> #REF! | D13: =+#REF! -> #REF! | E13: =+#REF! -> #REF! | F13: =+#REF! -> #REF! | G13: =+#REF! -> #REF! | H13: =+#REF! -> #REF! | ... S13: =+#REF! -> #REF!
... A443: =+#REF! -> #REF! | B443: =+#REF! -> #REF! | C443: =+#REF! -> #REF! | D443: =+#REF! -> #REF! | E443: =+#REF! -> #REF! | F443: =+#REF! -> #REF! | G443: =+#REF! -> #REF! | H443: =+#REF! -> #REF! | ... S443: =+#REF! -> #REF!

Sheet bma_se
A1: =+#REF! -> #REF! | B1: =+#REF! -> #REF! | C1: =+bma!C1 -> #REF! | D1: =+bma!D1 -> #REF! | E1: =+bma!E1 -> #REF! | F1: =+bma!F1 -> #REF! | G1: =+bma!G1 -> #REF! | H1: =+bma!H1 -> #REF! | I1: =+bma!I1 -> #REF! | J1: =+bma!L1 -> #REF! | K1: =+bma!M1 -> #REF! | L1: =+bma!J1 -> #REF! | M1: =+bma!K1 -> #REF! | N1: =+bma!N1 -> #REF! | O1: =+bma!O1 -> public | P1: =+bma!P1 -> #REF! | Q1: =+bma!Q1 -> #REF! | R1: =+bma!R1 -> #REF! | S1: =+bma!S1 -> #REF!
A2: =+#REF! -> #REF! | B2: =+#REF! -> #REF! | C2: =+bma!C2/#REF! -> #REF! | D2: =+bma!D2/#REF! -> #REF! | E2: =+bma!E2/#REF! -> #REF! | F2: =+bma!F2/#REF! -> #REF! | G2: =+bma!G2/#REF! -> #REF! | H2: =+bma!H2/#REF! -> #REF! | I2: =+bma!I2/#REF! -> #REF! | J2: =+bma!L2/#REF! -> #REF! | K2: =+bma!M2/#REF! -> #REF! | L2: =+bma!J2/#REF! -> #REF! | M2: =+bma!K2/#REF! -> #REF! | N2: =+bma!N2/#REF! -> #REF! | O2: =+bma!O2/#REF! -> #REF! | P2: =+bma!P2/#REF! -> #REF! | Q2: =+bma!Q2/#REF! -> #REF! | R2: =+bma!R2/#REF! -> #REF! | S2: =+bma!S2/#REF! -> #REF!
A3: =+#REF! -> #REF! | B3: =+#REF! -> #REF! | C3: =+bma!C3/#REF! -> #REF! | D3: =+bma!D3/#REF! -> #REF! | E3: =+bma!E3/#REF! -> #REF! | F3: =+bma!F3/#REF! -> #REF! | G3: =+bma!G3/#REF! -> #REF! | H3: =+bma!H3/#REF! -> #REF! | I3: =+bma!I3/#REF! -> #REF! | J3: =+bma!L3/#REF! -> #REF! | K3: =+bma!M3/#REF! -> #REF! | L3: =+bma!J3/#REF! -> #REF! | M3: =+bma!K3/#REF! -> #REF! | N3: =+bma!N3/#REF! -> #REF! | O3: =+bma!O3/#REF! -> #REF! | P3: =+bma!P3/#REF! -> #REF! | Q3: =+bma!Q3/#REF! -> #REF! | R3: =+bma!R3/#REF! -> #REF! | S3: =+bma!S3/#REF! -> #REF!
A4: =+#REF! -> #REF! | B4: =+#REF! -> #REF! | C4: =+bma!C4/#REF! -> #REF! | D4: =+bma!D4/#REF! -> #REF! | E4: =+bma!E4/#REF! -> #REF! | F4: =+bma!F4/#REF! -> #REF! | G4: =+bma!G4/#REF! -> #REF! | H4: =+bma!H4/#REF! -> #REF! | I4: =+bma!I4/#REF! -> #REF! | J4: =+bma!L4/#REF! -> #REF! | K4: =+bma!M4/#REF! -> #REF! | L4: =+bma!J4/#REF! -> #REF! | M4: =+bma!K4/#REF! -> #REF! | N4: =+bma!N4/#REF! -> #REF! | O4: =+bma!O4/#REF! -> #REF! | P4: =+bma!P4/#REF! -> #REF! | Q4: =+bma!Q4/#REF! -> #REF! | R4: =+bma!R4/#REF! -> #REF! | S4: =+bma!S4/#REF! -> #REF!
A5: =+#REF! -> #REF! | B5: =+#REF! -> #REF! | C5: =+bma!C5/#REF! -> #REF! | D5: =+bma!D5/#REF! -> #REF! | E5: =+bma!E5/#REF! -> #REF! | F5: =+bma!F5/#REF! -> #REF! | G5: =+bma!G5/#REF! -> #REF! | H5: =+bma!H5/#REF! -> #REF! | I5: =+bma!I5/#REF! -> #REF! | J5: =+bma!L5/#REF! -> #REF! | K5: =+bma!M5/#REF! -> #REF! | L5: =+bma!J5/#REF! -> #REF! | M5: =+bma!K5/#REF! -> #REF! | N5: =+bma!N5/#REF! -> #REF! | O5: =+bma!O5/#REF! -> #REF! | P5: =+bma!P5/#REF! -> #REF! | Q5: =+bma!Q5/#REF! -> #REF! | R5: =+bma!R5/#REF! -> #REF! | S5: =+bma!S5/#REF! -> #REF!
A6: =+#REF! -> #REF! | B6: =+#REF! -> #REF! | C6: =+bma!C6/#REF! -> #REF! | D6: =+bma!D6/#REF! -> #REF! | E6: =+bma!E6/#REF! -> #REF! | F6: =+bma!F6/#REF! -> #REF! | G6: =+bma!G6/#REF! -> #REF! | H6: =+bma!H6/#REF! -> #REF! | I6: =+bma!I6/#REF! -> #REF! | J6: =+bma!L6/#REF! -> #REF! | K6: =+bma!M6/#REF! -> #REF! | L6: =+bma!J6/#REF! -> #REF! | M6: =+bma!K6/#REF! -> #REF! | N6: =+bma!N6/#REF! -> #REF! | O6: =+bma!O6/#REF! -> #REF! | P6: =+bma!P6/#REF! -> #REF! | Q6: =+bma!Q6/#REF! -> #REF! | R6: =+bma!R6/#REF! -> #REF! | S6: =+bma!S6/#REF! -> #REF!
A7: =+#REF! -> #REF! | B7: =+#REF! -> #REF! | C7: =+bma!C7/#REF! -> #REF! | D7: =+bma!D7/#REF! -> #REF! | E7: =+bma!E7/#REF! -> #REF! | F7: =+bma!F7/#REF! -> #REF! | G7: =+bma!G7/#REF! -> #REF! | H7: =+bma!H7/#REF! -> #REF! | I7: =+bma!I7/#REF! -> #REF! | J7: =+bma!L7/#REF! -> #REF! | K7: =+bma!M7/#REF! -> #REF! | L7: =+bma!J7/#REF! -> #REF! | M7: =+bma!K7/#REF! -> #REF! | N7: =+bma!N7/#REF! -> #REF! | O7: =+bma!O7/#REF! -> #REF! | P7: =+bma!P7/#REF! -> #REF! | Q7: =+bma!Q7/#REF! -> #REF! | R7: =+bma!R7/#REF! -> #REF! | S7: =+bma!S7/#REF! -> #REF!
A8: =+#REF! -> #REF! | B8: =+#REF! -> #REF! | C8: =+bma!C8/#REF! -> #REF! | D8: =+bma!D8/#REF! -> #REF! | E8: =+bma!E8/#REF! -> #REF! | F8: =+bma!F8/#REF! -> #REF! | G8: =+bma!G8/#REF! -> #REF! | H8: =+bma!H8/#REF! -> #REF! | I8: =+bma!I8/#REF! -> #REF! | J8: =+bma!L8/#REF! -> #REF! | K8: =+bma!M8/#REF! -> #REF! | L8: =+bma!J8/#REF! -> #REF! | M8: =+bma!K8/#REF! -> #REF! | N8: =+bma!N8/#REF! -> #REF! | O8: =+bma!O8/#REF! -> #REF! | P8: =+bma!P8/#REF! -> #REF! | Q8: =+bma!Q8/#REF! -> #REF! | R8: =+bma!R8/#REF! -> #REF! | S8: =+bma!S8/#REF! -> #REF!
A9: =+#REF! -> #REF! | B9: =+#REF! -> #REF! | C9: =+bma!C9/#REF! -> #REF! | D9: =+bma!D9/#REF! -> #REF! | E9: =+bma!E9/#REF! -> #REF! | F9: =+bma!F9/#REF! -> #REF! | G9: =+bma!G9/#REF! -> #REF! | H9: =+bma!H9/#REF! -> #REF! | I9: =+bma!I9/#REF! -> #REF! | J9: =+bma!L9/#REF! -> #REF! | K9: =+bma!M9/#REF! -> #REF! | L9: =+bma!J9/#REF! -> #REF! | M9: =+bma!K9/#REF! -> #REF! | N9: =+bma!N9/#REF! -> #REF! | O9: =+bma!O9/#REF! -> #REF! | P9: =+bma!P9/#REF! -> #REF! | Q9: =+bma!Q9/#REF! -> #REF! | R9: =+bma!R9/#REF! -> #REF! | S9: =+bma!S9/#REF! -> #REF!
A10: =+#REF! -> #REF! | B10: =+#REF! -> #REF! | C10: =+bma!C10/#REF! -> #REF! | D10: =+bma!D10/#REF! -> #REF! | E10: =+bma!E10/#REF! -> #REF! | F10: =+bma!F10/#REF! -> #REF! | G10: =+bma!G10/#REF! -> #REF! | H10: =+bma!H10/#REF! -> #REF! | I10: =+bma!I10/#REF! -> #REF! | J10: =+bma!L10/#REF! -> #REF! | K10: =+bma!M10/#REF! -> #REF! | L10: =+bma!J10/#REF! -> #REF! | M10: =+bma!K10/#REF! -> #REF! | N10: =+bma!N10/#REF! -> #REF! | O10: =+bma!O10/#REF! -> #REF! | P10: =+bma!P10/#REF! -> #REF! | Q10: =+bma!Q10/#REF! -> #REF! | R10: =+bma!R10/#REF! -> #REF! | S10: =+bma!S10/#REF! -> #REF!
A11: =+#REF! -> #REF! | B11: =+#REF! -> #REF! | C11: =+bma!C11/#REF! -> #REF! | D11: =+bma!D11/#REF! -> #REF! | E11: =+bma!E11/#REF! -> #REF! | F11: =+bma!F11/#REF! -> #REF! | G11: =+bma!G11/#REF! -> #REF! | H11: =+bma!H11/#REF! -> #REF! | I11: =+bma!I11/#REF! -> #REF! | J11: =+bma!L11/#REF! -> #REF! | K11: =+bma!M11/#REF! -> #REF! | L11: =+bma!J11/#REF! -> #REF! | M11: =+bma!K11/#REF! -> #REF! | N11: =+bma!N11/#REF! -> #REF! | O11: =+bma!O11/#REF! -> #REF! | P11: =+bma!P11/#REF! -> #REF! | Q11: =+bma!Q11/#REF! -> #REF! | R11: =+bma!R11/#REF! -> #REF! | S11: =+bma!S11/#REF! -> #REF!
A12: =+#REF! -> #REF! | B12: =+#REF! -> #REF! | C12: =+bma!C12/#REF! -> #REF! | D12: =+bma!D12/#REF! -> #REF! | E12: =+bma!E12/#REF! -> #REF! | F12: =+bma!F12/#REF! -> #REF! | G12: =+bma!G12/#REF! -> #REF! | H12: =+bma!H12/#REF! -> #REF! | I12: =+bma!I12/#REF! -> #REF! | J12: =+bma!L12/#REF! -> #REF! | K12: =+bma!M12/#REF! -> #REF! | L12: =+bma!J12/#REF! -> #REF! | M12: =+bma!K12/#REF! -> #REF! | N12: =+bma!N12/#REF! -> #REF! | O12: =+bma!O12/#REF! -> #REF! | P12: =+bma!P12/#REF! -> #REF! | Q12: =+bma!Q12/#REF! -> #REF! | R12: =+bma!R12/#REF! -> #REF! | S12: =+bma!S12/#REF! -> #REF!
A13: =+#REF! -> #REF! | B13: =+#REF! -> #REF! | C13: =+bma!C13/#REF! -> #REF! | D13: =+bma!D13/#REF! -> #REF! | E13: =+bma!E13/#REF! -> #REF! | F13: =+bma!F13/#REF! -> #REF! | G13: =+bma!G13/#REF! -> #REF! | H13: =+bma!H13/#REF! -> #REF! | I13: =+bma!I13/#REF! -> #REF! | J13: =+bma!L13/#REF! -> #REF! | K13: =+bma!M13/#REF! -> #REF! | L13: =+bma!J13/#REF! -> #REF! | M13: =+bma!K13/#REF! -> #REF! | N13: =+bma!N13/#REF! -> #REF! | O13: =+bma!O13/#REF! -> #REF! | P13: =+bma!P13/#REF! -> #REF! | Q13: =+bma!Q13/#REF! -> #REF! | R13: =+bma!R13/#REF! -> #REF! | S13: =+bma!S13/#REF! -> #REF!
... A443: =+#REF! -> #REF! | B443: =+#REF! -> #REF! | C443: =+bma!C443/#REF! -> #REF! | D443: =+bma!D443/#REF! -> #REF! | E443: =+bma!E443/#REF! -> #REF! | F443: =+bma!F443/#REF! -> #REF! | G443: =+bma!G443/#REF! -> #REF! | H443: =+bma!H443/#REF! -> #REF! | I443: =+bma!I443/#REF! -> #REF! | J443: =+bma!L443/#REF! -> #REF! | K443: =+bma!M443/#REF! -> #REF! | L443: =+bma!J443/#REF! -> #REF! | M443: =+bma!K443/#REF! -> #REF! | N443: =+bma!N443/#REF! -> #REF! | O443: =+bma!O443/#REF! -> #REF! | P443: =+bma!P443/#REF! -> #REF! | Q443: =+bma!Q443/#REF! -> #REF! | R443: =+bma!R443/#REF! -> #REF! | S443: =+bma!S443/#REF! -> #REF!

Sheet tab.study
B2: Study (year)
B3: =+"\cite{"&C20&"}" -> \cite{Agarwal1985} | C3: =+"\cite{"&C35&"}" -> \cite{Doyle1980} | D3: =+"\cite{"&C50&"}" -> \cite{Murphy1994}
B4: =+"\cite{"&C21&"}" -> \cite{Alexander1984} | C4: =+"\cite{"&C36&"}" -> \cite{Elliott2013} | D4: =+"\cite{"&C51&"}" -> \cite{Noorbakhsh2002}
B5: =+"\cite{"&C22&"}" -> \cite{Allen1999} | C5: =+"\cite{"&C37&"}" -> \cite{Grubb1988} | D5: =+"\cite{"&C52&"}" -> \cite{Ordovensky1995}
B6: =+"\cite{"&C23&"}" -> \cite{Berger2002} | C6: =+"\cite{"&C38&"}" -> \cite{Hemelt2011} | D6: =+"\cite{"&C53&"}" -> \cite{Parker1993}
B7: =+"\cite{"&C24&"}" -> \cite{Bezmen1998} | C7: =+"\cite{"&C39&"}" -> \cite{Hight1975} | D7: =+"\cite{"&C54&"}" -> \cite{Paulsen1988}
B8: =+"\cite{"&C25&"}" -> \cite{Bruckmeier2013} | C8: =+"\cite{"&C40&"}" -> \cite{Hoenack1990} | D8: =+"\cite{"&C55&"}" -> \cite{Quigley1993}
B9: =+"\cite{"&C26&"}" -> \cite{Buss2004} | C9: =+"\cite{"&C41&"}" -> \cite{Hoenack1975} | D9: =+"\cite{"&C56&"}" -> \cite{Quinn1998}
B10: =+"\cite{"&C27&"}" -> \cite{Campbell1967} | C10: =+"\cite{"&C42&"}" -> \cite{Hsing1996} | D10: =+"\cite{"&C57&"}" -> \cite{Savoca1990}
B11: =+"\cite{"&C28&"}" -> \cite{Canton2002} | C11: =+"\cite{"&C43&"}" -> \cite{Huijsman1986} | D11: =+"\cite{"&C58&"}" -> \cite{Shin2008}
B12: =+"\cite{"&C29&"}" -> \cite{Chen2016} | C12: =+"\cite{"&C44&"}" -> \cite{Kane2007} | D12: =+"\cite{"&C59&"}" -> \cite{Suloc1982}
B13: =+"\cite{"&C30&"}" -> \cite{Cheslock2001} | C13: =+"\cite{"&C45&"}" -> \cite{King1993} | D13: =+"\cite{"&C60&"}" -> \cite{Tannen1978}
B14: =+"\cite{"&C31&"}" -> \cite{Chressanthis1986} | C14: =+"\cite{"&C46&"}" -> \cite{Knudsen1978} | D14: =+"\cite{"&C61&"}" -> \cite{Toutkoushian1998}
B15: =+"\cite{"&C32&"}" -> \cite{Coelli2009} | C15: =+"\cite{"&C47&"}" -> \cite{Koshal1976} | D15: =+"\cite{"&C62&"}" -> \cite{Tuckman1970}
B16: =+"\cite{"&C33&"}" -> \cite{Craft2012} | C16: =+"\cite{"&C48&"}" -> \cite{McPherson1991}
B17: =+"\cite{"&C34&"}" -> \cite{Dearden2011} | C17: =+"\cite{"&C49&"}" -> \cite{Mueller2005}
A19: Included studies
A20: 1 | B20: Agarwal & Winkler (1985) | C20: Agarwal1985 | D20: Agarwal, V.B., Winkler, D.R., 1985. Foreign demand for United States higher education: a study of developing countries in the eastern hemisphere. Economic Development and Cultural Change, 33(3), 623-644.
A21: 2 | B21: Alexander & Frey (1984) | C21: Alexander1984 | D21: Alexander, E.R., DE Frey D.E., 1984. An econometric estimate of the demand for MBA enrollment. Economics of Education Review, 3(2), 97-103.
A22: 3 | B22: Allen & Shen (1999) | C22: Allen1999 | D22: Allen R.F., Shen J., 1999. Some new evidence of the character of competition among higher education institutions. Economics of Education Review, 18(4), 465-470.
A23: 4 | B23: Berger & Kostal (2002) | C23: Berger2002 | D23: Berger, M.C., Kostal, T., 2002. Financial resources, regulation, and enrollment in US public higher education. Economics of Education Review, 21(2), 101-110.
A24: 5 | B24: Bezmen & Depken (1998) | C24: Bezmen1998 | D24: Bezmen, T., Depken C.A., 1998. School characteristics and the demand for college. Economics of Education Review, 17(2), 205-210.
A25: 6 | B25: Bruckmeier et al. (2013) | C25: Bruckmeier2013 | D25: Bruckmeier, K., Fischer, G.B., Wigger, B.U., 2013. The willingness to pay for higher education: does the type of fee matter? Applied Economics Letters 20(13), 1279-1282.
A26: 7 | B26: Buss et al. (2004) | C26: Buss2004 | D26: Buss, C., Parker, J., Rivenburg, J., 2004.Cost, quality and enrollment demand at liberal arts colleges. Economics of Education Review, 23(1), 57-65.
A27: 8 | B27: Campbell & Siegel (1967) | C27: Campbell1967 | D27: Campbell, R., Siegel, B.N., 1967. The demand for higher education in the United States, 1919-1964. The American Economic Review, 57(3), 482-294.
A28: 9 | B28: Canton & de Jong (2002) | C28: Canton2002 | D28: Canton, E., de Jong, F., 2002. The Demand for Higher Education in the Netherlands, 1950-'99, Economics of Education Review, 24(6), 651-663.
A29: 10 | B29: Chen (2016) | C29: Chen2016 | D29: Chen S.J., 2016. College Costs, Freshman Enrollment, and Student Quality: Evidence from an Urban State University. International Journal of Information and Education, 6(9), 664-671.
A30: 11 | B30: Cheslock (2001) | C30: Cheslock2001 | D30: Cheslock, J.J., 2001. The Determinants of an Institution's Transfer Student Enrollment, Working paper 20/2001, Center for the Study of Higher Education at the University of Arizona.
A31: 12 | B31: Chressanthis (1986) | C31: Chressanthis1986 | D31: Chressanthis, G.A., 1986. The impacts of tuition rate changes on college undergraduate headcounts and credit hours over time: a case study, Economics of Education Review, 5(2), 205-217.
... A62: 43 | B62: Tuckman (1970) | C62: Tuckman1970 | D62: Tuckman, H.P., 1970. Determinants of college student migration. Southern Economic Journal, 37(2), 184-189.
A64: Excluded studies
A65: 1 | B65: Corman & Davidson (1984) | C65: Corman, H., Davidson, P.K., 1984. Economic Aspects of Post-secondary Schooling Decisions. Economics of Educonon Review, 3(2), 131-139.
A66: 2 | B66: Curs & Singell (2010) | C66: Curs B.R., Singell L.D., 2010. Aim High or Go Low? Pricing Strategies and Enrollment Effects when the Net Price Elasticity Varies with Need and Ability. The Journal of Higher Education, 81(4), 515-543.
A67: 3 | B67: Hemelt & Marcotte (2008) | C67: Hemelt, S.W., Marcotte, D.E. 2008. Rising tuition and enrollment in public higher education. IZA Discussion Paper 3827/2008, Institute for the Study of Labor, Bonn, Germany.
A68: 4 | B68: McDuff (2006) | C68: McDuff, DF., 2006. Quality, tuition, and applications to in-state public colleges. Economics of Education Review, 26(4), 433-449.
A69: 5 | B69: Neill (2009) | C69: Neill, C., 2009. Tuition fees and the demand for university places, Economics of Education Review, 28(5), 561-570.
